Workbook

Sheet README
A1: IDR Prep Studio v4 – Build Spec
A3: Version | B3: 4.0
A4: Date | B4: 2026-10-26
A5: Audience | B5: IT and software development, and the Studio admins (sheet "Configuration guide").
A6: Purpose | B6: Build spec for IDR Prep Studio v4. v4 moves configuration and access into the Sheet: every list on Options (with Key, Sort, Strict), a Fields tab merged into the schema, a Users tab with roles checked on the server, a BillingEntities tab, RCM Specialist (was Owner), and upload before saving.
A7: Reference | B7: This workbook matches the finished v4 code (idr-prep-studio/Code.gs and README.md). Field rows, Options and BillingEntities seed rows and tab columns are dumped from Code.gs by dump_code.js. Where spec-studio-v4.md and the code differ, the code wins.
A8: Source (portal rules) | B8: "IDR Gateway Notice of IDR Initiation User Guide, Version 15.0, October 14, 2026". Portal labels, option texts, format rules and messages are quoted from that guide. Sheet "Guide changes" maps each guide section to the Studio.
A9: Other sources | B9: spec-studio-v4.md (on top of v3 and v2). Seed lists from the business: 24 billing entities, 124 non-initiating parties (payers), 373 service codes. Trends and Observed lines: the 4 real notices used for v2 (DISP-7984427, DISP-7986216, DISP-7997846, DISP-7998956).
A10: Fixed business facts | B10: 1. We always initiate (provider or facility); plan/issuer paths are not built. 2. q_acting_as is "Health care provider" or "Health care facility" only. 3. Location of service is always TX (Fixed + Locked on the Fields tab).
A11: Timing count | B11: The ON start date is business day 1; b counts both days. Day 30 ends open negotiation; days 31–34 are the window; after 34 an extension reason is needed. Before day 31 a dispute can go to the US desk ("Not open yet"); Start portal entry and Mark as filed wait.
A12: Roles | B12: Admin, LB Member (Lebanon preparers), US Member (US desk). Only active rows on the Users tab can open the app; every server function checks the role. See "Roles & permissions".
A13: Configuration | B13: Admins change lists, fields, settings, users and billing entities in the app (Admin screens) or on the tabs. See "Configuration guide" for which tab and column to edit.
A14: Not the CMS portal | B14: The Studio never connects to the federal IDR portal or the IDR Gateway. The US desk copies values by hand. Keep the "not the CMS portal" banner.
... A18: How to use | B18: 1. Configuration guide: for admins, which tab and column to edit for each change.
B19: 2. Fields: every field as the Fields tab seeds it, with portal page, guide label, rules and notes. Rows marked "In Fields tab? No" are Studio-only (US desk tracking, derived or display).
B20: 3. Lists (Options seed, 637 rows), Payers, BillingEntities (tab seed) and ServiceCodes hold the seed data.
B21: 4. Validation rules, Workflow, Roles & permissions and Learning rules are the requirements. Cite the IDs.
B22: 5. Data model (all tabs and columns, Settings keys) and API (server functions) describe the build.
B23: 6. Backlog, Open questions and Guide changes. Trends and Observed lines show the 4 v2 notices.
A24: Formulas | B24: ServiceCodes (Times seen, QPA min and max) and Trends (Share) use formulas over Observed lines.
A25: Version legend | B25: v2, v3, v4 = the version that added the item; "(changed)" = changed in that version; Removed = dropped; Not built = shown by the portal but never applies to us.
A26: Dispute statuses | B26: Draft, Ready for US desk, Returned, Filed. IDRE selection is tracked in idre_final and idre_status. Ready disputes before business day 31 are grouped under "Not open yet".
A27: Orange cells | B27: A flag: a data-quality finding, a guess to confirm, or a value that needs a business answer.
A28: Grey rows | B28: Not built, Removed, Studio-only or answered rows.
A29: Sheets | B29: README, Configuration guide, Fields, Lists, Payers, BillingEntities, ServiceCodes, Trends, Observed lines, Learning rules, Validation rules, Workflow, Roles & permissions, Data model, API, Backlog, Open questions, Guide changes.

Sheet Configuration guide
A1: Area | B1: Change you want | C1: Where in the app | D1: Tab | E1: Column(s) | F1: How | G1: Takes effect | H1: Notes / limits
A2: People | B2: Add a member, or give access | C2: Admin -> Users | D2: Users | E2: Email, Name, Role, Team, Active | F2: Add a row (Active Yes). Role: Admin, LB Member or US Member. | G2: Within 2 minutes | H2: Never delete a row.
A3: People | B3: Change a role or team | C3: Admin -> Users | D3: Users | E3: Role, Team | F3: Edit the row. | G3: Within 2 minutes | H3: The last active Admin cannot be demoted.
A4: People | B4: Remove access | C4: Admin -> Users | D4: Users | E4: Active | F4: Set Active to No. | G4: Within 2 minutes | H4: Rows are never deleted (history).
A5: Lists | B5: Add a payer or IDR entity, or fix its contact | C5: Admin -> Lists (or let users learn it) | D5: Options | E5: List, Value, Data (JSON for payer address, email, phone, fax) | F5: Add or edit a row; Status Active. | G5: Within 10 minutes (or at once from the app) | H5: Payer names must use the portal name characters.
A6: Lists | B6: Hide a value, or merge a duplicate | C6: Admin -> Lists | D6: Options | E6: Status / merge | F6: Hide, or merge the learned value into the right one. | G6: At once | H6: Hidden values are never suggested.
A7: Lists | B7: CMS rewords a portal option | C7: Admin -> Lists | D7: Options | E7: Value (keep Key) | F7: Reword the Value. Never change the Key. | G7: At once | H7: Strict lists: HealthPlanType, PlanRole, ActingAs, ExtensionReason, ItemType, DisputeType, LineType, YesNo, BundledPayment, NipMethod, IdreStatus.
A8: Lists | B8: Change the order of a portal list | C8: Admin -> Lists | D8: Options | E8: Sort | F8: Set Sort numbers. | G8: At once
A9: Lists | B9: Add a service code description | C9: Admin -> Lists (or first save) | D9: Options | E9: Label (ServiceCode) | F9: Type the description. | G9: At once | H9: Code must be 5 letters or digits.
A10: Lists | B10: Add next year's holidays (each December) | C10: Sheet | D10: Options | E10: List Holiday, Value YYYY-MM-DD, Label | F10: Add one row per federal holiday. | G10: Within 10 minutes | H10: The timing rules use them.
A11: Lists | B11: Add a modifier, POS code or return reason | C11: Admin -> Lists (or learned) | D11: Options | E11: List, Value, Label | F11: Add a row. | G11: At once
A12: Billing entities | B12: Add or complete a billing entity | C12: Admin -> Billing entities | D12: BillingEntities | E12: Name, ActingAs, TIN, NPI, GroupName, Addr1, City, State, ZIP, Email, Phone, Fax | F12: Fill the columns; set Confirmed Yes once checked. | G12: At once | H12: Checks: TIN 9, NPI 10, ZIP, phone, email, portal characters.
A13: Billing entities | B13: Rename or record an old spelling | C13: Admin -> Billing entities | D13: BillingEntities | E13: Name, Aliases | F13: Rename (the old name goes into Aliases) or add to Aliases (semicolon list). | G13: At once
A14: Billing entities | B14: Hide an entity | C14: Admin -> Billing entities | D14: BillingEntities | E14: Status | F14: Hidden. | G14: At once
A15: Fields | B15: Change a label or help text | C15: Admin -> Settings & fields | D15: Fields | E15: Label, Help | F15: Edit the row. | G15: Within 10 minutes (at once from the app) | H15: Keep the portal wording for portal fields.
A16: Fields | B16: Make a field required or optional | C16: Admin -> Settings & fields | D16: Fields | E16: Required | F16: Yes or No. | G16: At once | H16: Rule fields (portal logic) cannot be changed.
A17: Fields | B17: Change a default | C17: Admin -> Settings & fields | D17: Fields | E17: Default, DefaultMode | F17: Fixed = always Default; Learned = most used recent value, else Default; None. Tokens @top, @me, @myteam. | G17: At once | H17: A default must be an option of its list.
A18: Fields | B18: Lock or hide a field, or change the order | C18: Admin -> Settings & fields | D18: Fields | E18: Locked, Visible, Order | F18: Edit the row. | G18: At once | H18: A required field cannot be hidden.
A19: Fields | B19: Change a format check or the copy order | C19: Sheet | D19: Fields | E19: Pattern, PatternMessage, CopyOrder | F19: Edit the row (regex for Pattern). | G19: Within 10 minutes | H19: An invalid pattern is ignored with a warning.
A20: Settings | B20: Learning on or off | C20: Admin -> Settings & fields | D20: Settings | E20: LearningMode | F20: On or Off. | G20: At once | H20: Off: new values wait as Hidden.
A21: Settings | B21: Learned default sensitivity | C21: Admin -> Settings & fields | D21: Settings | E21: DefaultWindow, DefaultShare | F21: Numbers (50; 0.8). | G21: At once
A22: Settings | B22: Complex State list | C22: Admin -> Settings & fields | D22: Settings | E22: ComplexStates | F22: Codes like TX, NM. | G22: At once | H22: Open question: is TX on the list?
A23: Settings | B23: File limits | C23: Admin -> Settings & fields | D23: Settings | E23: MaxFileMb, DisputeMaxMb | F23: At most 45 and 500. | G23: At once
A24: Settings | B24: Gateway banner and portal timer | C24: Admin -> Settings & fields | D24: Settings | E24: GatewayFrom, GatewayBannerUntil, PortalSessionMinutes, PortalWarnMinutes | F24: Dates YYYY-MM-DD; minutes. | G24: At once
A25: Settings | B25: Staged upload cleanup | C25: Admin -> Settings & fields; editor | D25: Settings | E25: StagingDays | F25: Days (1-90). Run installTriggers once for the daily cleanup. | G25: Next cleanup
A26: Do not edit by hand | B26: Dispute data | C26: - | D26: Disputes, LineItems, Files, Log | E26: - | F26: Use the app. Never edit Keys, DisputeIDs, FileIds or the Log. | G26: - | H26: Edits outside the app skip the checks and the Log.
A27: After a code update | B27: New fields or lists | C27: Editor | D27: all | E27: - | F27: Run setup (safe to run again). | G27: At once | H27: setup never changes existing Fields rows (Open questions Q29).

Sheet Fields
A1: Portal page | B1: Guide § | C1: Page (Fields tab) | D1: Section | E1: Order | F1: Key | G1: Label (Fields tab seed = Code.gs) | H1: Portal label (guide v15) | I1: Help | J1: Type | K1: List | L1: Required | M1: Default | N1: DefaultMode | O1: Locked | P1: Visible | Q1: Pattern | R1: PatternMessage | S1: CopyOrder | T1: Validation rule | U1: Auto-fill from | V1: Version | W1: Notes | X1: In Fields tab?
A2: Dispute header (Studio only) | B2: - | C2: internal | D2: Internal | E2: 1 | F2: Team | G2: Team | H2: (not on the portal) | J2: combo | K2: Team | L2: No | M2: @myteam | N2: Fixed | O2: No | P2: Yes | T2: Typo check (V31). | V2: v4 (changed) | W2: Learned on save; no seed. v4: searchable box with "Add new" (name characters). Default @myteam = the signed-in user's Team on the Users tab. New values join the Team list on save. | X2: Yes
A3: Dispute header (Studio only) | B3: - | C3: internal | D3: Internal | E3: 2 | F3: RcmSpecialist | G3: RCM Specialist | H3: (not on the portal) | J3: combo | K3: RcmSpecialist | L3: No | M3: @me | N3: Fixed | O3: No | P3: Yes | V3: v4 (changed) | W3: v4: was Owner. Searchable box with "Add new": suggestions = active Users (email or name) + the RcmSpecialist list; a new value must be a valid email and joins the list on save. Default @me = the signed-in LB Member's email. | X3: Yes
A4: 1 · Introduction & Qualification Questions | B4: 1.3 (2) | C4: qual | E4: 1 | F4: q_prior_2022 | G4: Was the service in question provided prior to 1/1/2022? | H4: *Was the service in question provided prior to 1/1/2022? | J4: radio | K4: YesNo | L4: Yes | M4: No | N4: Learned | O4: No | P4: Yes | T4: Yes or No. Yes = hard stop with the portal alert (V11). | V4: v2 | W4: Guide: if the plan renewal date for plan year 2022 is after the date of service, the dispute is not eligible. | X4: Yes
A5: 1 · Introduction & Qualification Questions | B5: 1.3 (3) | C5: qual | E5: 2 | F5: q_acting_as | G5: I am (or I am acting on behalf of) a: | H5: *I am (or I am acting on behalf of) a: | J5: radio | K5: ActingAs | L5: Yes | N5: None | O5: No | P5: Yes | T5: One of the 2 ActingAs values (V39). | U5: BillingEntity.acting_as | V5: v3 (changed) | W5: Portal shows 6 options; we only use "Health care provider" or "Health care facility" (fixed business fact). Locked chip filled from the billing entity; "guess from the name: check it" chip while BillingEntities Confirmed = No. | X5: Yes
A6: 1 · Introduction & Qualification Questions | B6: 1.3 (4a) | C6: qual | E6: 3 | F6: tin | G6: Tax ID: | H6: * Tax ID | J6: text | L6: Rule | N6: None | O6: No | P6: Yes | Q6: ^\d{9}$ | R6: must be 9 digits | T6: ^\d{9}$ when filled (V09). At least one of tin / npi (V38). | U6: BillingEntity.tin | V6: v3 (changed) | W6: Required depends on other answers (portal rule in code) Guide: "The initiating party must complete at least one of the two fields." TIN must be nine digits. | X6: Yes
A7: 1 · Introduction & Qualification Questions | B7: 1.3 (4b) | C7: qual | E7: 4 | F7: npi | G7: National Provider Identifier (NPI): | H7: * National Provider Identifier (NPI) | J7: text | L7: Rule | N7: None | O7: No | P7: Yes | Q7: ^\d{10}$ | R7: must be 10 digits | T7: ^\d{10}$ when filled (V10). At least one of tin / npi (V38). | U7: BillingEntity.npi | V7: v3 (changed) | W7: Required depends on other answers (portal rule in code) NPI must be ten digits. | X7: Yes
A8: 1 · Introduction & Qualification Questions | B8: 1.3 (5) | C8: qual | E8: 5 | F8: q_plan_type | G8: Health Plan Type: | H8: *Health Plan Type | I8: Not eligible if the member is only enrolled in coverage such as Medicare, Medicaid, CHIP, TRICARE or a health care sharing ministry. | J8: select | K8: HealthPlanType | L8: Yes | M8: Either partially or fully self-insured ERISA group health plan | N8: Learned | O8: No | P8: Yes | T8: One of the 7 HealthPlanType values, exact text (V40). Info warning under the field (V41). | V8: v3 (changed) | W8: Changed: combo to strict dropdown; no learning of new values. Usage counts still feed the learned default. "No Plan/Issuer Response" only shows to provider initiators (always us). | X8: Yes
A9: 1 · Introduction & Qualification Questions | B9: 1.3 (6) | C9: qual | E9: 6 | F9: fehb_enrollment_code | G9: Enrollment Code: | H9: *Enrollment Code | J9: text | L9: Rule | N9: None | O9: No | P9: Yes | Q9: ^\d{3}$ | R9: must be 3 digits | T9: ^\d{3}$; shown and required only when q_plan_type = "Federal Employees Health Benefits (FEHB) carrier" (V42). | V9: v3 | W9: Required depends on other answers (portal rule in code) Guide: "the three digit *Enrollment Code". | X9: Yes
A10: 1 · Introduction & Qualification Questions | B10: 1.3 (9) | C10: qual | E10: 7 | F10: on_start_date | G10: When did the open negotiation period start? | H10: *When did the open negotiation period start? | J10: date | L10: Yes | N10: None | O10: No | P10: Yes | T10: YYYY-MM-DD; not in the future (V08). Timing bands: b < 31 = notice on Ready, blocks US desk filing (V43); 31–34 window helper (V14); b > 34 needs extension_reason (V13). | V10: v3 (changed) | W10: Batched with several ON dates: enter the ON start date of the first claim in the batch (guide note). b = business days from on_start_date to today, both days counted (the start date is day 1; federal holidays from the Holiday list). | X10: Yes
A11: 1 · Introduction & Qualification Questions | B11: 1.3 (9) | C11: qual | E11: 8 | F11: on_evidence | G11: Upload evidence of the open negotiation period start date (for example, the notice or notices of open negotiation sent to the non-initiating party). | H11: (upload) evidence of the open negotiation period start date | I11: At least one file. In a batch with different open negotiation start dates, enter the first claim’s date above and upload a notice for each start date. | J11: file | L11: Yes | N11: None | O11: No | P11: Yes | T11: At least 1 file (V24); one per distinct ON start date in a batch (reminder, V24). Dispute total <= 500 MB (V60). | V11: v4 (changed) | W11: Category on_evidence. Example: the notice(s) of open negotiation sent to the non-initiating party. Names seen: "OMB <account>.pdf", "PROOF <account>.png", "<date> LLC NSA NEG LETTER C <account>.pdf". v4: can be attached before the dispute or line is saved (staging). | X11: Yes
A12: 1 · Introduction & Qualification Questions | B12: 1.3 (9b, 9c) | C12: qual | E12: 9 | F12: extension_reason | G12: Extension justification reason: | H12: (extension justification reasons, shown when the date is more than 34 business days before today) | J12: radio | K12: ExtensionReason | L12: Rule | N12: None | O12: No | P12: Yes | T12: One of the 2 ExtensionReason texts (V13). | V12: v3 | W12: Required depends on other answers (portal rule in code) Without a reason, Ready is blocked ("Deadline passed"). | X12: Yes
A13: 1 · Introduction & Qualification Questions | B13: 1.3 (9c i) | C13: qual | E13: 10 | F13: ext_approval | G13: Upload a copy of the extension approval received from the Federal IDR Questions mailbox. | H13: (Upload) copy of the extension approval received from the Federal IDR Questions mailbox | J13: file | L13: Rule | N13: None | O13: No | P13: Yes | T13: At least 1 file (V44). | V13: v4 (changed) | W13: Required depends on other answers (portal rule in code) File category extension. v4: can be attached before the dispute or line is saved (staging). | X13: Yes
A14: 1 · Introduction & Qualification Questions | B14: 1.3 (9c ii) | C14: qual | E14: 11 | F14: cooling_dispute_ref | G14: Dispute Reference Number: | H14: Dispute Reference Number | J14: text | L14: Rule | N14: None | O14: No | P14: Yes | Q14: ^DISP-\d+$ | R14: is not valid: use the DISP-XXXXXX format | T14: ^DISP-\d+$ (V45). Portal: "Enter the dispute reference number." when empty. | V14: v3 | W14: Required depends on other answers (portal rule in code) The dispute number that triggered the cooling off period (portal format "DISP-XXXXXX"). | X14: Yes
A15: 1 · Introduction & Qualification Questions | B15: 1.3 (9c ii) | C15: qual | E15: 12 | F15: cooling_docs | G15: Upload a copy of the payment determination(s) that initiated the cooling off period (all of them if cooling off periods overlap). | H15: (Upload) copy of the payment determination(s) that initiated the cooling off period | J15: file | L15: Rule | N15: None | O15: No | P15: Yes | T15: At least 1 file (V46). | V15: v4 (changed) | W15: Required depends on other answers (portal rule in code) All determinations if cooling off periods overlap. File category cooling. v4: can be attached before the dispute or line is saved (staging). | X15: Yes
A16: 1 · Introduction & Qualification Questions | B16: 1.3 (10) | C16: qual | E16: 13 | F16: consent_waiver | G16: Did the health care provider or health care facility get consent from the participant, beneficiary, or enrollee to waive surprise billing protections for these items or services? | H16: *Did the health care provider or health care facility get consent from the participant, beneficiary, or enrollee to waive surprise billing protections for these items or services? | J16: radio | K16: YesNo | L16: Yes | M16: No | N16: Learned | O16: No | P16: Yes | T16: Yes or No. Yes = hard stop (V12). | V16: v3 (changed) | W16: Label text changed in guide v15 (air ambulance wording dropped). | X16: Yes
A17: 2 · Dispute Type | B17: 1.4 (1) | C17: dtype | E17: 1 | F17: dispute_type | G17: What are you disputing today? | H17: *What are you disputing today? | J17: radio | K17: DisputeType | L17: Yes | M17: A batched dispute | N17: Learned | O17: No | P17: Yes | T17: One of the 2 DisputeType values (V62). | V17: v3 | W17: Portal option texts: "A single dispute. I’m disputing either (a) one service code that represents one item or service, or (b) one service code that represents multiple items or services (a bundled payment arrangement)."; "A batched dispute. I’m disputing multiple items or services related to the treatment of a similar condition.". Default batched (most used, learned). | X17: Yes
A18: 2 · Dispute Type | B18: 1.4 (1a) | C18: dtype | E18: 2 | F18: bundled_payment | G18: Are you disputing a bundled payment arrangement (multiple items or services billed or reimbursed under one service code)? | H18: Are you disputing a bundled payment arrangement (multiple items or services billed or reimbursed under one service code)? | J18: radio | K18: BundledPayment | L18: Rule | N18: None | O18: No | P18: Yes | T18: Yes or No (V62). | V18: v3 | W18: Required depends on other answers (portal rule in code) Shown only when dispute_type = A single dispute. | X18: Yes
A19: 2 · Dispute Type | B19: 1.4 (1b) | C19: dtype | E19: 3 | F19: batch_qualifies | G19: I reviewed the batching questions and this dispute qualifies | H19: Do your disputes qualify for the batching process? (Studio: "I reviewed the batching questions and this dispute qualifies") | I19: The portal asks "Do your disputes qualify for the batching process?" in a pop-up. Answer Yes there only when this is ticked. | J19: check | L19: Rule | N19: None | O19: No | P19: Yes | T19: Checked (V62). | V19: v3 | W19: Required depends on other answers (portal rule in code) Mirrors the portal pop-up. On the portal: No returns to single dispute; Yes continues. | X19: Yes
A20: 3 · Contact Information – Initiating party | B20: 1.5.1 (1a) | C20: init | D20: Name and Address Information | E20: 1 | F20: prov_name | G20: Health care provider name: | H20: *Health care provider name | J20: combo | K20: BillingEntity | L20: Yes | N20: Learned | O20: No | P20: Yes | T20: Name characters (V58); typo check (V31). | V20: v3 (changed) | W20: Billing entity combo at the top of the page: picking it fills q_acting_as, tin, npi, prov_group_name and the contact fields below (L06). Also the signature name. Billing entity: suggestions and auto-fill come from the BillingEntities tab (v4). | X20: Yes
A21: 3 · Contact Information – Initiating party | B21: 1.5.1 (1b) | C21: init | D21: Name and Address Information | E21: 2 | F21: prov_group_name | G21: Hospital, Health Care Facility or Group Name: | H21: *Hospital, Health Care Facility or Group Name | J21: text | L21: Yes | N21: None | O21: No | P21: Yes | T21: Required (V01); name characters (V58). | U21: BillingEntity.group_name | V21: v3 (changed) | W21: Changed: optional in v2, REQUIRED in v3. Only Capital Health, PLLC has a group name today. | X21: Yes
A22: 3 · Contact Information – Initiating party | B22: 1.5.1 (1) | C22: init | D22: Name and Address Information | E22: 3 | F22: prov_email | G22: Email: | H22: *Email | J22: email | L22: Yes | N22: None | O22: No | P22: Yes | T22: V04 | U22: BillingEntity.email | V22: v2 | W22: Organization handling the dispute. | X22: Yes
A23: 3 · Contact Information – Initiating party | B23: 1.5.1 (1) | C23: init | D23: Name and Address Information | E23: 4 | F23: prov_phone | G23: Phone: | H23: *Phone | J23: phone | L23: Yes | N23: None | O23: No | P23: Yes | T23: V03 | U23: BillingEntity.phone | V23: v2 | X23: Yes
A24: 3 · Contact Information – Initiating party | B24: 1.5.1 (1) | C24: init | D24: Name and Address Information | E24: 5 | F24: prov_fax | G24: Fax: | H24: Fax | J24: phone | L24: No | N24: None | O24: No | P24: Yes | T24: V03 | U24: BillingEntity.fax | V24: v2 | X24: Yes
A25: 3 · Contact Information – Initiating party | B25: 1.5.1 (1) | C25: init | D25: Name and Address Information | E25: 6 | F25: prov_addr1 | G25: Mailing Address: | H25: *Mailing Address | J25: text | L25: Yes | N25: None | O25: No | P25: Yes | T25: Address characters (V59). | U25: BillingEntity.addr1 | V25: v2 | X25: Yes
A26: 3 · Contact Information – Initiating party | B26: 1.5.1 (1) | C26: init | D26: Name and Address Information | E26: 7 | F26: prov_addr2 | G26: Mailing Address Line 2: | H26: Mailing Address Line 2 (Studio; not in the guide v15 list) | J26: text | L26: No | N26: None | O26: No | P26: Yes | T26: Address characters (V59). | U26: BillingEntity.addr2 | V26: v2 | W26: Kept from v2 (Code.gs mainContact_). Guide v15 lists one address line (Open questions Q26). | X26: Yes
A27: 3 · Contact Information – Initiating party | B27: 1.5.1 (1) | C27: init | D27: Name and Address Information | E27: 8 | F27: prov_city | G27: City: | H27: *City | J27: text | L27: Yes | N27: None | O27: No | P27: Yes | T27: Address characters (V59). | U27: BillingEntity.city | V27: v2 | X27: Yes
A28: 3 · Contact Information – Initiating party | B28: 1.5.1 (1) | C28: init | D28: Name and Address Information | E28: 9 | F28: prov_state | G28: State: | H28: *State | J28: select | K28: State | L28: Yes | M28: TX | N28: Learned | O28: No | P28: Yes | T28: Strict select from State (V32). | U28: BillingEntity.state | V28: v3 (changed) | W28: Default TX (fixed business fact). | X28: Yes
A29: 3 · Contact Information – Initiating party | B29: 1.5.1 (1) | C29: init | D29: Name and Address Information | E29: 10 | F29: prov_zip | G29: ZIP Code: | H29: *ZIP Code | J29: zip | L29: Yes | N29: None | O29: No | P29: Yes | T29: V02 | U29: BillingEntity.zip | V29: v2 | X29: Yes
A30: 3 · Contact Information – Initiating party | B30: 1.5.1 (2) | C30: init | D30: Primary point of contact if different from above: | E30: 1 | F30: prov_p1_name | G30: Primary Contact Name: | H30: Primary Contact Name | J30: text | L30: No | N30: None | O30: No | P30: Yes | T30: Name characters (V58). Full contact incl. mailing address required once a name is entered (V64). | V30: v3 (changed) | W30: Collapsed by default ("Add point of contact"). Empty on all 4 notices. Studio order: name, email, phone, address (Code.gs pocSection_); the guide lists phone/email in a slightly different order per section. | X30: Yes
A31: 3 · Contact Information – Initiating party | B31: 1.5.1 (2) | C31: init | D31: Primary point of contact if different from above: | E31: 2 | F31: prov_p1_email | G31: Email: | H31: Email | J31: email | L31: Rule | N31: None | O31: No | P31: Yes | T31: V04 Full contact incl. mailing address required once a name is entered (V64). | V31: v2 | W31: Required depends on other answers (portal rule in code) | X31: Yes
A32: 3 · Contact Information – Initiating party | B32: 1.5.1 (2) | C32: init | D32: Primary point of contact if different from above: | E32: 3 | F32: prov_p1_phone | G32: Phone: | H32: Phone | J32: phone | L32: Rule | N32: None | O32: No | P32: Yes | T32: V03 Full contact incl. mailing address required once a name is entered (V64). | V32: v2 | W32: Required depends on other answers (portal rule in code) | X32: Yes
A33: 3 · Contact Information – Initiating party | B33: 1.5.1 (2) | C33: init | D33: Primary point of contact if different from above: | E33: 4 | F33: prov_p1_addr1 | G33: Mailing Address: | H33: Mailing Address | J33: text | L33: Rule | N33: None | O33: No | P33: Yes | T33: Full contact incl. mailing address required once a name is entered (V64). | V33: v2 | W33: Required depends on other answers (portal rule in code) | X33: Yes
A34: 3 · Contact Information – Initiating party | B34: 1.5.1 (2) | C34: init | D34: Primary point of contact if different from above: | E34: 5 | F34: prov_p1_addr2 | G34: Mailing Address Line 2: | H34: Mailing Address Line 2 (Studio) | J34: text | L34: No | N34: None | O34: No | P34: Yes | T34: Full contact incl. mailing address required once a name is entered (V64). | V34: v2 | X34: Yes
A35: 3 · Contact Information – Initiating party | B35: 1.5.1 (2) | C35: init | D35: Primary point of contact if different from above: | E35: 6 | F35: prov_p1_city | G35: City: | H35: City | J35: text | L35: Rule | N35: None | O35: No | P35: Yes | T35: Full contact incl. mailing address required once a name is entered (V64). | V35: v2 | W35: Required depends on other answers (portal rule in code) | X35: Yes
A36: 3 · Contact Information – Initiating party | B36: 1.5.1 (2) | C36: init | D36: Primary point of contact if different from above: | E36: 7 | F36: prov_p1_state | G36: State: | H36: State | J36: select | K36: State | L36: Rule | N36: None | O36: No | P36: Yes | T36: Strict select from State (V32). Full contact incl. mailing address required once a name is entered (V64). | V36: v2 | W36: Required depends on other answers (portal rule in code) | X36: Yes
A37: 3 · Contact Information – Initiating party | B37: 1.5.1 (2) | C37: init | D37: Primary point of contact if different from above: | E37: 8 | F37: prov_p1_zip | G37: ZIP Code: | H37: ZIP Code | J37: zip | L37: Rule | N37: None | O37: No | P37: Yes | T37: V02 Full contact incl. mailing address required once a name is entered (V64). | V37: v2 | W37: Required depends on other answers (portal rule in code) | X37: Yes
A38: 3 · Contact Information – Initiating party | B38: 1.5.1 (3) | C38: init | D38: Secondary point of contact: (optional) | E38: 1 | F38: prov_p2_name | G38: Secondary Contact Name: | H38: Secondary Contact Name | J38: text | L38: No | N38: None | O38: No | P38: Yes | T38: Name characters (V58). Full contact incl. mailing address required once a name is entered (V64). | V38: v3 (changed) | W38: Collapsed by default ("Add point of contact"). Empty on all 4 notices. Studio order: name, email, phone, address (Code.gs pocSection_); the guide lists phone/email in a slightly different order per section. | X38: Yes
A39: 3 · Contact Information – Initiating party | B39: 1.5.1 (3) | C39: init | D39: Secondary point of contact: (optional) | E39: 2 | F39: prov_p2_email | G39: Email: | H39: Email | J39: email | L39: Rule | N39: None | O39: No | P39: Yes | T39: V04 Full contact incl. mailing address required once a name is entered (V64). | V39: v2 | W39: Required depends on other answers (portal rule in code) | X39: Yes
A40: 3 · Contact Information – Initiating party | B40: 1.5.1 (3) | C40: init | D40: Secondary point of contact: (optional) | E40: 3 | F40: prov_p2_phone | G40: Phone: | H40: Phone | J40: phone | L40: Rule | N40: None | O40: No | P40: Yes | T40: V03 Full contact incl. mailing address required once a name is entered (V64). | V40: v2 | W40: Required depends on other answers (portal rule in code) | X40: Yes
A41: 3 · Contact Information – Initiating party | B41: 1.5.1 (3) | C41: init | D41: Secondary point of contact: (optional) | E41: 4 | F41: prov_p2_addr1 | G41: Mailing Address: | H41: Mailing Address | J41: text | L41: Rule | N41: None | O41: No | P41: Yes | T41: Full contact incl. mailing address required once a name is entered (V64). | V41: v2 | W41: Required depends on other answers (portal rule in code) | X41: Yes
A42: 3 · Contact Information – Initiating party | B42: 1.5.1 (3) | C42: init | D42: Secondary point of contact: (optional) | E42: 5 | F42: prov_p2_addr2 | G42: Mailing Address Line 2: | H42: Mailing Address Line 2 (Studio) | J42: text | L42: No | N42: None | O42: No | P42: Yes | T42: Full contact incl. mailing address required once a name is entered (V64). | V42: v2 | X42: Yes
A43: 3 · Contact Information – Initiating party | B43: 1.5.1 (3) | C43: init | D43: Secondary point of contact: (optional) | E43: 6 | F43: prov_p2_city | G43: City: | H43: City | J43: text | L43: Rule | N43: None | O43: No | P43: Yes | T43: Full contact incl. mailing address required once a name is entered (V64). | V43: v2 | W43: Required depends on other answers (portal rule in code) | X43: Yes
A44: 3 · Contact Information – Initiating party | B44: 1.5.1 (3) | C44: init | D44: Secondary point of contact: (optional) | E44: 7 | F44: prov_p2_state | G44: State: | H44: State | J44: select | K44: State | L44: Rule | N44: None | O44: No | P44: Yes | T44: Strict select from State (V32). Full contact incl. mailing address required once a name is entered (V64). | V44: v2 | W44: Required depends on other answers (portal rule in code) | X44: Yes
A45: 3 · Contact Information – Initiating party | B45: 1.5.1 (3) | C45: init | D45: Secondary point of contact: (optional) | E45: 8 | F45: prov_p2_zip | G45: ZIP Code: | H45: ZIP Code | J45: zip | L45: Rule | N45: None | O45: No | P45: Yes | T45: V02 Full contact incl. mailing address required once a name is entered (V64). | V45: v2 | W45: Required depends on other answers (portal rule in code) | X45: Yes
A46: 4 · Contact Information – Non-initiating party | B46: 1.5.2 (1) | C46: noninit | D46: Insurance provider type | E46: 1 | F46: plan_role | G46: Select one of the insurance provider types below: | H46: *Select one of the insurance provider types below: | J46: radio | K46: PlanRole | L46: Yes | N46: None | O46: No | P46: Yes | T46: One of the 3 PlanRole values. | U46: q_plan_type | V46: v3 (changed) | W46: Auto-set, editable: "Individual health insurance issuer" -> Individual health insurance issuer; "Federal Employees Health Benefits (FEHB) carrier" -> Federal Employee Health Benefits (FEHB) carrier; all other plan types -> Group health plan. Note the portal spells "Employee" here and "Employees" in Health Plan Type. | X46: Yes
A47: 4 · Contact Information – Non-initiating party | B47: 1.5.2 (2a) | C47: noninit | D47: Name and Address Information | E47: 1 | F47: plan_name | G47: Health Insurance Plan or Company: | H47: *Health Insurance Plan or Company | J47: combo | K47: Payer | L47: Yes | N47: None | O47: No | P47: Yes | T47: Name characters (V58); typo check (V31). | V47: v3 (changed) | W47: The Payer list is the non-initiating party list. Picking a payer fills the fields below (L06). | X47: Yes
A48: 4 · Contact Information – Non-initiating party | B48: 1.5.2 (2) | C48: noninit | D48: Name and Address Information | E48: 2 | F48: plan_email | G48: Email: | H48: *Email | J48: email | L48: Yes | N48: None | O48: No | P48: Yes | T48: V04 | U48: Payer.email | V48: v2 | X48: Yes
A49: 4 · Contact Information – Non-initiating party | B49: 1.5.2 (2) | C49: noninit | D49: Name and Address Information | E49: 3 | F49: plan_phone | G49: Phone: | H49: *Phone | J49: phone | L49: Yes | N49: None | O49: No | P49: Yes | T49: V03 | U49: Payer.phone | V49: v2 | X49: Yes
A50: 4 · Contact Information – Non-initiating party | B50: 1.5.2 (2) | C50: noninit | D50: Name and Address Information | E50: 4 | F50: plan_fax | G50: Fax: | H50: Fax | J50: phone | L50: No | N50: None | O50: No | P50: Yes | T50: V03 | U50: Payer.fax | V50: v2 | W50: Blank on all 4 notices. | X50: Yes
A51: 4 · Contact Information – Non-initiating party | B51: 1.5.2 (2) | C51: noninit | D51: Name and Address Information | E51: 5 | F51: plan_addr1 | G51: Mailing Address: | H51: *Mailing Address | J51: text | L51: Yes | N51: None | O51: No | P51: Yes | T51: Address characters (V59). | U51: Payer.addr1 | V51: v2 | X51: Yes
A52: 4 · Contact Information – Non-initiating party | B52: 1.5.2 (2) | C52: noninit | D52: Name and Address Information | E52: 6 | F52: plan_addr2 | G52: Mailing Address Line 2: | H52: Mailing Address Line 2 (Studio; not in the guide v15 list) | J52: text | L52: No | N52: None | O52: No | P52: Yes | T52: Address characters (V59). | U52: Payer.addr2 | V52: v2 | W52: Kept from v2 (Code.gs mainContact_). Guide v15 lists one address line (Open questions Q26). | X52: Yes
A53: 4 · Contact Information – Non-initiating party | B53: 1.5.2 (2) | C53: noninit | D53: Name and Address Information | E53: 7 | F53: plan_city | G53: City: | H53: *City | J53: text | L53: Yes | N53: None | O53: No | P53: Yes | T53: Address characters (V59). | U53: Payer.city | V53: v2 | X53: Yes
A54: 4 · Contact Information – Non-initiating party | B54: 1.5.2 (2) | C54: noninit | D54: Name and Address Information | E54: 8 | F54: plan_state | G54: State: | H54: *State | J54: select | K54: State | L54: Yes | N54: None | O54: No | P54: Yes | T54: Strict select from State (V32). | U54: Payer.state | V54: v2 | X54: Yes
A55: 4 · Contact Information – Non-initiating party | B55: 1.5.2 (2) | C55: noninit | D55: Name and Address Information | E55: 9 | F55: plan_zip | G55: ZIP Code: | H55: *ZIP Code | J55: zip | L55: Yes | N55: None | O55: No | P55: Yes | T55: V02 | U55: Payer.zip | V55: v2 | X55: Yes
A56: 4 · Contact Information – Non-initiating party | B56: 1.5.2 (3) | C56: noninit | D56: Primary point of contact if different from above: | E56: 1 | F56: plan_p1_name | G56: Primary Contact Name: | H56: Primary Contact Name | J56: text | L56: No | N56: None | O56: No | P56: Yes | T56: Name characters (V58). Full contact incl. mailing address required once a name is entered (V64). | V56: v3 (changed) | W56: Collapsed by default ("Add point of contact"). Empty on all 4 notices. Studio order: name, email, phone, address (Code.gs pocSection_); the guide lists phone/email in a slightly different order per section. | X56: Yes
A57: 4 · Contact Information – Non-initiating party | B57: 1.5.2 (3) | C57: noninit | D57: Primary point of contact if different from above: | E57: 2 | F57: plan_p1_email | G57: Email: | H57: Email | J57: email | L57: Rule | N57: None | O57: No | P57: Yes | T57: V04 Full contact incl. mailing address required once a name is entered (V64). | V57: v2 | W57: Required depends on other answers (portal rule in code) | X57: Yes
A58: 4 · Contact Information – Non-initiating party | B58: 1.5.2 (3) | C58: noninit | D58: Primary point of contact if different from above: | E58: 3 | F58: plan_p1_phone | G58: Phone: | H58: Phone | J58: phone | L58: Rule | N58: None | O58: No | P58: Yes | T58: V03 Full contact incl. mailing address required once a name is entered (V64). | V58: v2 | W58: Required depends on other answers (portal rule in code) | X58: Yes
A59: 4 · Contact Information – Non-initiating party | B59: 1.5.2 (3) | C59: noninit | D59: Primary point of contact if different from above: | E59: 4 | F59: plan_p1_addr1 | G59: Mailing Address: | H59: Mailing Address | J59: text | L59: Rule | N59: None | O59: No | P59: Yes | T59: Full contact incl. mailing address required once a name is entered (V64). | V59: v2 | W59: Required depends on other answers (portal rule in code) | X59: Yes
A60: 4 · Contact Information – Non-initiating party | B60: 1.5.2 (3) | C60: noninit | D60: Primary point of contact if different from above: | E60: 5 | F60: plan_p1_addr2 | G60: Mailing Address Line 2: | H60: Mailing Address Line 2 (Studio) | J60: text | L60: No | N60: None | O60: No | P60: Yes | T60: Full contact incl. mailing address required once a name is entered (V64). | V60: v2 | X60: Yes
A61: 4 · Contact Information – Non-initiating party | B61: 1.5.2 (3) | C61: noninit | D61: Primary point of contact if different from above: | E61: 6 | F61: plan_p1_city | G61: City: | H61: City | J61: text | L61: Rule | N61: None | O61: No | P61: Yes | T61: Full contact incl. mailing address required once a name is entered (V64). | V61: v2 | W61: Required depends on other answers (portal rule in code) | X61: Yes
A62: 4 · Contact Information – Non-initiating party | B62: 1.5.2 (3) | C62: noninit | D62: Primary point of contact if different from above: | E62: 7 | F62: plan_p1_state | G62: State: | H62: State | J62: select | K62: State | L62: Rule | N62: None | O62: No | P62: Yes | T62: Strict select from State (V32). Full contact incl. mailing address required once a name is entered (V64). | V62: v2 | W62: Required depends on other answers (portal rule in code) | X62: Yes
A63: 4 · Contact Information – Non-initiating party | B63: 1.5.2 (3) | C63: noninit | D63: Primary point of contact if different from above: | E63: 8 | F63: plan_p1_zip | G63: ZIP Code: | H63: ZIP Code | J63: zip | L63: Rule | N63: None | O63: No | P63: Yes | T63: V02 Full contact incl. mailing address required once a name is entered (V64). | V63: v2 | W63: Required depends on other answers (portal rule in code) | X63: Yes
A64: 4 · Contact Information – Non-initiating party | B64: 1.5.2 (4) | C64: noninit | D64: Secondary point of contact: (optional) | E64: 1 | F64: plan_p2_name | G64: Secondary Contact Name: | H64: Secondary Contact Name | J64: text | L64: No | N64: None | O64: No | P64: Yes | T64: Name characters (V58). Full contact incl. mailing address required once a name is entered (V64). | V64: v3 (changed) | W64: Collapsed by default ("Add point of contact"). Empty on all 4 notices. Studio order: name, email, phone, address (Code.gs pocSection_); the guide lists phone/email in a slightly different order per section. | X64: Yes
A65: 4 · Contact Information – Non-initiating party | B65: 1.5.2 (4) | C65: noninit | D65: Secondary point of contact: (optional) | E65: 2 | F65: plan_p2_email | G65: Email: | H65: Email | J65: email | L65: Rule | N65: None | O65: No | P65: Yes | T65: V04 Full contact incl. mailing address required once a name is entered (V64). | V65: v2 | W65: Required depends on other answers (portal rule in code) | X65: Yes
A66: 4 · Contact Information – Non-initiating party | B66: 1.5.2 (4) | C66: noninit | D66: Secondary point of contact: (optional) | E66: 3 | F66: plan_p2_phone | G66: Phone: | H66: Phone | J66: phone | L66: Rule | N66: None | O66: No | P66: Yes | T66: V03 Full contact incl. mailing address required once a name is entered (V64). | V66: v2 | W66: Required depends on other answers (portal rule in code) | X66: Yes
A67: 4 · Contact Information – Non-initiating party | B67: 1.5.2 (4) | C67: noninit | D67: Secondary point of contact: (optional) | E67: 4 | F67: plan_p2_addr1 | G67: Mailing Address: | H67: Mailing Address | J67: text | L67: Rule | N67: None | O67: No | P67: Yes | T67: Full contact incl. mailing address required once a name is entered (V64). | V67: v2 | W67: Required depends on other answers (portal rule in code) | X67: Yes
A68: 4 · Contact Information – Non-initiating party | B68: 1.5.2 (4) | C68: noninit | D68: Secondary point of contact: (optional) | E68: 5 | F68: plan_p2_addr2 | G68: Mailing Address Line 2: | H68: Mailing Address Line 2 (Studio) | J68: text | L68: No | N68: None | O68: No | P68: Yes | T68: Full contact incl. mailing address required once a name is entered (V64). | V68: v2 | X68: Yes
A69: 4 · Contact Information – Non-initiating party | B69: 1.5.2 (4) | C69: noninit | D69: Secondary point of contact: (optional) | E69: 6 | F69: plan_p2_city | G69: City: | H69: City | J69: text | L69: Rule | N69: None | O69: No | P69: Yes | T69: Full contact incl. mailing address required once a name is entered (V64). | V69: v2 | W69: Required depends on other answers (portal rule in code) | X69: Yes
A70: 4 · Contact Information – Non-initiating party | B70: 1.5.2 (4) | C70: noninit | D70: Secondary point of contact: (optional) | E70: 7 | F70: plan_p2_state | G70: State: | H70: State | J70: select | K70: State | L70: Rule | N70: None | O70: No | P70: Yes | T70: Strict select from State (V32). Full contact incl. mailing address required once a name is entered (V64). | V70: v2 | W70: Required depends on other answers (portal rule in code) | X70: Yes
A71: 4 · Contact Information – Non-initiating party | B71: 1.5.2 (4) | C71: noninit | D71: Secondary point of contact: (optional) | E71: 8 | F71: plan_p2_zip | G71: ZIP Code: | H71: ZIP Code | J71: zip | L71: Rule | N71: None | O71: No | P71: Yes | T71: V02 Full contact incl. mailing address required once a name is entered (V64). | V71: v2 | W71: Required depends on other answers (portal rule in code) | X71: Yes
A72: 5 · Dispute Line Items | B72: 1.6.1.1 (1) | C72: lines | D72: New Line Item | E72: 1 | F72: description | G72: Enter the description of the item or service. | H72: Enter the description of the item or service. | J72: textarea | L72: Yes | N72: None | O72: No | P72: Yes | S72: 1 | T72: Required (V19). | U72: ServiceCode.label | V72: v2 | W72: Summary table column 1. | X72: Yes
A73: 5 · Dispute Line Items | B73: 1.6.1.1 (2) | C73: lines | D73: New Line Item | E73: 2 | F73: claim_number | G73: Claim Number: | H73: Claim Number | J73: text | L73: Yes | N73: None | O73: No | P73: Yes | Q73: ^[A-Za-z0-9]{1,40}$ | R73: must be up to 40 letters and digits (no spaces or symbols) | S73: 2 | T73: ^[A-Za-z0-9]{1,40}$ (V48). Duplicate rules V56, V57. | U73: Previous line | V73: v3 (changed) | W73: Up to 40 characters, alphanumeric (guide). | X73: Yes
A74: 5 · Dispute Line Items | B74: 1.6.1.1 (3) | C74: lines | D74: New Line Item | E74: 3 | F74: service_date | G74: Date of the qualified IDR item or service: | H74: Date of the qualified IDR item or service | J74: date | L74: Yes | N74: None | O74: No | P74: Yes | S74: 4 | T74: YYYY-MM-DD; on or after 2022-01-01 (V07); strictly before on_start_date (V47); batch spread (V37). | U74: Previous line | V74: v3 (changed) | W74: Portal: calendar icon. | X74: Yes
A75: 5 · Dispute Line Items | B75: 1.6.1.1 (4) | C75: lines | D75: New Line Item | E75: 4 | F75: qpa | G75: Qualifying Payment Amount (QPA): | H75: *QPA | J75: money | L75: Yes | N75: None | O75: No | P75: Yes | S75: 5 | T75: V05; warn if 0 (V18). | V75: v2 | W75: Summary table: "Qualifying Payment Amount (QPA)". | X75: Yes
A76: 5 · Dispute Line Items | B76: 1.6.1.1 (5) | C76: lines | D76: New Line Item | E76: 5 | F76: cost_sharing | G76: Cost sharing amount allowed: | H76: *Cost sharing amount allowed | J76: money | L76: Yes | N76: None | O76: No | P76: Yes | S76: 10 | T76: V05; required (V19); warn if above QPA (V16). | V76: v3 (changed) | W76: Changed: now required (portal marks it *). | X76: Yes
A77: 5 · Dispute Line Items | B77: 1.6.1.1 (6) | C77: lines | D77: New Line Item | E77: 6 | F77: initial_payment | G77: Initial payment amount for the item(s) and/or service(s) (if applicable): | H77: Initial payment amount for the item(s) and/or service(s) (if applicable) | J77: money | L77: No | N77: None | O77: No | P77: Yes | S77: 11 | T77: V05; warn if cost sharing + initial is not QPA (V17). | U77: Computed | V77: v2 | X77: Yes
A78: 5 · Dispute Line Items | B78: 1.6.1.1 (7) | C78: lines | D78: Item(s) or service(s) under dispute | E78: 1 | F78: item_types | G78: Select the item(s) or service(s) under dispute. | H78: (checkboxes) item(s) or service(s) under dispute | J78: checkboxes | K78: ItemType | L78: Yes | M78: Emergency item(s)/service(s) | N78: Learned | O78: No | P78: Yes | S78: 12 | T78: At least one. | U78: Previous line | V78: v3 (changed) | W78: More than one allowed. "Out-of-network air ambulance service(s)" removed (never applies to us). | X78: Yes
A79: 5 · Dispute Line Items | B79: 1.6.1.1 (7g) | C79: lines | D79: Item(s) or service(s) under dispute | E79: 2 | F79: other_desc | G79: Other: Provide description | H79: Other: Provide description | J79: text | L79: Rule | N79: None | O79: No | P79: Yes | S79: 13 | T79: Required when item_types includes Other (V25). | V79: v2 | W79: Required depends on other answers (portal rule in code) | X79: Yes
A80: 5 · Dispute Line Items | B80: 1.6.1.1 (8a) | C80: lines | D80: Service codes | E80: 1 | F80: service_code | G80: Service Code: | H80: *Service Code (five-character code) | J80: combo | K80: ServiceCode | L80: Yes | N80: None | O80: No | P80: Yes | Q80: ^[A-Za-z0-9]{5}$ | R80: must be exactly 5 letters or digits | S80: 7 | T80: ^[A-Za-z0-9]{5}$ (V49); typo check (V31). | V80: v3 (changed) | W80: Picking a code fills description when the code has a label. | X80: Yes
A81: 5 · Dispute Line Items | B81: 1.6.1.1 (8b) | C81: lines | D81: Service codes | E81: 2 | F81: modifiers | G81: Service Code Modifier(s): | H81: Service Code Modifier(s) | J81: combo | K81: Modifier | L81: No | N81: Learned | O81: No | P81: Yes | S81: 8 | T81: 0–4 codes, each ^[A-Za-z0-9]{2}$; stored and copied "; "-separated (V50). | V81: v3 (changed) | W81: Portal separates several modifiers with a semicolon automatically. | X81: Yes
A82: 5 · Dispute Line Items | B82: 1.6.1.1 (8c) | C82: lines | D82: Service codes | E82: 3 | F82: pos_code | G82: Place of Service Code: | H82: *Place of Service Code (two digits) | J82: combo | K82: PosCode | L82: Yes | M82: 23 | N82: Learned | O82: No | P82: Yes | Q82: ^\d{2}$ | R82: must be 2 digits | S82: 9 | T82: ^\d{2}$ (V51). | U82: Previous line | V82: v3 (changed) | X82: Yes
A83: 5 · Dispute Line Items | B83: 1.6.1.1 (8d) | C83: lines | D83: Service codes | E83: 4 | F83: location | G83: Location of Service: | H83: *Location of Service (state) | J83: select | K83: State | L83: Yes | M83: TX | N83: Fixed | O83: Yes | P83: Yes | S83: 6 | T83: Always TX (V32). | U83: Fixed | V83: v3 (changed) | W83: Fixed business fact. Read-only; still copied to the portal. Fixed + Locked on the Fields tab: always stored as TX. | X83: Yes
A84: 5 · Dispute Line Items | B84: 1.6.1.1 (9) | C84: lines | D84: Documentation | E84: 1 | F84: qpa_docs | G84: Upload documentation of the claim and QPA (for example, the initial payment or notice of denial of payment, remittance form and explanation of benefits, explanation of payments). | H84: (Upload) documentation of the claim and QPA | J84: file | L84: Yes | N84: None | O84: No | P84: Yes | S84: 14 | T84: At least 1 per line (V23); a file marked "use for all lines with this claim number" counts. Dispute total <= 500 MB (V60). | U84: Previous line | V84: v4 (changed) | W84: Examples: initial payment or notice of denial of payment, remittance and EOB, EOP. Category qpa. Names seen: "EOB <account>.pdf", "<date> LLC EOB C <account>.pdf". v4: can be attached before the dispute or line is saved (staging). | X84: Yes
A85: 5 · Dispute Line Items | B85: 1.6.1.1 (10) | C85: lines | D85: Documentation | E85: 2 | F85: state_attest | G85: I have reviewed the state-specific eligibility criteria regarding the IDR processes for this item or service, and attest that this item or service is eligible for the Federal IDR process. | H85: *I have reviewed the state-specific eligibility criteria regarding the IDR processes for this item or service, and attest that this item or service is eligible for the Federal IDR process. | J85: check | L85: Rule | N85: None | O85: No | P85: Yes | S85: 15 | T85: Required when location is in Settings.ComplexStates (V61). | V85: v3 | W85: Required depends on other answers (portal rule in code) ComplexStates default empty. Open question: is TX on the CMS Complex State list? | X85: Yes
A86: 6 · Preferred Certified IDR Entity & Conflict of Interest | B86: 1.7.1 | C86: final | D86: Preferred Certified IDR Entity Selection | E86: 1 | F86: idr_entity | G86: IDRE legal business name: | H86: *IDRE legal business name | J86: combo | K86: IdrEntity | L86: Yes | M86: @top | N86: Learned | O86: No | P86: Yes | T86: Required (V26); typo check (V31). | V86: v3 (changed) | W86: Portal: dropdown. Default @top = the most used value of the IdrEntity list. | X86: Yes
A87: 6 · Preferred Certified IDR Entity & Conflict of Interest | B87: 1.7.2 (1) | C87: final | D87: Conflict of Interest Attestation | E87: 1 | F87: third_party_attest | G87: Is the undersigned individual below a third-party administrator or other service provider initiating on behalf of the plan, issuer, carrier, or Health Care Provider/Health Care Facility/Provider of Air Ambulance Services? | H87: Is the undersigned individual below a third-party administrator or other service provider initiating on behalf of the plan, issuer, carrier, or Health Care Provider/Health Care Facility/Provider of Air Ambulance Services? | J87: radio | K87: YesNo | L87: Yes | M87: No | N87: Learned | O87: No | P87: Yes | T87: Yes or No (V27). | V87: v3 (changed) | W87: Exact portal question (label changed from v2 "Third Party Attestation:"). | X87: Yes
A88: 6 · Preferred Certified IDR Entity & Conflict of Interest | B88: 1.7.2 (2) | C88: final | D88: Conflict of Interest Attestation | E88: 2 | F88: coi_attest | G88: I (We), the undersigned initiating party (or representative of the initiating party), attest that to the best of my knowledge the preferred certified IDR entity does not have a disqualifying conflict of interest and that the item(s) and/or service(s) at issue are qualified IDR item(s) and/or service(s) within the scope of the Federal IDR process. | H88: *I (We), the undersigned initiating party (or representative of the initiating party), attest that to the best of my knowledge the preferred certified IDR entity does not have a disqualifying conflict of interest and that the item(s) and/or service(s) at issue are qualified IDR item(s) and/or service(s) within the scope of the Federal IDR process. | J88: check | L88: Yes | N88: None | O88: No | P88: Yes | T88: Must be checked (V63). | V88: v3 | W88: Portal statement. | X88: Yes
A89: 6 · Preferred Certified IDR Entity & Conflict of Interest | B89: 1.7.3 | C89: final | D89: Additional Supporting Documentation | E89: 1 | F89: additional_docs | G89: Upload any additional supporting documentation that is relevant to the dispute. | H89: (Upload) additional supporting documentation | J89: file | L89: No | N89: None | O89: No | P89: Yes | T89: Under 45 MB per file (V35); dispute total <= 500 MB (V60). | V89: v4 (changed) | W89: Category additional. Name seen: "UB04 Form C-<account>.pdf" (1/4). v4: can be attached before the dispute or line is saved (staging). | X89: Yes
A90: 1 · Introduction & Qualification Questions | B90: 1.3 (7) | C90: - | D90: Qualification Questions | F90: (none) | H90: *Has the self-insured plan opted into any specified state laws that would apply to the items and services in this dispute? | J90: radio | L90: n/a | V90: Not built | W90: Plan/issuer initiators only. Not built (we always initiate as provider or facility). | X90: No
A91: 1 · Introduction & Qualification Questions | B91: 1.3 (8) | C91: - | D91: Qualification Questions | F91: (none) | H91: *Is the health plan fully or self-insured? | J91: radio | L91: n/a | V91: Not built | W91: Church plan / non-federal governmental plan, plan/issuer initiators only. Not built. | X91: No
A92: 2 · Dispute Type | B92: 1.6.1 | C92: - | D92: Dispute Type | F92: dispute_kind | H92: (derived) Single Line Item – Not Bundled | Single Line Item – Bundled | Batched Items or Services | J92: derived | K92: DisputeKind (fixed, 3) | L92: Auto | T92: Computed from dispute_type + bundled_payment. Drives line rules V52–V55. | U92: dispute_type, bundled_payment | V92: v3 (changed) | W92: Changed values. Migration: "Single dispute" -> single + bundled No; "A batched dispute" -> batched; "A bundled dispute" -> single + bundled Yes. | X92: No
A93: 5 · Dispute Line Items | B93: 1.6.1.2 | C93: - | D93: New Line Item | F93: line_type | H93: *Item or Service Type (grayed out) | J93: display (read-only column) | K93: LineType (fixed, 2) | L93: Auto (bundled) | S93: 3 | T93: Line 1 = "Bundled Item or Service"; lines 2+ = "Component Item or Service" (V53). | U93: Line number | V93: v3 | W93: Only for Single Line Item – Bundled. Derived on read (not stored). The portal grays it out; the copy desk shows it in the summary-table position. Copy order 3 in the line copy desk (Code.gs deskOrder). | X93: No
A94: 5 · Dispute Line Items | B94: 1.6.3 | C94: - | D94: Summary of Qualified Items and/or Services | F94: (display) | H94: (table) Description, Claim Number, [Line Item Type], Date of Item or Service, QPA, Location of Service, Service Code, Service Code Modifier(s), Place of Service Code(s), Actions | J94: grid | L94: n/a | T94: Each row validated on paste (bulk paste, B44). | V94: v3 | W94: Studio line grid mirrors this table. Copy-desk order for lines follows these columns. | X94: No
A95: 6 · Preferred Certified IDR Entity & Conflict of Interest | B95: 1.7.2 (3) | C95: - | D95: Conflict of Interest Attestation | F95: (display only) | H95: *Initiating party | J95: display (locked chip) | L95: n/a | M95: Portal fills | U95: prov_name | V95: v3 (changed) | W95: Auto-populated by the portal, cannot be changed. Studio shows prov_name. | X95: No
A96: 6 · Preferred Certified IDR Entity & Conflict of Interest | B96: 1.7.2 (3) | C96: - | D96: Conflict of Interest Attestation | F96: (display only) | H96: *Date | J96: display (locked chip) | L96: n/a | M96: Portal fills | V96: v2 | W96: Auto-populated by the portal (initiation date). Not stored. | X96: No
A97: 7 · Review & Submit | B97: 1.8 | C97: - | D97: Review & Submit | F97: (display) | H97: (Studio summary of every page + confirmation PDF) | J97: summary | L97: n/a | T97: All blocking rules pass (finalizeDispute). | V97: v3 (changed) | W97: Portal: changing the dispute type on the portal means re-entering all line items. Then the US desk files. | X97: No
A98: US copy desk (Studio only) | B98: 1.1 | C98: - | D98: Copy desk | F98: (client only) | H98: (Start portal entry – 60-minute timer) | J98: button + timer | L98: n/a | T98: Blocked before business day 31 (V43). | V98: v3 | W98: "Start only when you can finish this dispute in one sitting." Warning at 50 minutes. | X98: No
A99: US copy desk (Studio only) | B99: 1.9 | C99: - | D99: Mark as filed | F99: PortalDisputeNumber | H99: Dispute Reference Number (portal) | J99: text | L99: Yes (to file) | T99: ^DISP-\d+$ (V28). | V99: v3 (changed) | W99: Changed: v2 used ^DISP-\d{7}$. | X99: No
A100: US copy desk (Studio only) | B100: 1.9 (1) | C100: - | D100: Mark as filed | F100: PortalPdfUrl | H100: Notice of IDR Initiation PDF (portal "Save as PDF") | J100: file | L100: Yes (to file) | T100: V29. | V100: v3 (changed) | W100: Category portal_confirmation. | X100: No
...

Sheet Lists
A1: List | B1: Key | C1: Value | D1: Label | E1: Data JSON | F1: Count (seed) | G1: Source | H1: Status | I1: Sort | J1: Strict | K1: Flag / note
A2: State | C2: AL | F2: 0 | G2: seed | H2: Active
A3: State | C3: AK | F3: 0 | G3: seed | H3: Active
A4: State | C4: AZ | F4: 0 | G4: seed | H4: Active
A5: State | C5: AR | F5: 0 | G5: seed | H5: Active
A6: State | C6: CA | F6: 0 | G6: seed | H6: Active
A7: State | C7: CO | F7: 0 | G7: seed | H7: Active
A8: State | C8: CT | F8: 0 | G8: seed | H8: Active
A9: State | C9: DE | F9: 0 | G9: seed | H9: Active
A10: State | C10: DC | F10: 0 | G10: seed | H10: Active
A11: State | C11: FL | F11: 0 | G11: seed | H11: Active
A12: State | C12: GA | F12: 0 | G12: seed | H12: Active
A13: State | C13: HI | F13: 0 | G13: seed | H13: Active
... A57: State | C57: VI | F57: 0 | G57: seed | H57: Active
A58: YesNo | B58: yes | C58: Yes | F58: 0 | G58: seed | H58: Active | I58: 1 | J58: Yes | K58: Strict: portal wording, never learns. Rewording keeps the Key; the rules use the Key.
A59: YesNo | B59: no | C59: No | F59: 0 | G59: seed | H59: Active | I59: 2 | J59: Yes | K59: Strict: portal wording, never learns. Rewording keeps the Key; the rules use the Key.
A60: BundledPayment | B60: yes | C60: Yes | F60: 0 | G60: seed | H60: Active | I60: 1 | J60: Yes | K60: Strict: portal wording, never learns. Rewording keeps the Key; the rules use the Key.
A61: BundledPayment | B61: no | C61: No | F61: 0 | G61: seed | H61: Active | I61: 2 | J61: Yes | K61: Strict: portal wording, never learns. Rewording keeps the Key; the rules use the Key.
A62: ActingAs | B62: provider | C62: Health care provider | F62: 0 | G62: seed | H62: Active | I62: 1 | J62: Yes | K62: Strict: portal wording, never learns. Rewording keeps the Key; the rules use the Key.
A63: ActingAs | B63: facility | C63: Health care facility | F63: 0 | G63: seed | H63: Active | I63: 2 | J63: Yes | K63: Strict: portal wording, never learns. Rewording keeps the Key; the rules use the Key.
A64: PlanRole | B64: group | C64: Group health plan | F64: 0 | G64: seed | H64: Active | I64: 1 | J64: Yes | K64: Strict: portal wording, never learns. Rewording keeps the Key; the rules use the Key.
A65: PlanRole | B65: individual | C65: Individual health insurance issuer | F65: 0 | G65: seed | H65: Active | I65: 2 | J65: Yes | K65: Strict: portal wording, never learns. Rewording keeps the Key; the rules use the Key.
A66: PlanRole | B66: fehb | C66: Federal Employee Health Benefits (FEHB) carrier | F66: 0 | G66: seed | H66: Active | I66: 3 | J66: Yes | K66: Strict: portal wording, never learns. Rewording keeps the Key; the rules use the Key.
A67: HealthPlanType | B67: individual | C67: Individual health insurance issuer | F67: 0 | G67: seed | H67: Active | I67: 1 | J67: Yes | K67: Strict: portal wording, never learns. Rewording keeps the Key; the rules use the Key.
A68: HealthPlanType | B68: fully_insured | C68: Fully-insured ERISA group health plan | F68: 0 | G68: seed | H68: Active | I68: 2 | J68: Yes | K68: Strict: portal wording, never learns. Rewording keeps the Key; the rules use the Key.
A69: HealthPlanType | B69: fehb | C69: Federal Employees Health Benefits (FEHB) carrier | F69: 0 | G69: seed | H69: Active | I69: 3 | J69: Yes | K69: Strict: portal wording, never learns. Rewording keeps the Key; the rules use the Key.
... A73: HealthPlanType | B73: no_response | C73: No Plan/Issuer Response | F73: 0 | G73: seed | H73: Active | I73: 7 | J73: Yes | K73: Strict: portal wording, never learns. Rewording keeps the Key; the rules use the Key.
A74: DisputeType | B74: single | C74: A single dispute | D74: I’m disputing either (a) one service code that represents one item or service, or (b) one service code that represents multiple items or services (a bundled payment arrangement). | F74: 0 | G74: seed | H74: Active | I74: 1 | J74: Yes | K74: Strict: portal wording, never learns. Rewording keeps the Key; the rules use the Key.
A75: DisputeType | B75: batched | C75: A batched dispute | D75: I’m disputing multiple items or services related to the treatment of a similar condition. | F75: 0 | G75: seed | H75: Active | I75: 2 | J75: Yes | K75: Strict: portal wording, never learns. Rewording keeps the Key; the rules use the Key.
A76: ExtensionReason | B76: approval | C76: I received an extension approval from the Federal IDR mailbox and will upload evidence of this extension in the Supporting Documentation section of this web form. | D76: Extension approval | F76: 0 | G76: seed | H76: Active | I76: 1 | J76: Yes | K76: Strict: portal wording, never learns. Rewording keeps the Key; the rules use the Key.
A77: ExtensionReason | B77: cooling | C77: The item(s) or service(s) under dispute was subject to the cooling off period. | D77: Cooling off period | F77: 0 | G77: seed | H77: Active | I77: 2 | J77: Yes | K77: Strict: portal wording, never learns. Rewording keeps the Key; the rules use the Key.
A78: ItemType | B78: emergency | C78: Emergency item(s)/service(s) | F78: 0 | G78: seed | H78: Active | I78: 1 | J78: Yes | K78: Strict: portal wording, never learns. Rewording keeps the Key; the rules use the Key.
A79: ItemType | B79: post_stabilization | C79: Post-stabilization service(s) | F79: 0 | G79: seed | H79: Active | I79: 2 | J79: Yes | K79: Strict: portal wording, never learns. Rewording keeps the Key; the rules use the Key.
A80: ItemType | B80: professional | C80: Professional service(s) | F80: 0 | G80: seed | H80: Active | I80: 3 | J80: Yes | K80: Strict: portal wording, never learns. Rewording keeps the Key; the rules use the Key.
A81: ItemType | B81: hospital_based | C81: Hospital-based service(s) | F81: 0 | G81: seed | H81: Active | I81: 4 | J81: Yes | K81: Strict: portal wording, never learns. Rewording keeps the Key; the rules use the Key.
A82: ItemType | B82: nonpar_at_par | C82: Item(s)/service(s) furnished by a nonparticipating provider at a participating health care facility | F82: 0 | G82: seed | H82: Active | I82: 5 | J82: Yes | K82: Strict: portal wording, never learns. Rewording keeps the Key; the rules use the Key.
A83: ItemType | B83: other | C83: Other: Provide description | F83: 0 | G83: seed | H83: Active | I83: 6 | J83: Yes | K83: Strict: portal wording, never learns. Rewording keeps the Key; the rules use the Key.
A84: LineType | B84: bundled | C84: Bundled Item or Service | F84: 0 | G84: seed | H84: Active | I84: 1 | J84: Yes | K84: Strict: portal wording, never learns. Rewording keeps the Key; the rules use the Key.
A85: LineType | B85: component | C85: Component Item or Service | F85: 0 | G85: seed | H85: Active | I85: 2 | J85: Yes | K85: Strict: portal wording, never learns. Rewording keeps the Key; the rules use the Key.
A86: NipMethod | B86: email | C86: Email | F86: 0 | G86: seed | H86: Active | I86: 1 | J86: Yes | K86: Strict: portal wording, never learns. Rewording keeps the Key; the rules use the Key.
A87: NipMethod | B87: mail | C87: Mail | F87: 0 | G87: seed | H87: Active | I87: 2 | J87: Yes | K87: Strict: portal wording, never learns. Rewording keeps the Key; the rules use the Key.
A88: NipMethod | B88: fax | C88: Fax | F88: 0 | G88: seed | H88: Active | I88: 3 | J88: Yes | K88: Strict: portal wording, never learns. Rewording keeps the Key; the rules use the Key.
A89: NipMethod | B89: portal | C89: Portal | F89: 0 | G89: seed | H89: Active | I89: 4 | J89: Yes | K89: Strict: portal wording, never learns. Rewording keeps the Key; the rules use the Key.
... A93: IdreStatus | B93: alternate_denied | C93: Alternate denied | F93: 0 | G93: seed | H93: Active | I93: 4 | J93: Yes | K93: Strict: portal wording, never learns. Rewording keeps the Key; the rules use the Key.
A94: ReturnReason | C94: Missing document | F94: 0 | G94: seed | H94: Active
A95: ReturnReason | C95: Wrong amount | F95: 0 | G95: seed | H95: Active
A96: ReturnReason | C96: Wrong payer details | F96: 0 | G96: seed | H96: Active
A97: ReturnReason | C97: Not eligible | F97: 0 | G97: seed | H97: Active
A98: ReturnReason | C98: Deadline passed | F98: 0 | G98: seed | H98: Active
A99: ReturnReason | C99: Duplicate line item | F99: 0 | G99: seed | H99: Active
A100: ReturnReason | C100: Other | F100: 0 | G100: seed | H100: Active
A101: PosCode | C101: 23 | D101: Emergency room – hospital | F101: 25 | G101: seed | H101: Active
A102: PosCode | C102: 22 | D102: On campus-outpatient hospital | F102: 0 | G102: seed | H102: Active
A103: PosCode | C103: 11 | D103: Office | F103: 0 | G103: seed | H103: Active
A104: PosCode | C104: 20 | D104: Urgent care facility | F104: 0 | G104: seed | H104: Active
A105: PosCode | C105: 41 | D105: Ambulance – land | F105: 0 | G105: seed | H105: Active
A106: Modifier | C106: 25 | F106: 0 | G106: seed | H106: Active
A107: Modifier | C107: 59 | F107: 0 | G107: seed | H107: Active
A108: Modifier | C108: XU | F108: 0 | G108: seed | H108: Active
A109: Modifier | C109: 76 | F109: 0 | G109: seed | H109: Active
A110: Modifier | C110: 77 | F110: 0 | G110: seed | H110: Active
A111: Modifier | C111: LT | F111: 0 | G111: seed | H111: Active
A112: Modifier | C112: RT | F112: 0 | G112: seed | H112: Active
A113: Modifier | C113: GC | F113: 0 | G113: seed | H113: Active
A114: IdrEntity | C114: Maximus Federal Services Inc | F114: 2 | G114: seed | H114: Active
A115: IdrEntity | C115: Capitol Bridge LLC | F115: 1 | G115: seed | H115: Active
A116: IdrEntity | C116: Federal Hearings and Appeals Services, LLC | F116: 1 | G116: seed | H116: Active
A117: Payer | C117: 90 Degree Benefits | F117: 0 | G117: seed | H117: Active | K117: Contact details needed.
A118: Payer | C118: ABA | F118: 0 | G118: seed | H118: Active | K118: Contact details needed.
A119: Payer | C119: Aetna | F119: 0 | G119: seed | H119: Active | K119: Contact details needed.
A120: Payer | C120: Allegiance | F120: 0 | G120: seed | H120: Active | K120: Contact details needed.
A121: Payer | C121: Allegiance Benefi Plan Management, Inc | F121: 0 | G121: seed | H121: Active | K121: Contact details needed. Possible typo "Benefi"; also close to "Allegiance". Business to confirm.
A122: Payer | C122: Allied Benefit Systems, Inc. | F122: 0 | G122: seed | H122: Active | K122: Contact details needed.
A123: Payer | C123: Allstate | F123: 0 | G123: seed | H123: Active | K123: Contact details needed.
A124: Payer | C124: Ambetter-Superior HealthPlan | F124: 0 | G124: seed | H124: Active | K124: Contact details needed.
A125: Payer | C125: Angle Health | F125: 0 | G125: seed | H125: Active | K125: Contact details needed.
A126: Payer | C126: Ameriben | F126: 0 | G126: seed | H126: Active | K126: Contact details needed.
A127: Payer | C127: APWU Health Plan | F127: 0 | G127: seed | H127: Active | K127: Contact details needed.
A128: Payer | C128: Assured Benefits Administrator | F128: 0 | G128: seed | H128: Active | K128: Contact details needed.
... A131: Payer | C131: Baylor Scott & White | F131: 0 | G131: seed | H131: Active | K131: Contact details needed.
A132: Payer | C132: BCBS | E132: {"addr1": "PO BOX 660044", "city": "Dallas", "state": "TX", "zip": "75266", "email": "nsa.disputes@bcbstx.com", "phone": "(800) 451-0287"} | F132: 1 | G132: seed | H132: Active
A133: Payer | C133: Benefit & Risk Management Services- BRMS | F133: 0 | G133: seed | H133: Active | K133: Contact details needed.
A134: Payer | C134: BENEFITS HEALTHSMART | F134: 0 | G134: seed | H134: Active | K134: Contact details needed. Kept separate from Healthsmart (may be a different TPA). Business to confirm.
A135: Payer | C135: Boon Chapman | F135: 0 | G135: seed | H135: Active | K135: Contact details needed.
A136: Payer | C136: Bright HealthCare | F136: 0 | G136: seed | H136: Active | K136: Contact details needed.
A137: Payer | C137: Cantex Inc | F137: 0 | G137: seed | H137: Active | K137: Contact details needed.
A138: Payer | C138: CareFactor | F138: 0 | G138: seed | H138: Active | K138: Contact details needed.
A139: Payer | C139: Centivo | F139: 0 | G139: seed | H139: Active | K139: Contact details needed.
A140: Payer | C140: CGS Health | F140: 0 | G140: seed | H140: Active | K140: Contact details needed.
A141: Payer | C141: Chesterfield Resources Inc. | F141: 0 | G141: seed | H141: Active | K141: Contact details needed.
A142: Payer | C142: Cigna | E142: {"addr1": "P.O. BOX 182223", "city": "CHATTANOOGA", "state": "TN", "zip": "37422-7223", "email": "nsaidr@multiplan.com", "phone": "(800) 244-6224"} | F142: 1 | G142: seed | H142: Active
A143: Payer | C143: CITY OF FORT WORTH | F143: 0 | G143: seed | H143: Active | K143: Contact details needed.
A144: Payer | C144: Coeur Plan | F144: 0 | G144: seed | H144: Active | K144: Contact details needed.
A145: Payer | C145: Concord Hospital Entreprises | F145: 0 | G145: seed | H145: Active | K145: Contact details needed. Possible typo "Entreprises". Business to confirm.
A146: Payer | C146: Connected Care | F146: 0 | G146: seed | H146: Active | K146: Contact details needed.
A147: Payer | C147: COOK CHILDREN'S HEALTH CARE SYSTEM | F147: 0 | G147: seed | H147: Active | K147: Contact details needed.
A148: Payer | C148: Dean Health Plan | F148: 0 | G148: seed | H148: Active | K148: Contact details needed.
A149: Payer | C149: EMI Health | F149: 0 | G149: seed | H149: Active | K149: Contact details needed.
A150: Payer | C150: Employers Health Network | F150: 0 | G150: seed | H150: Active | K150: Contact details needed.
A151: Payer | C151: Enterprise Group Planning, INC | F151: 0 | G151: seed | H151: Active | K151: Contact details needed.
...

Sheet Payers
A1: Name (non-initiating party) | B1: Mailing Address | C1: City | D1: State | E1: ZIP Code | F1: Email | G1: Phone | H1: Fax | I1: Aliases | J1: Times seen (4 notices) | K1: Seen on dispute | L1: Portal name check | M1: Flag / note
A2: 90 Degree Benefits | J2: 0 | L2: OK | M2: Contact details needed.
A3: ABA | J3: 0 | L3: OK | M3: Contact details needed.
A4: Aetna | J4: 0 | L4: OK | M4: Contact details needed.
A5: Allegiance | J5: 0 | L5: OK | M5: Contact details needed.
A6: Allegiance Benefi Plan Management, Inc | J6: 0 | L6: OK | M6: Contact details needed. Possible typo "Benefi"; also close to "Allegiance". Business to confirm.
A7: Allied Benefit Systems, Inc. | J7: 0 | L7: OK | M7: Contact details needed.
A8: Allstate | J8: 0 | L8: OK | M8: Contact details needed.
A9: Ambetter-Superior HealthPlan | J9: 0 | L9: OK | M9: Contact details needed.
A10: Angle Health | J10: 0 | L10: OK | M10: Contact details needed.
A11: Ameriben | J11: 0 | L11: OK | M11: Contact details needed.
A12: APWU Health Plan | J12: 0 | L12: OK | M12: Contact details needed.
A13: Assured Benefits Administrator | J13: 0 | L13: OK | M13: Contact details needed.
... A16: Baylor Scott & White | J16: 0 | L16: OK | M16: Contact details needed.
A17: BCBS | B17: PO BOX 660044 | C17: Dallas | D17: TX | E17: 75266 | F17: nsa.disputes@bcbstx.com | G17: (800) 451-0287 | I17: BLUECROSS BLUESHIELD | J17: 1 | K17: DISP-7998956 | L17: OK
A18: Benefit & Risk Management Services- BRMS | J18: 0 | L18: OK | M18: Contact details needed.
A19: BENEFITS HEALTHSMART | J19: 0 | L19: OK | M19: Contact details needed. Kept separate from Healthsmart (may be a different TPA). Business to confirm.
A20: Boon Chapman | J20: 0 | L20: OK | M20: Contact details needed.
A21: Bright HealthCare | J21: 0 | L21: OK | M21: Contact details needed.
A22: Cantex Inc | J22: 0 | L22: OK | M22: Contact details needed.
A23: CareFactor | J23: 0 | L23: OK | M23: Contact details needed.
A24: Centivo | J24: 0 | L24: OK | M24: Contact details needed.
A25: CGS Health | J25: 0 | L25: OK | M25: Contact details needed.
A26: Chesterfield Resources Inc. | J26: 0 | L26: OK | M26: Contact details needed.
A27: Cigna | B27: P.O. BOX 182223 | C27: CHATTANOOGA | D27: TN | E27: 37422-7223 | F27: nsaidr@multiplan.com | G27: (800) 244-6224 | J27: 1 | K27: DISP-7997846 | L27: OK
A28: CITY OF FORT WORTH | J28: 0 | L28: OK | M28: Contact details needed.
A29: Coeur Plan | J29: 0 | L29: OK | M29: Contact details needed.
A30: Concord Hospital Entreprises | J30: 0 | L30: OK | M30: Contact details needed. Possible typo "Entreprises". Business to confirm.
A31: Connected Care | J31: 0 | L31: OK | M31: Contact details needed.
A32: COOK CHILDREN'S HEALTH CARE SYSTEM | J32: 0 | L32: OK | M32: Contact details needed.
A33: Dean Health Plan | J33: 0 | L33: OK | M33: Contact details needed.
A34: EMI Health | J34: 0 | L34: OK | M34: Contact details needed.
A35: Employers Health Network | J35: 0 | L35: OK | M35: Contact details needed.
A36: Enterprise Group Planning, INC | J36: 0 | L36: OK | M36: Contact details needed.
A37: EVHC | J37: 0 | L37: OK | M37: Contact details needed.
A38: First Health Network | J38: 0 | L38: OK | M38: Contact details needed.
A39: Fringe Benefit Group | J39: 0 | L39: OK | M39: Contact details needed.
... A54: healthnet | J54: 0 | L54: OK | M54: Contact details needed. All lower case. Business to confirm the display name.
A55: HealthNow | I55: Health Now | J55: 0 | L55: OK | M55: Contact details needed.
A56: HealthScope Benefits | J56: 0 | L56: OK | M56: Contact details needed.
A57: Healthsmart | J57: 0 | L57: OK | M57: Contact details needed. Kept separate from BENEFITS HEALTHSMART. Business to confirm.
A58: Humana | J58: 0 | L58: OK | M58: Contact details needed.
A59: IBEW-NECA Southwestern Health & Benefit Fund | J59: 0 | L59: OK | M59: Contact details needed.
A60: IDA | J60: 0 | L60: OK | M60: Contact details needed.
A61: Imagine 360 | J61: 0 | L61: OK | M61: Contact details needed.
A62: Imagine Health | J62: 0 | L62: OK | M62: Contact details needed.
A63: JP Farley | J63: 0 | L63: OK | M63: Contact details needed.
A64: Insurance Management Services | J64: 0 | L64: OK | M64: Contact details needed.
A65: Insurance Administrator of America | J65: 0 | L65: OK | M65: Contact details needed.
A66: Insurance Medical Services | J66: 0 | L66: OK | M66: Contact details needed.
A67: Kaiser Permanente | J67: 0 | L67: OK | M67: Contact details needed.
... A109: UFCW Med 1000 | J109: 0 | L109: OK | M109: Contact details needed.
A110: UHC | B110: PO Box 30783 | C110: Salt Lake City | D110: UT | E110: 84130-0783 | F110: uhg_idr_disputes@uhc.com | G110: (877) 842-3210 | I110: United Healthcare | J110: 1 | K110: DISP-7984427 | L110: OK
A111: UHC Shared Services | J111: 0 | L111: OK | M111: Contact details needed. May be the same as "UHSS". Business to confirm.
A112: UHC Surest | J112: 0 | L112: OK | M112: Contact details needed.
A113: UHSS | J113: 0 | L113: OK | M113: Contact details needed. May be the same as "UHC Shared Services". Business to confirm.
A114: UMR | B114: PO BOX 30541 | C114: SALT LAKE CITY | D114: UT | E114: 84130 | F114: idr@clearhealthcloud.com | G114: (877) 233-1800 | J114: 1 | K114: DISP-7986216 | L114: OK
A115: Unified Group Services | J115: 0 | L115: OK | M115: Contact details needed.
A116: UNITED AGRICULTURAL BENEFIT TRUST | J116: 0 | L116: OK | M116: Contact details needed.
A117: United Benefit Fund | J117: 0 | L117: OK | M117: Contact details needed.
A118: UPMC | J118: 0 | L118: OK | M118: Contact details needed.
A119: US Benefits | J119: 0 | L119: OK | M119: Contact details needed.
A120: Vitori Health | J120: 0 | L120: OK | M120: Contact details needed.
A121: WebTPA | J121: 0 | L121: OK | M121: Contact details needed.
A122: YUZU Health | J122: 0 | L122: OK | M122: Contact details needed.
A123: ZELIS | J123: 0 | L123: OK | M123: Contact details needed.
A124: Friday Health Plan | J124: 0 | L124: OK | M124: Contact details needed.
A125: Unite Here Health | J125: 0 | L125: OK | M125: Contact details needed.
A127: Note | B127: Names exactly as given by the business. Profiles kept from the 4 notices: UMR, UHC (was "United Healthcare"), BCBS (was "BLUECROSS BLUESHIELD"), Cigna. The other 120 payers have no contact details yet; they are learned on first save.

Sheet BillingEntities
A1: Name | B1: ActingAs | C1: TIN | D1: NPI | E1: GroupName | F1: Addr1 | G1: Addr2 | H1: City | I1: State | J1: ZIP | K1: Email | L1: Phone | M1: Fax | N1: Confirmed | O1: Status | P1: Count | Q1: LastUsed | R1: AddedBy | S1: AddedAt | T1: Notes | U1: Aliases | V1: Flag / note
A2: Jade Medical, PLLC | B2: Health care provider | N2: No | O2: Active | P2: 0 | R2: setup | S2: (setup time) | V2: ActingAs is a guess from the legal suffix (PLLC -> provider, LLC -> facility); Confirmed No until a saved dispute confirms it. TIN, NPI, GroupName and contact needed (learned on first save or entered in Admin -> Billing entities).
A3: Deerfield plains, LLC | B3: Health care facility | N3: No | O3: Active | P3: 0 | R3: setup | S3: (setup time) | V3: ActingAs is a guess from the legal suffix (PLLC -> provider, LLC -> facility); Confirmed No until a saved dispute confirms it. TIN, NPI, GroupName and contact needed (learned on first save or entered in Admin -> Billing entities). Possible typo to confirm (not changed): Lower-case "plains" (Deerfield Plains?).
A4: CareMed, PLLC | B4: Health care provider | N4: No | O4: Active | P4: 0 | R4: setup | S4: (setup time) | V4: ActingAs is a guess from the legal suffix (PLLC -> provider, LLC -> facility); Confirmed No until a saved dispute confirms it. TIN, NPI, GroupName and contact needed (learned on first save or entered in Admin -> Billing entities).
A5: Sycamore Rush, LLC | B5: Health care facility | N5: No | O5: Active | P5: 0 | R5: setup | S5: (setup time) | V5: ActingAs is a guess from the legal suffix (PLLC -> provider, LLC -> facility); Confirmed No until a saved dispute confirms it. TIN, NPI, GroupName and contact needed (learned on first save or entered in Admin -> Billing entities).
A6: WRFER University, LLC | B6: Health care facility | N6: No | O6: Active | P6: 0 | R6: setup | S6: (setup time) | V6: ActingAs is a guess from the legal suffix (PLLC -> provider, LLC -> facility); Confirmed No until a saved dispute confirms it. TIN, NPI, GroupName and contact needed (learned on first save or entered in Admin -> Billing entities). Possible typo to confirm (not changed): "WRFER" vs "WFRER" in WFRER Denton and WFRER Cooper.
A7: Windview First, PLLC | B7: Health care provider | N7: No | O7: Active | P7: 0 | R7: setup | S7: (setup time) | V7: ActingAs is a guess from the legal suffix (PLLC -> provider, LLC -> facility); Confirmed No until a saved dispute confirms it. TIN, NPI, GroupName and contact needed (learned on first save or entered in Admin -> Billing entities).
A8: Capital Health, PLLC | B8: Health care provider | C8: 872524265 | D8: 1609548056 | E8: Totalcare ER, Cedar Hill | F8: 6049 S. Hulen St. | H8: Fort Worth | I8: TX | J8: 76132 | K8: cedarhill.negotiations@totalcare.us | L8: (817) 566-1232 | N8: Yes | O8: Active | P8: 1 | R8: setup | S8: (setup time) | U8: CAPITAL HEALTH PLLC | V8: ActingAs confirmed by the 4 notices. v2 spellings kept in Aliases.
A9: Silver Alliance, LLC | B9: Health care facility | C9: 862923814 | D9: 1972273233 | F9: 6049 S. Hulen St. | H9: Fort Worth | I9: TX | J9: 76132 | K9: cedarhill.negotiations@totalcare.us | L9: (817) 566-1232 | N9: Yes | O9: Active | P9: 3 | R9: setup | S9: (setup time) | U9: SILVER ALLIANCE LLC; SILVER ALLIANCE,LLC | V9: ActingAs confirmed by the 4 notices. v2 spellings kept in Aliases. GroupName missing; now required on page 3.
A10: Trans Oakley, LLC | B10: Health care facility | N10: No | O10: Active | P10: 0 | R10: setup | S10: (setup time) | V10: ActingAs is a guess from the legal suffix (PLLC -> provider, LLC -> facility); Confirmed No until a saved dispute confirms it. TIN, NPI, GroupName and contact needed (learned on first save or entered in Admin -> Billing entities).
A11: Eastern Elm, PLLC | B11: Health care provider | N11: No | O11: Active | P11: 0 | R11: setup | S11: (setup time) | V11: ActingAs is a guess from the legal suffix (PLLC -> provider, LLC -> facility); Confirmed No until a saved dispute confirms it. TIN, NPI, GroupName and contact needed (learned on first save or entered in Admin -> Billing entities).
A12: Lakewood Green, LLC | B12: Health care facility | N12: No | O12: Active | P12: 0 | R12: setup | S12: (setup time) | V12: ActingAs is a guess from the legal suffix (PLLC -> provider, LLC -> facility); Confirmed No until a saved dispute confirms it. TIN, NPI, GroupName and contact needed (learned on first save or entered in Admin -> Billing entities).
A13: Silver choice, PLLC | B13: Health care provider | N13: No | O13: Active | P13: 0 | R13: setup | S13: (setup time) | V13: ActingAs is a guess from the legal suffix (PLLC -> provider, LLC -> facility); Confirmed No until a saved dispute confirms it. TIN, NPI, GroupName and contact needed (learned on first save or entered in Admin -> Billing entities). Possible typo to confirm (not changed): Lower-case "choice" (Silver Choice?).
A14: Greenwood South, LLC | B14: Health care facility | N14: No | O14: Active | P14: 0 | R14: setup | S14: (setup time) | V14: ActingAs is a guess from the legal suffix (PLLC -> provider, LLC -> facility); Confirmed No until a saved dispute confirms it. TIN, NPI, GroupName and contact needed (learned on first save or entered in Admin -> Billing entities).
A15: Aspen Willow, PLLC | B15: Health care provider | N15: No | O15: Active | P15: 0 | R15: setup | S15: (setup time) | V15: ActingAs is a guess from the legal suffix (PLLC -> provider, LLC -> facility); Confirmed No until a saved dispute confirms it. TIN, NPI, GroupName and contact needed (learned on first save or entered in Admin -> Billing entities).
A16: RSER Benbrook, LLC | B16: Health care facility | N16: No | O16: Active | P16: 0 | R16: setup | S16: (setup time) | V16: ActingAs is a guess from the legal suffix (PLLC -> provider, LLC -> facility); Confirmed No until a saved dispute confirms it. TIN, NPI, GroupName and contact needed (learned on first save or entered in Admin -> Billing entities). Possible typo to confirm (not changed): "RSER" (compare TotalCare ER Benbrook, PLLC).
A17: TotalCare ER Benbrook, PLLC | B17: Health care provider | N17: No | O17: Active | P17: 0 | R17: setup | S17: (setup time) | V17: ActingAs is a guess from the legal suffix (PLLC -> provider, LLC -> facility); Confirmed No until a saved dispute confirms it. TIN, NPI, GroupName and contact needed (learned on first save or entered in Admin -> Billing entities).
A18: Cedar Physcians, PLLC | B18: Health care provider | N18: No | O18: Active | P18: 0 | R18: setup | S18: (setup time) | V18: ActingAs is a guess from the legal suffix (PLLC -> provider, LLC -> facility); Confirmed No until a saved dispute confirms it. TIN, NPI, GroupName and contact needed (learned on first save or entered in Admin -> Billing entities). Possible typo to confirm (not changed): "Physcians" (Physicians?).
A19: WFRER Denton, LLC | B19: Health care facility | N19: No | O19: Active | P19: 0 | R19: setup | S19: (setup time) | V19: ActingAs is a guess from the legal suffix (PLLC -> provider, LLC -> facility); Confirmed No until a saved dispute confirms it. TIN, NPI, GroupName and contact needed (learned on first save or entered in Admin -> Billing entities).
A20: Sun Choice, PLLC | B20: Health care provider | N20: No | O20: Active | P20: 0 | R20: setup | S20: (setup time) | V20: ActingAs is a guess from the legal suffix (PLLC -> provider, LLC -> facility); Confirmed No until a saved dispute confirms it. TIN, NPI, GroupName and contact needed (learned on first save or entered in Admin -> Billing entities).
A21: WFRER Cooper, LLC | B21: Health care facility | N21: No | O21: Active | P21: 0 | R21: setup | S21: (setup time) | V21: ActingAs is a guess from the legal suffix (PLLC -> provider, LLC -> facility); Confirmed No until a saved dispute confirms it. TIN, NPI, GroupName and contact needed (learned on first save or entered in Admin -> Billing entities).
... A25: Gracious Health, LLC | B25: Health care facility | N25: No | O25: Active | P25: 0 | R25: setup | S25: (setup time) | V25: ActingAs is a guess from the legal suffix (PLLC -> provider, LLC -> facility); Confirmed No until a saved dispute confirms it. TIN, NPI, GroupName and contact needed (learned on first save or entered in Admin -> Billing entities).
A27: Note | B27: Seed rows of the BillingEntities tab exactly as setup() writes them (Code.gs seedEntityRows_). setup() moves v3 BillingEntity rows from Options here (Data JSON -> columns, alias rows -> Aliases). Legal names exactly as given; not corrected.

Sheet ServiceCodes
A1: Code | B1: Description (label) | C1: Times seen | D1: Lines with a QPA | E1: QPA min | F1: QPA max | G1: Typical QPA range seen | H1: Source | I1: Format check (5 alphanumeric)
A2: 99285 | C2: =COUNTIF('Observed lines'!$F$2:$F$36,A2) -> 0 | D2: =COUNTIFS('Observed lines'!$F$2:$F$36,A2,'Observed lines'!$G$2:$G$36,"<>") -> 0 | E2: =IF(D2=0,"",_xlfn.MINIFS('Observed lines'!$G$2:$G$36,'Observed lines'!$F$2:$F$36,A2)) | F2: =IF(D2=0,"",_xlfn.MAXIFS('Observed lines'!$G$2:$G$36,'Observed lines'!$F$2:$F$36,A2)) | G2: =IF(D2=0,"none seen",IF(E2=F2,TEXT(E2,"$#,##0.00"),TEXT(E2,"$#,##0.00")&" – "&TEXT(F2,"$#,##0.00"))) -> none seen | H2: seed (business list) | I2: OK
A3: 99284 | B3: EMERGENCY ROOM SERVICE | C3: =COUNTIF('Observed lines'!$F$2:$F$36,A3) -> 3 | D3: =COUNTIFS('Observed lines'!$F$2:$F$36,A3,'Observed lines'!$G$2:$G$36,"<>") -> 2 | E3: =IF(D3=0,"",_xlfn.MINIFS('Observed lines'!$G$2:$G$36,'Observed lines'!$F$2:$F$36,A3)) -> 250.3 | F3: =IF(D3=0,"",_xlfn.MAXIFS('Observed lines'!$G$2:$G$36,'Observed lines'!$F$2:$F$36,A3)) -> 1052.46 | G3: =IF(D3=0,"none seen",IF(E3=F3,TEXT(E3,"$#,##0.00"),TEXT(E3,"$#,##0.00")&" – "&TEXT(F3,"$#,##0.00"))) -> $250.30 – $1,052.46 | H3: seed + observed | I3: OK
A4: 99291 | C4: =COUNTIF('Observed lines'!$F$2:$F$36,A4) -> 0 | D4: =COUNTIFS('Observed lines'!$F$2:$F$36,A4,'Observed lines'!$G$2:$G$36,"<>") -> 0 | E4: =IF(D4=0,"",_xlfn.MINIFS('Observed lines'!$G$2:$G$36,'Observed lines'!$F$2:$F$36,A4)) | F4: =IF(D4=0,"",_xlfn.MAXIFS('Observed lines'!$G$2:$G$36,'Observed lines'!$F$2:$F$36,A4)) | G4: =IF(D4=0,"none seen",IF(E4=F4,TEXT(E4,"$#,##0.00"),TEXT(E4,"$#,##0.00")&" – "&TEXT(F4,"$#,##0.00"))) -> none seen | H4: seed (business list) | I4: OK
A5: 70450 | B5: CT HEAD/BRAIN W/O DYE | C5: =COUNTIF('Observed lines'!$F$2:$F$36,A5) -> 1 | D5: =COUNTIFS('Observed lines'!$F$2:$F$36,A5,'Observed lines'!$G$2:$G$36,"<>") -> 1 | E5: =IF(D5=0,"",_xlfn.MINIFS('Observed lines'!$G$2:$G$36,'Observed lines'!$F$2:$F$36,A5)) -> 348.35 | F5: =IF(D5=0,"",_xlfn.MAXIFS('Observed lines'!$G$2:$G$36,'Observed lines'!$F$2:$F$36,A5)) -> 348.35 | G5: =IF(D5=0,"none seen",IF(E5=F5,TEXT(E5,"$#,##0.00"),TEXT(E5,"$#,##0.00")&" – "&TEXT(F5,"$#,##0.00"))) -> $348.35 | H5: seed + observed | I5: OK
A6: 74176 | C6: =COUNTIF('Observed lines'!$F$2:$F$36,A6) -> 0 | D6: =COUNTIFS('Observed lines'!$F$2:$F$36,A6,'Observed lines'!$G$2:$G$36,"<>") -> 0 | E6: =IF(D6=0,"",_xlfn.MINIFS('Observed lines'!$G$2:$G$36,'Observed lines'!$F$2:$F$36,A6)) | F6: =IF(D6=0,"",_xlfn.MAXIFS('Observed lines'!$G$2:$G$36,'Observed lines'!$F$2:$F$36,A6)) | G6: =IF(D6=0,"none seen",IF(E6=F6,TEXT(E6,"$#,##0.00"),TEXT(E6,"$#,##0.00")&" – "&TEXT(F6,"$#,##0.00"))) -> none seen | H6: seed (business list) | I6: OK
A7: 0202U | C7: =COUNTIF('Observed lines'!$F$2:$F$36,A7) -> 0 | D7: =COUNTIFS('Observed lines'!$F$2:$F$36,A7,'Observed lines'!$G$2:$G$36,"<>") -> 0 | E7: =IF(D7=0,"",_xlfn.MINIFS('Observed lines'!$G$2:$G$36,'Observed lines'!$F$2:$F$36,A7)) | F7: =IF(D7=0,"",_xlfn.MAXIFS('Observed lines'!$G$2:$G$36,'Observed lines'!$F$2:$F$36,A7)) | G7: =IF(D7=0,"none seen",IF(E7=F7,TEXT(E7,"$#,##0.00"),TEXT(E7,"$#,##0.00")&" – "&TEXT(F7,"$#,##0.00"))) -> none seen | H7: seed (business list) | I7: OK
A8: 71046 | C8: =COUNTIF('Observed lines'!$F$2:$F$36,A8) -> 0 | D8: =COUNTIFS('Observed lines'!$F$2:$F$36,A8,'Observed lines'!$G$2:$G$36,"<>") -> 0 | E8: =IF(D8=0,"",_xlfn.MINIFS('Observed lines'!$G$2:$G$36,'Observed lines'!$F$2:$F$36,A8)) | F8: =IF(D8=0,"",_xlfn.MAXIFS('Observed lines'!$G$2:$G$36,'Observed lines'!$F$2:$F$36,A8)) | G8: =IF(D8=0,"none seen",IF(E8=F8,TEXT(E8,"$#,##0.00"),TEXT(E8,"$#,##0.00")&" – "&TEXT(F8,"$#,##0.00"))) -> none seen | H8: seed (business list) | I8: OK
A9: 71100 | C9: =COUNTIF('Observed lines'!$F$2:$F$36,A9) -> 0 | D9: =COUNTIFS('Observed lines'!$F$2:$F$36,A9,'Observed lines'!$G$2:$G$36,"<>") -> 0 | E9: =IF(D9=0,"",_xlfn.MINIFS('Observed lines'!$G$2:$G$36,'Observed lines'!$F$2:$F$36,A9)) | F9: =IF(D9=0,"",_xlfn.MAXIFS('Observed lines'!$G$2:$G$36,'Observed lines'!$F$2:$F$36,A9)) | G9: =IF(D9=0,"none seen",IF(E9=F9,TEXT(E9,"$#,##0.00"),TEXT(E9,"$#,##0.00")&" – "&TEXT(F9,"$#,##0.00"))) -> none seen | H9: seed (business list) | I9: OK
A10: 99283 | B10: EMERGENCY ROOM SERVICE | C10: =COUNTIF('Observed lines'!$F$2:$F$36,A10) -> 1 | D10: =COUNTIFS('Observed lines'!$F$2:$F$36,A10,'Observed lines'!$G$2:$G$36,"<>") -> 1 | E10: =IF(D10=0,"",_xlfn.MINIFS('Observed lines'!$G$2:$G$36,'Observed lines'!$F$2:$F$36,A10)) -> 905.44 | F10: =IF(D10=0,"",_xlfn.MAXIFS('Observed lines'!$G$2:$G$36,'Observed lines'!$F$2:$F$36,A10)) -> 905.44 | G10: =IF(D10=0,"none seen",IF(E10=F10,TEXT(E10,"$#,##0.00"),TEXT(E10,"$#,##0.00")&" – "&TEXT(F10,"$#,##0.00"))) -> $905.44 | H10: seed + observed | I10: OK
A11: 27780 | C11: =COUNTIF('Observed lines'!$F$2:$F$36,A11) -> 0 | D11: =COUNTIFS('Observed lines'!$F$2:$F$36,A11,'Observed lines'!$G$2:$G$36,"<>") -> 0 | E11: =IF(D11=0,"",_xlfn.MINIFS('Observed lines'!$G$2:$G$36,'Observed lines'!$F$2:$F$36,A11)) | F11: =IF(D11=0,"",_xlfn.MAXIFS('Observed lines'!$G$2:$G$36,'Observed lines'!$F$2:$F$36,A11)) | G11: =IF(D11=0,"none seen",IF(E11=F11,TEXT(E11,"$#,##0.00"),TEXT(E11,"$#,##0.00")&" – "&TEXT(F11,"$#,##0.00"))) -> none seen | H11: seed (business list) | I11: OK
A12: 99000 | C12: =COUNTIF('Observed lines'!$F$2:$F$36,A12) -> 0 | D12: =COUNTIFS('Observed lines'!$F$2:$F$36,A12,'Observed lines'!$G$2:$G$36,"<>") -> 0 | E12: =IF(D12=0,"",_xlfn.MINIFS('Observed lines'!$G$2:$G$36,'Observed lines'!$F$2:$F$36,A12)) | F12: =IF(D12=0,"",_xlfn.MAXIFS('Observed lines'!$G$2:$G$36,'Observed lines'!$F$2:$F$36,A12)) | G12: =IF(D12=0,"none seen",IF(E12=F12,TEXT(E12,"$#,##0.00"),TEXT(E12,"$#,##0.00")&" – "&TEXT(F12,"$#,##0.00"))) -> none seen | H12: seed (business list) | I12: OK
A13: 36410 | C13: =COUNTIF('Observed lines'!$F$2:$F$36,A13) -> 0 | D13: =COUNTIFS('Observed lines'!$F$2:$F$36,A13,'Observed lines'!$G$2:$G$36,"<>") -> 0 | E13: =IF(D13=0,"",_xlfn.MINIFS('Observed lines'!$G$2:$G$36,'Observed lines'!$F$2:$F$36,A13)) | F13: =IF(D13=0,"",_xlfn.MAXIFS('Observed lines'!$G$2:$G$36,'Observed lines'!$F$2:$F$36,A13)) | G13: =IF(D13=0,"none seen",IF(E13=F13,TEXT(E13,"$#,##0.00"),TEXT(E13,"$#,##0.00")&" – "&TEXT(F13,"$#,##0.00"))) -> none seen | H13: seed (business list) | I13: OK
A14: 76705 | C14: =COUNTIF('Observed lines'!$F$2:$F$36,A14) -> 0 | D14: =COUNTIFS('Observed lines'!$F$2:$F$36,A14,'Observed lines'!$G$2:$G$36,"<>") -> 0 | E14: =IF(D14=0,"",_xlfn.MINIFS('Observed lines'!$G$2:$G$36,'Observed lines'!$F$2:$F$36,A14)) | F14: =IF(D14=0,"",_xlfn.MAXIFS('Observed lines'!$G$2:$G$36,'Observed lines'!$F$2:$F$36,A14)) | G14: =IF(D14=0,"none seen",IF(E14=F14,TEXT(E14,"$#,##0.00"),TEXT(E14,"$#,##0.00")&" – "&TEXT(F14,"$#,##0.00"))) -> none seen | H14: seed (business list) | I14: OK
A15: 96372 | B15: THERAPY/PROPHYLAXIS/DIAGNOSIS INJECTION, SC/IM | C15: =COUNTIF('Observed lines'!$F$2:$F$36,A15) -> 1 | D15: =COUNTIFS('Observed lines'!$F$2:$F$36,A15,'Observed lines'!$G$2:$G$36,"<>") -> 1 | E15: =IF(D15=0,"",_xlfn.MINIFS('Observed lines'!$G$2:$G$36,'Observed lines'!$F$2:$F$36,A15)) -> 37.78 | F15: =IF(D15=0,"",_xlfn.MAXIFS('Observed lines'!$G$2:$G$36,'Observed lines'!$F$2:$F$36,A15)) -> 37.78 | G15: =IF(D15=0,"none seen",IF(E15=F15,TEXT(E15,"$#,##0.00"),TEXT(E15,"$#,##0.00")&" – "&TEXT(F15,"$#,##0.00"))) -> $37.78 | H15: seed + observed | I15: OK
A16: 74177 | C16: =COUNTIF('Observed lines'!$F$2:$F$36,A16) -> 0 | D16: =COUNTIFS('Observed lines'!$F$2:$F$36,A16,'Observed lines'!$G$2:$G$36,"<>") -> 0 | E16: =IF(D16=0,"",_xlfn.MINIFS('Observed lines'!$G$2:$G$36,'Observed lines'!$F$2:$F$36,A16)) | F16: =IF(D16=0,"",_xlfn.MAXIFS('Observed lines'!$G$2:$G$36,'Observed lines'!$F$2:$F$36,A16)) | G16: =IF(D16=0,"none seen",IF(E16=F16,TEXT(E16,"$#,##0.00"),TEXT(E16,"$#,##0.00")&" – "&TEXT(F16,"$#,##0.00"))) -> none seen | H16: seed (business list) | I16: OK
A17: 96365 | C17: =COUNTIF('Observed lines'!$F$2:$F$36,A17) -> 0 | D17: =COUNTIFS('Observed lines'!$F$2:$F$36,A17,'Observed lines'!$G$2:$G$36,"<>") -> 0 | E17: =IF(D17=0,"",_xlfn.MINIFS('Observed lines'!$G$2:$G$36,'Observed lines'!$F$2:$F$36,A17)) | F17: =IF(D17=0,"",_xlfn.MAXIFS('Observed lines'!$G$2:$G$36,'Observed lines'!$F$2:$F$36,A17)) | G17: =IF(D17=0,"none seen",IF(E17=F17,TEXT(E17,"$#,##0.00"),TEXT(E17,"$#,##0.00")&" – "&TEXT(F17,"$#,##0.00"))) -> none seen | H17: seed (business list) | I17: OK
A18: 96366 | C18: =COUNTIF('Observed lines'!$F$2:$F$36,A18) -> 0 | D18: =COUNTIFS('Observed lines'!$F$2:$F$36,A18,'Observed lines'!$G$2:$G$36,"<>") -> 0 | E18: =IF(D18=0,"",_xlfn.MINIFS('Observed lines'!$G$2:$G$36,'Observed lines'!$F$2:$F$36,A18)) | F18: =IF(D18=0,"",_xlfn.MAXIFS('Observed lines'!$G$2:$G$36,'Observed lines'!$F$2:$F$36,A18)) | G18: =IF(D18=0,"none seen",IF(E18=F18,TEXT(E18,"$#,##0.00"),TEXT(E18,"$#,##0.00")&" – "&TEXT(F18,"$#,##0.00"))) -> none seen | H18: seed (business list) | I18: OK
A19: 96368 | C19: =COUNTIF('Observed lines'!$F$2:$F$36,A19) -> 0 | D19: =COUNTIFS('Observed lines'!$F$2:$F$36,A19,'Observed lines'!$G$2:$G$36,"<>") -> 0 | E19: =IF(D19=0,"",_xlfn.MINIFS('Observed lines'!$G$2:$G$36,'Observed lines'!$F$2:$F$36,A19)) | F19: =IF(D19=0,"",_xlfn.MAXIFS('Observed lines'!$G$2:$G$36,'Observed lines'!$F$2:$F$36,A19)) | G19: =IF(D19=0,"none seen",IF(E19=F19,TEXT(E19,"$#,##0.00"),TEXT(E19,"$#,##0.00")&" – "&TEXT(F19,"$#,##0.00"))) -> none seen | H19: seed (business list) | I19: OK
A20: 96375 | C20: =COUNTIF('Observed lines'!$F$2:$F$36,A20) -> 0 | D20: =COUNTIFS('Observed lines'!$F$2:$F$36,A20,'Observed lines'!$G$2:$G$36,"<>") -> 0 | E20: =IF(D20=0,"",_xlfn.MINIFS('Observed lines'!$G$2:$G$36,'Observed lines'!$F$2:$F$36,A20)) | F20: =IF(D20=0,"",_xlfn.MAXIFS('Observed lines'!$G$2:$G$36,'Observed lines'!$F$2:$F$36,A20)) | G20: =IF(D20=0,"none seen",IF(E20=F20,TEXT(E20,"$#,##0.00"),TEXT(E20,"$#,##0.00")&" – "&TEXT(F20,"$#,##0.00"))) -> none seen | H20: seed (business list) | I20: OK
A21: 72125 | B21: CT NECK SPINE W/O DYE | C21: =COUNTIF('Observed lines'!$F$2:$F$36,A21) -> 1 | D21: =COUNTIFS('Observed lines'!$F$2:$F$36,A21,'Observed lines'!$G$2:$G$36,"<>") -> 1 | E21: =IF(D21=0,"",_xlfn.MINIFS('Observed lines'!$G$2:$G$36,'Observed lines'!$F$2:$F$36,A21)) -> 374.66 | F21: =IF(D21=0,"",_xlfn.MAXIFS('Observed lines'!$G$2:$G$36,'Observed lines'!$F$2:$F$36,A21)) -> 374.66 | G21: =IF(D21=0,"none seen",IF(E21=F21,TEXT(E21,"$#,##0.00"),TEXT(E21,"$#,##0.00")&" – "&TEXT(F21,"$#,##0.00"))) -> $374.66 | H21: seed + observed | I21: OK
A22: 73030 | C22: =COUNTIF('Observed lines'!$F$2:$F$36,A22) -> 0 | D22: =COUNTIFS('Observed lines'!$F$2:$F$36,A22,'Observed lines'!$G$2:$G$36,"<>") -> 0 | E22: =IF(D22=0,"",_xlfn.MINIFS('Observed lines'!$G$2:$G$36,'Observed lines'!$F$2:$F$36,A22)) | F22: =IF(D22=0,"",_xlfn.MAXIFS('Observed lines'!$G$2:$G$36,'Observed lines'!$F$2:$F$36,A22)) | G22: =IF(D22=0,"none seen",IF(E22=F22,TEXT(E22,"$#,##0.00"),TEXT(E22,"$#,##0.00")&" – "&TEXT(F22,"$#,##0.00"))) -> none seen | H22: seed (business list) | I22: OK
A23: 76870 | C23: =COUNTIF('Observed lines'!$F$2:$F$36,A23) -> 0 | D23: =COUNTIFS('Observed lines'!$F$2:$F$36,A23,'Observed lines'!$G$2:$G$36,"<>") -> 0 | E23: =IF(D23=0,"",_xlfn.MINIFS('Observed lines'!$G$2:$G$36,'Observed lines'!$F$2:$F$36,A23)) | F23: =IF(D23=0,"",_xlfn.MAXIFS('Observed lines'!$G$2:$G$36,'Observed lines'!$F$2:$F$36,A23)) | G23: =IF(D23=0,"none seen",IF(E23=F23,TEXT(E23,"$#,##0.00"),TEXT(E23,"$#,##0.00")&" – "&TEXT(F23,"$#,##0.00"))) -> none seen | H23: seed (business list) | I23: OK
A24: A4670 | B24: AUTOMATIC BLOOD PRESSURE MONITOR | C24: =COUNTIF('Observed lines'!$F$2:$F$36,A24) -> 2 | D24: =COUNTIFS('Observed lines'!$F$2:$F$36,A24,'Observed lines'!$G$2:$G$36,"<>") -> 2 | E24: =IF(D24=0,"",_xlfn.MINIFS('Observed lines'!$G$2:$G$36,'Observed lines'!$F$2:$F$36,A24)) -> 2.12 | F24: =IF(D24=0,"",_xlfn.MAXIFS('Observed lines'!$G$2:$G$36,'Observed lines'!$F$2:$F$36,A24)) -> 10.32 | G24: =IF(D24=0,"none seen",IF(E24=F24,TEXT(E24,"$#,##0.00"),TEXT(E24,"$#,##0.00")&" – "&TEXT(F24,"$#,##0.00"))) -> $2.12 – $10.32 | H24: seed + observed | I24: OK
A25: 94761 | B25: MEASURE BLOOD OXYGEN LEVEL | C25: =COUNTIF('Observed lines'!$F$2:$F$36,A25) -> 2 | D25: =COUNTIFS('Observed lines'!$F$2:$F$36,A25,'Observed lines'!$G$2:$G$36,"<>") -> 2 | E25: =IF(D25=0,"",_xlfn.MINIFS('Observed lines'!$G$2:$G$36,'Observed lines'!$F$2:$F$36,A25)) -> 29.41 | F25: =IF(D25=0,"",_xlfn.MAXIFS('Observed lines'!$G$2:$G$36,'Observed lines'!$F$2:$F$36,A25)) -> 143.2 | G25: =IF(D25=0,"none seen",IF(E25=F25,TEXT(E25,"$#,##0.00"),TEXT(E25,"$#,##0.00")&" – "&TEXT(F25,"$#,##0.00"))) -> $29.41 – $143.20 | H25: seed + observed | I25: OK
A26: 96374 | C26: =COUNTIF('Observed lines'!$F$2:$F$36,A26) -> 0 | D26: =COUNTIFS('Observed lines'!$F$2:$F$36,A26,'Observed lines'!$G$2:$G$36,"<>") -> 0 | E26: =IF(D26=0,"",_xlfn.MINIFS('Observed lines'!$G$2:$G$36,'Observed lines'!$F$2:$F$36,A26)) | F26: =IF(D26=0,"",_xlfn.MAXIFS('Observed lines'!$G$2:$G$36,'Observed lines'!$F$2:$F$36,A26)) | G26: =IF(D26=0,"none seen",IF(E26=F26,TEXT(E26,"$#,##0.00"),TEXT(E26,"$#,##0.00")&" – "&TEXT(F26,"$#,##0.00"))) -> none seen | H26: seed (business list) | I26: OK
A27: 93005 | C27: =COUNTIF('Observed lines'!$F$2:$F$36,A27) -> 0 | D27: =COUNTIFS('Observed lines'!$F$2:$F$36,A27,'Observed lines'!$G$2:$G$36,"<>") -> 0 | E27: =IF(D27=0,"",_xlfn.MINIFS('Observed lines'!$G$2:$G$36,'Observed lines'!$F$2:$F$36,A27)) | F27: =IF(D27=0,"",_xlfn.MAXIFS('Observed lines'!$G$2:$G$36,'Observed lines'!$F$2:$F$36,A27)) | G27: =IF(D27=0,"none seen",IF(E27=F27,TEXT(E27,"$#,##0.00"),TEXT(E27,"$#,##0.00")&" – "&TEXT(F27,"$#,##0.00"))) -> none seen | H27: seed (business list) | I27: OK
A28: E0445 | C28: =COUNTIF('Observed lines'!$F$2:$F$36,A28) -> 0 | D28: =COUNTIFS('Observed lines'!$F$2:$F$36,A28,'Observed lines'!$G$2:$G$36,"<>") -> 0 | E28: =IF(D28=0,"",_xlfn.MINIFS('Observed lines'!$G$2:$G$36,'Observed lines'!$F$2:$F$36,A28)) | F28: =IF(D28=0,"",_xlfn.MAXIFS('Observed lines'!$G$2:$G$36,'Observed lines'!$F$2:$F$36,A28)) | G28: =IF(D28=0,"none seen",IF(E28=F28,TEXT(E28,"$#,##0.00"),TEXT(E28,"$#,##0.00")&" – "&TEXT(F28,"$#,##0.00"))) -> none seen | H28: seed (business list) | I28: OK
A29: 96361 | C29: =COUNTIF('Observed lines'!$F$2:$F$36,A29) -> 0 | D29: =COUNTIFS('Observed lines'!$F$2:$F$36,A29,'Observed lines'!$G$2:$G$36,"<>") -> 0 | E29: =IF(D29=0,"",_xlfn.MINIFS('Observed lines'!$G$2:$G$36,'Observed lines'!$F$2:$F$36,A29)) | F29: =IF(D29=0,"",_xlfn.MAXIFS('Observed lines'!$G$2:$G$36,'Observed lines'!$F$2:$F$36,A29)) | G29: =IF(D29=0,"none seen",IF(E29=F29,TEXT(E29,"$#,##0.00"),TEXT(E29,"$#,##0.00")&" – "&TEXT(F29,"$#,##0.00"))) -> none seen | H29: seed (business list) | I29: OK
A30: 99239 | C30: =COUNTIF('Observed lines'!$F$2:$F$36,A30) -> 0 | D30: =COUNTIFS('Observed lines'!$F$2:$F$36,A30,'Observed lines'!$G$2:$G$36,"<>") -> 0 | E30: =IF(D30=0,"",_xlfn.MINIFS('Observed lines'!$G$2:$G$36,'Observed lines'!$F$2:$F$36,A30)) | F30: =IF(D30=0,"",_xlfn.MAXIFS('Observed lines'!$G$2:$G$36,'Observed lines'!$F$2:$F$36,A30)) | G30: =IF(D30=0,"none seen",IF(E30=F30,TEXT(E30,"$#,##0.00"),TEXT(E30,"$#,##0.00")&" – "&TEXT(F30,"$#,##0.00"))) -> none seen | H30: seed (business list) | I30: OK
A31: G0378 | C31: =COUNTIF('Observed lines'!$F$2:$F$36,A31) -> 0 | D31: =COUNTIFS('Observed lines'!$F$2:$F$36,A31,'Observed lines'!$G$2:$G$36,"<>") -> 0 | E31: =IF(D31=0,"",_xlfn.MINIFS('Observed lines'!$G$2:$G$36,'Observed lines'!$F$2:$F$36,A31)) | F31: =IF(D31=0,"",_xlfn.MAXIFS('Observed lines'!$G$2:$G$36,'Observed lines'!$F$2:$F$36,A31)) | G31: =IF(D31=0,"none seen",IF(E31=F31,TEXT(E31,"$#,##0.00"),TEXT(E31,"$#,##0.00")&" – "&TEXT(F31,"$#,##0.00"))) -> none seen | H31: seed (business list) | I31: OK
A32: 73552 | C32: =COUNTIF('Observed lines'!$F$2:$F$36,A32) -> 0 | D32: =COUNTIFS('Observed lines'!$F$2:$F$36,A32,'Observed lines'!$G$2:$G$36,"<>") -> 0 | E32: =IF(D32=0,"",_xlfn.MINIFS('Observed lines'!$G$2:$G$36,'Observed lines'!$F$2:$F$36,A32)) | F32: =IF(D32=0,"",_xlfn.MAXIFS('Observed lines'!$G$2:$G$36,'Observed lines'!$F$2:$F$36,A32)) | G32: =IF(D32=0,"none seen",IF(E32=F32,TEXT(E32,"$#,##0.00"),TEXT(E32,"$#,##0.00")&" – "&TEXT(F32,"$#,##0.00"))) -> none seen | H32: seed (business list) | I32: OK
A33: 71250 | C33: =COUNTIF('Observed lines'!$F$2:$F$36,A33) -> 0 | D33: =COUNTIFS('Observed lines'!$F$2:$F$36,A33,'Observed lines'!$G$2:$G$36,"<>") -> 0 | E33: =IF(D33=0,"",_xlfn.MINIFS('Observed lines'!$G$2:$G$36,'Observed lines'!$F$2:$F$36,A33)) | F33: =IF(D33=0,"",_xlfn.MAXIFS('Observed lines'!$G$2:$G$36,'Observed lines'!$F$2:$F$36,A33)) | G33: =IF(D33=0,"none seen",IF(E33=F33,TEXT(E33,"$#,##0.00"),TEXT(E33,"$#,##0.00")&" – "&TEXT(F33,"$#,##0.00"))) -> none seen | H33: seed (business list) | I33: OK
A34: Q9967 | C34: =COUNTIF('Observed lines'!$F$2:$F$36,A34) -> 0 | D34: =COUNTIFS('Observed lines'!$F$2:$F$36,A34,'Observed lines'!$G$2:$G$36,"<>") -> 0 | E34: =IF(D34=0,"",_xlfn.MINIFS('Observed lines'!$G$2:$G$36,'Observed lines'!$F$2:$F$36,A34)) | F34: =IF(D34=0,"",_xlfn.MAXIFS('Observed lines'!$G$2:$G$36,'Observed lines'!$F$2:$F$36,A34)) | G34: =IF(D34=0,"none seen",IF(E34=F34,TEXT(E34,"$#,##0.00"),TEXT(E34,"$#,##0.00")&" – "&TEXT(F34,"$#,##0.00"))) -> none seen | H34: seed (business list) | I34: OK
A35: 94760 | C35: =COUNTIF('Observed lines'!$F$2:$F$36,A35) -> 0 | D35: =COUNTIFS('Observed lines'!$F$2:$F$36,A35,'Observed lines'!$G$2:$G$36,"<>") -> 0 | E35: =IF(D35=0,"",_xlfn.MINIFS('Observed lines'!$G$2:$G$36,'Observed lines'!$F$2:$F$36,A35)) | F35: =IF(D35=0,"",_xlfn.MAXIFS('Observed lines'!$G$2:$G$36,'Observed lines'!$F$2:$F$36,A35)) | G35: =IF(D35=0,"none seen",IF(E35=F35,TEXT(E35,"$#,##0.00"),TEXT(E35,"$#,##0.00")&" – "&TEXT(F35,"$#,##0.00"))) -> none seen | H35: seed (business list) | I35: OK
A36: 90471 | C36: =COUNTIF('Observed lines'!$F$2:$F$36,A36) -> 0 | D36: =COUNTIFS('Observed lines'!$F$2:$F$36,A36,'Observed lines'!$G$2:$G$36,"<>") -> 0 | E36: =IF(D36=0,"",_xlfn.MINIFS('Observed lines'!$G$2:$G$36,'Observed lines'!$F$2:$F$36,A36)) | F36: =IF(D36=0,"",_xlfn.MAXIFS('Observed lines'!$G$2:$G$36,'Observed lines'!$F$2:$F$36,A36)) | G36: =IF(D36=0,"none seen",IF(E36=F36,TEXT(E36,"$#,##0.00"),TEXT(E36,"$#,##0.00")&" – "&TEXT(F36,"$#,##0.00"))) -> none seen | H36: seed (business list) | I36: OK
A37: 74022 | C37: =COUNTIF('Observed lines'!$F$2:$F$36,A37) -> 0 | D37: =COUNTIFS('Observed lines'!$F$2:$F$36,A37,'Observed lines'!$G$2:$G$36,"<>") -> 0 | E37: =IF(D37=0,"",_xlfn.MINIFS('Observed lines'!$G$2:$G$36,'Observed lines'!$F$2:$F$36,A37)) | F37: =IF(D37=0,"",_xlfn.MAXIFS('Observed lines'!$G$2:$G$36,'Observed lines'!$F$2:$F$36,A37)) | G37: =IF(D37=0,"none seen",IF(E37=F37,TEXT(E37,"$#,##0.00"),TEXT(E37,"$#,##0.00")&" – "&TEXT(F37,"$#,##0.00"))) -> none seen | H37: seed (business list) | I37: OK
... A40: 73110 | C40: =COUNTIF('Observed lines'!$F$2:$F$36,A40) -> 0 | D40: =COUNTIFS('Observed lines'!$F$2:$F$36,A40,'Observed lines'!$G$2:$G$36,"<>") -> 0 | E40: =IF(D40=0,"",_xlfn.MINIFS('Observed lines'!$G$2:$G$36,'Observed lines'!$F$2:$F$36,A40)) | F40: =IF(D40=0,"",_xlfn.MAXIFS('Observed lines'!$G$2:$G$36,'Observed lines'!$F$2:$F$36,A40)) | G40: =IF(D40=0,"none seen",IF(E40=F40,TEXT(E40,"$#,##0.00"),TEXT(E40,"$#,##0.00")&" – "&TEXT(F40,"$#,##0.00"))) -> none seen | H40: seed (business list) | I40: OK
A41: 72128 | B41: Computed tomography, thoracic spine | C41: =COUNTIF('Observed lines'!$F$2:$F$36,A41) -> 1 | D41: =COUNTIFS('Observed lines'!$F$2:$F$36,A41,'Observed lines'!$G$2:$G$36,"<>") -> 1 | E41: =IF(D41=0,"",_xlfn.MINIFS('Observed lines'!$G$2:$G$36,'Observed lines'!$F$2:$F$36,A41)) -> 228.66 | F41: =IF(D41=0,"",_xlfn.MAXIFS('Observed lines'!$G$2:$G$36,'Observed lines'!$F$2:$F$36,A41)) -> 228.66 | G41: =IF(D41=0,"none seen",IF(E41=F41,TEXT(E41,"$#,##0.00"),TEXT(E41,"$#,##0.00")&" – "&TEXT(F41,"$#,##0.00"))) -> $228.66 | H41: seed + observed | I41: OK
A42: 93971 | C42: =COUNTIF('Observed lines'!$F$2:$F$36,A42) -> 0 | D42: =COUNTIFS('Observed lines'!$F$2:$F$36,A42,'Observed lines'!$G$2:$G$36,"<>") -> 0 | E42: =IF(D42=0,"",_xlfn.MINIFS('Observed lines'!$G$2:$G$36,'Observed lines'!$F$2:$F$36,A42)) | F42: =IF(D42=0,"",_xlfn.MAXIFS('Observed lines'!$G$2:$G$36,'Observed lines'!$F$2:$F$36,A42)) | G42: =IF(D42=0,"none seen",IF(E42=F42,TEXT(E42,"$#,##0.00"),TEXT(E42,"$#,##0.00")&" – "&TEXT(F42,"$#,##0.00"))) -> none seen | H42: seed (business list) | I42: OK
A43: 70486 | C43: =COUNTIF('Observed lines'!$F$2:$F$36,A43) -> 0 | D43: =COUNTIFS('Observed lines'!$F$2:$F$36,A43,'Observed lines'!$G$2:$G$36,"<>") -> 0 | E43: =IF(D43=0,"",_xlfn.MINIFS('Observed lines'!$G$2:$G$36,'Observed lines'!$F$2:$F$36,A43)) | F43: =IF(D43=0,"",_xlfn.MAXIFS('Observed lines'!$G$2:$G$36,'Observed lines'!$F$2:$F$36,A43)) | G43: =IF(D43=0,"none seen",IF(E43=F43,TEXT(E43,"$#,##0.00"),TEXT(E43,"$#,##0.00")&" – "&TEXT(F43,"$#,##0.00"))) -> none seen | H43: seed (business list) | I43: OK
A44: 87507 | C44: =COUNTIF('Observed lines'!$F$2:$F$36,A44) -> 0 | D44: =COUNTIFS('Observed lines'!$F$2:$F$36,A44,'Observed lines'!$G$2:$G$36,"<>") -> 0 | E44: =IF(D44=0,"",_xlfn.MINIFS('Observed lines'!$G$2:$G$36,'Observed lines'!$F$2:$F$36,A44)) | F44: =IF(D44=0,"",_xlfn.MAXIFS('Observed lines'!$G$2:$G$36,'Observed lines'!$F$2:$F$36,A44)) | G44: =IF(D44=0,"none seen",IF(E44=F44,TEXT(E44,"$#,##0.00"),TEXT(E44,"$#,##0.00")&" – "&TEXT(F44,"$#,##0.00"))) -> none seen | H44: seed (business list) | I44: OK
A45: L3809 | C45: =COUNTIF('Observed lines'!$F$2:$F$36,A45) -> 0 | D45: =COUNTIFS('Observed lines'!$F$2:$F$36,A45,'Observed lines'!$G$2:$G$36,"<>") -> 0 | E45: =IF(D45=0,"",_xlfn.MINIFS('Observed lines'!$G$2:$G$36,'Observed lines'!$F$2:$F$36,A45)) | F45: =IF(D45=0,"",_xlfn.MAXIFS('Observed lines'!$G$2:$G$36,'Observed lines'!$F$2:$F$36,A45)) | G45: =IF(D45=0,"none seen",IF(E45=F45,TEXT(E45,"$#,##0.00"),TEXT(E45,"$#,##0.00")&" – "&TEXT(F45,"$#,##0.00"))) -> none seen | H45: seed (business list) | I45: OK
A46: A4649 | C46: =COUNTIF('Observed lines'!$F$2:$F$36,A46) -> 0 | D46: =COUNTIFS('Observed lines'!$F$2:$F$36,A46,'Observed lines'!$G$2:$G$36,"<>") -> 0 | E46: =IF(D46=0,"",_xlfn.MINIFS('Observed lines'!$G$2:$G$36,'Observed lines'!$F$2:$F$36,A46)) | F46: =IF(D46=0,"",_xlfn.MAXIFS('Observed lines'!$G$2:$G$36,'Observed lines'!$F$2:$F$36,A46)) | G46: =IF(D46=0,"none seen",IF(E46=F46,TEXT(E46,"$#,##0.00"),TEXT(E46,"$#,##0.00")&" – "&TEXT(F46,"$#,##0.00"))) -> none seen | H46: seed (business list) | I46: OK
A47: 12013 | C47: =COUNTIF('Observed lines'!$F$2:$F$36,A47) -> 0 | D47: =COUNTIFS('Observed lines'!$F$2:$F$36,A47,'Observed lines'!$G$2:$G$36,"<>") -> 0 | E47: =IF(D47=0,"",_xlfn.MINIFS('Observed lines'!$G$2:$G$36,'Observed lines'!$F$2:$F$36,A47)) | F47: =IF(D47=0,"",_xlfn.MAXIFS('Observed lines'!$G$2:$G$36,'Observed lines'!$F$2:$F$36,A47)) | G47: =IF(D47=0,"none seen",IF(E47=F47,TEXT(E47,"$#,##0.00"),TEXT(E47,"$#,##0.00")&" – "&TEXT(F47,"$#,##0.00"))) -> none seen | H47: seed (business list) | I47: OK
A48: 73130 | C48: =COUNTIF('Observed lines'!$F$2:$F$36,A48) -> 0 | D48: =COUNTIFS('Observed lines'!$F$2:$F$36,A48,'Observed lines'!$G$2:$G$36,"<>") -> 0 | E48: =IF(D48=0,"",_xlfn.MINIFS('Observed lines'!$G$2:$G$36,'Observed lines'!$F$2:$F$36,A48)) | F48: =IF(D48=0,"",_xlfn.MAXIFS('Observed lines'!$G$2:$G$36,'Observed lines'!$F$2:$F$36,A48)) | G48: =IF(D48=0,"none seen",IF(E48=F48,TEXT(E48,"$#,##0.00"),TEXT(E48,"$#,##0.00")&" – "&TEXT(F48,"$#,##0.00"))) -> none seen | H48: seed (business list) | I48: OK
A49: A4467 | C49: =COUNTIF('Observed lines'!$F$2:$F$36,A49) -> 0 | D49: =COUNTIFS('Observed lines'!$F$2:$F$36,A49,'Observed lines'!$G$2:$G$36,"<>") -> 0 | E49: =IF(D49=0,"",_xlfn.MINIFS('Observed lines'!$G$2:$G$36,'Observed lines'!$F$2:$F$36,A49)) | F49: =IF(D49=0,"",_xlfn.MAXIFS('Observed lines'!$G$2:$G$36,'Observed lines'!$F$2:$F$36,A49)) | G49: =IF(D49=0,"none seen",IF(E49=F49,TEXT(E49,"$#,##0.00"),TEXT(E49,"$#,##0.00")&" – "&TEXT(F49,"$#,##0.00"))) -> none seen | H49: seed (business list) | I49: OK
A50: 76830 | C50: =COUNTIF('Observed lines'!$F$2:$F$36,A50) -> 0 | D50: =COUNTIFS('Observed lines'!$F$2:$F$36,A50,'Observed lines'!$G$2:$G$36,"<>") -> 0 | E50: =IF(D50=0,"",_xlfn.MINIFS('Observed lines'!$G$2:$G$36,'Observed lines'!$F$2:$F$36,A50)) | F50: =IF(D50=0,"",_xlfn.MAXIFS('Observed lines'!$G$2:$G$36,'Observed lines'!$F$2:$F$36,A50)) | G50: =IF(D50=0,"none seen",IF(E50=F50,TEXT(E50,"$#,##0.00"),TEXT(E50,"$#,##0.00")&" – "&TEXT(F50,"$#,##0.00"))) -> none seen | H50: seed (business list) | I50: OK
A51: 74019 | C51: =COUNTIF('Observed lines'!$F$2:$F$36,A51) -> 0 | D51: =COUNTIFS('Observed lines'!$F$2:$F$36,A51,'Observed lines'!$G$2:$G$36,"<>") -> 0 | E51: =IF(D51=0,"",_xlfn.MINIFS('Observed lines'!$G$2:$G$36,'Observed lines'!$F$2:$F$36,A51)) | F51: =IF(D51=0,"",_xlfn.MAXIFS('Observed lines'!$G$2:$G$36,'Observed lines'!$F$2:$F$36,A51)) | G51: =IF(D51=0,"none seen",IF(E51=F51,TEXT(E51,"$#,##0.00"),TEXT(E51,"$#,##0.00")&" – "&TEXT(F51,"$#,##0.00"))) -> none seen | H51: seed (business list) | I51: OK
A52: 73610 | C52: =COUNTIF('Observed lines'!$F$2:$F$36,A52) -> 0 | D52: =COUNTIFS('Observed lines'!$F$2:$F$36,A52,'Observed lines'!$G$2:$G$36,"<>") -> 0 | E52: =IF(D52=0,"",_xlfn.MINIFS('Observed lines'!$G$2:$G$36,'Observed lines'!$F$2:$F$36,A52)) | F52: =IF(D52=0,"",_xlfn.MAXIFS('Observed lines'!$G$2:$G$36,'Observed lines'!$F$2:$F$36,A52)) | G52: =IF(D52=0,"none seen",IF(E52=F52,TEXT(E52,"$#,##0.00"),TEXT(E52,"$#,##0.00")&" – "&TEXT(F52,"$#,##0.00"))) -> none seen | H52: seed (business list) | I52: OK
A53: 10120 | C53: =COUNTIF('Observed lines'!$F$2:$F$36,A53) -> 0 | D53: =COUNTIFS('Observed lines'!$F$2:$F$36,A53,'Observed lines'!$G$2:$G$36,"<>") -> 0 | E53: =IF(D53=0,"",_xlfn.MINIFS('Observed lines'!$G$2:$G$36,'Observed lines'!$F$2:$F$36,A53)) | F53: =IF(D53=0,"",_xlfn.MAXIFS('Observed lines'!$G$2:$G$36,'Observed lines'!$F$2:$F$36,A53)) | G53: =IF(D53=0,"none seen",IF(E53=F53,TEXT(E53,"$#,##0.00"),TEXT(E53,"$#,##0.00")&" – "&TEXT(F53,"$#,##0.00"))) -> none seen | H53: seed (business list) | I53: OK
... A58: 85379 | C58: =COUNTIF('Observed lines'!$F$2:$F$36,A58) -> 0 | D58: =COUNTIFS('Observed lines'!$F$2:$F$36,A58,'Observed lines'!$G$2:$G$36,"<>") -> 0 | E58: =IF(D58=0,"",_xlfn.MINIFS('Observed lines'!$G$2:$G$36,'Observed lines'!$F$2:$F$36,A58)) | F58: =IF(D58=0,"",_xlfn.MAXIFS('Observed lines'!$G$2:$G$36,'Observed lines'!$F$2:$F$36,A58)) | G58: =IF(D58=0,"none seen",IF(E58=F58,TEXT(E58,"$#,##0.00"),TEXT(E58,"$#,##0.00")&" – "&TEXT(F58,"$#,##0.00"))) -> none seen | H58: seed (business list) | I58: OK
A59: 85025 | B59: COMPLETE CBC W/AUTO DIFF WBC | C59: =COUNTIF('Observed lines'!$F$2:$F$36,A59) -> 1 | D59: =COUNTIFS('Observed lines'!$F$2:$F$36,A59,'Observed lines'!$G$2:$G$36,"<>") -> 0 | E59: =IF(D59=0,"",_xlfn.MINIFS('Observed lines'!$G$2:$G$36,'Observed lines'!$F$2:$F$36,A59)) | F59: =IF(D59=0,"",_xlfn.MAXIFS('Observed lines'!$G$2:$G$36,'Observed lines'!$F$2:$F$36,A59)) | G59: =IF(D59=0,"none seen",IF(E59=F59,TEXT(E59,"$#,##0.00"),TEXT(E59,"$#,##0.00")&" – "&TEXT(F59,"$#,##0.00"))) -> none seen | H59: seed + observed | I59: OK
A60: 29584 | C60: =COUNTIF('Observed lines'!$F$2:$F$36,A60) -> 0 | D60: =COUNTIFS('Observed lines'!$F$2:$F$36,A60,'Observed lines'!$G$2:$G$36,"<>") -> 0 | E60: =IF(D60=0,"",_xlfn.MINIFS('Observed lines'!$G$2:$G$36,'Observed lines'!$F$2:$F$36,A60)) | F60: =IF(D60=0,"",_xlfn.MAXIFS('Observed lines'!$G$2:$G$36,'Observed lines'!$F$2:$F$36,A60)) | G60: =IF(D60=0,"none seen",IF(E60=F60,TEXT(E60,"$#,##0.00"),TEXT(E60,"$#,##0.00")&" – "&TEXT(F60,"$#,##0.00"))) -> none seen | H60: seed (business list) | I60: OK
A61: 80051 | B61: ELECTROLYTE PANEL | C61: =COUNTIF('Observed lines'!$F$2:$F$36,A61) -> 1 | D61: =COUNTIFS('Observed lines'!$F$2:$F$36,A61,'Observed lines'!$G$2:$G$36,"<>") -> 0 | E61: =IF(D61=0,"",_xlfn.MINIFS('Observed lines'!$G$2:$G$36,'Observed lines'!$F$2:$F$36,A61)) | F61: =IF(D61=0,"",_xlfn.MAXIFS('Observed lines'!$G$2:$G$36,'Observed lines'!$F$2:$F$36,A61)) | G61: =IF(D61=0,"none seen",IF(E61=F61,TEXT(E61,"$#,##0.00"),TEXT(E61,"$#,##0.00")&" – "&TEXT(F61,"$#,##0.00"))) -> none seen | H61: seed + observed | I61: OK
A62: 82550 | B62: ASSAY OF CK (CPK) | C62: =COUNTIF('Observed lines'!$F$2:$F$36,A62) -> 1 | D62: =COUNTIFS('Observed lines'!$F$2:$F$36,A62,'Observed lines'!$G$2:$G$36,"<>") -> 0 | E62: =IF(D62=0,"",_xlfn.MINIFS('Observed lines'!$G$2:$G$36,'Observed lines'!$F$2:$F$36,A62)) | F62: =IF(D62=0,"",_xlfn.MAXIFS('Observed lines'!$G$2:$G$36,'Observed lines'!$F$2:$F$36,A62)) | G62: =IF(D62=0,"none seen",IF(E62=F62,TEXT(E62,"$#,##0.00"),TEXT(E62,"$#,##0.00")&" – "&TEXT(F62,"$#,##0.00"))) -> none seen | H62: seed + observed | I62: OK
A63: 82565 | B63: ASSAY OF CREATININE | C63: =COUNTIF('Observed lines'!$F$2:$F$36,A63) -> 1 | D63: =COUNTIFS('Observed lines'!$F$2:$F$36,A63,'Observed lines'!$G$2:$G$36,"<>") -> 0 | E63: =IF(D63=0,"",_xlfn.MINIFS('Observed lines'!$G$2:$G$36,'Observed lines'!$F$2:$F$36,A63)) | F63: =IF(D63=0,"",_xlfn.MAXIFS('Observed lines'!$G$2:$G$36,'Observed lines'!$F$2:$F$36,A63)) | G63: =IF(D63=0,"none seen",IF(E63=F63,TEXT(E63,"$#,##0.00"),TEXT(E63,"$#,##0.00")&" – "&TEXT(F63,"$#,##0.00"))) -> none seen | H63: seed + observed | I63: OK
A64: 82947 | B64: ASSAY, GLUCOSE, BLOOD QUANT | C64: =COUNTIF('Observed lines'!$F$2:$F$36,A64) -> 1 | D64: =COUNTIFS('Observed lines'!$F$2:$F$36,A64,'Observed lines'!$G$2:$G$36,"<>") -> 0 | E64: =IF(D64=0,"",_xlfn.MINIFS('Observed lines'!$G$2:$G$36,'Observed lines'!$F$2:$F$36,A64)) | F64: =IF(D64=0,"",_xlfn.MAXIFS('Observed lines'!$G$2:$G$36,'Observed lines'!$F$2:$F$36,A64)) | G64: =IF(D64=0,"none seen",IF(E64=F64,TEXT(E64,"$#,##0.00"),TEXT(E64,"$#,##0.00")&" – "&TEXT(F64,"$#,##0.00"))) -> none seen | H64: seed + observed | I64: OK
A65: 84520 | B65: ASSAY OF UREA NITROGEN | C65: =COUNTIF('Observed lines'!$F$2:$F$36,A65) -> 1 | D65: =COUNTIFS('Observed lines'!$F$2:$F$36,A65,'Observed lines'!$G$2:$G$36,"<>") -> 0 | E65: =IF(D65=0,"",_xlfn.MINIFS('Observed lines'!$G$2:$G$36,'Observed lines'!$F$2:$F$36,A65)) | F65: =IF(D65=0,"",_xlfn.MAXIFS('Observed lines'!$G$2:$G$36,'Observed lines'!$F$2:$F$36,A65)) | G65: =IF(D65=0,"none seen",IF(E65=F65,TEXT(E65,"$#,##0.00"),TEXT(E65,"$#,##0.00")&" – "&TEXT(F65,"$#,##0.00"))) -> none seen | H65: seed + observed | I65: OK
A66: A4770 | C66: =COUNTIF('Observed lines'!$F$2:$F$36,A66) -> 0 | D66: =COUNTIFS('Observed lines'!$F$2:$F$36,A66,'Observed lines'!$G$2:$G$36,"<>") -> 0 | E66: =IF(D66=0,"",_xlfn.MINIFS('Observed lines'!$G$2:$G$36,'Observed lines'!$F$2:$F$36,A66)) | F66: =IF(D66=0,"",_xlfn.MAXIFS('Observed lines'!$G$2:$G$36,'Observed lines'!$F$2:$F$36,A66)) | G66: =IF(D66=0,"none seen",IF(E66=F66,TEXT(E66,"$#,##0.00"),TEXT(E66,"$#,##0.00")&" – "&TEXT(F66,"$#,##0.00"))) -> none seen | H66: seed (business list) | I66: OK
A67: A9150 | C67: =COUNTIF('Observed lines'!$F$2:$F$36,A67) -> 0 | D67: =COUNTIFS('Observed lines'!$F$2:$F$36,A67,'Observed lines'!$G$2:$G$36,"<>") -> 0 | E67: =IF(D67=0,"",_xlfn.MINIFS('Observed lines'!$G$2:$G$36,'Observed lines'!$F$2:$F$36,A67)) | F67: =IF(D67=0,"",_xlfn.MAXIFS('Observed lines'!$G$2:$G$36,'Observed lines'!$F$2:$F$36,A67)) | G67: =IF(D67=0,"none seen",IF(E67=F67,TEXT(E67,"$#,##0.00"),TEXT(E67,"$#,##0.00")&" – "&TEXT(F67,"$#,##0.00"))) -> none seen | H67: seed (business list) | I67: OK
A68: 70490 | C68: =COUNTIF('Observed lines'!$F$2:$F$36,A68) -> 0 | D68: =COUNTIFS('Observed lines'!$F$2:$F$36,A68,'Observed lines'!$G$2:$G$36,"<>") -> 0 | E68: =IF(D68=0,"",_xlfn.MINIFS('Observed lines'!$G$2:$G$36,'Observed lines'!$F$2:$F$36,A68)) | F68: =IF(D68=0,"",_xlfn.MAXIFS('Observed lines'!$G$2:$G$36,'Observed lines'!$F$2:$F$36,A68)) | G68: =IF(D68=0,"none seen",IF(E68=F68,TEXT(E68,"$#,##0.00"),TEXT(E68,"$#,##0.00")&" – "&TEXT(F68,"$#,##0.00"))) -> none seen | H68: seed (business list) | I68: OK
A69: A4657 | B69: SYRINGE WITH OR WITHOUT NEEDLE EACH | C69: =COUNTIF('Observed lines'!$F$2:$F$36,A69) -> 1 | D69: =COUNTIFS('Observed lines'!$F$2:$F$36,A69,'Observed lines'!$G$2:$G$36,"<>") -> 1 | E69: =IF(D69=0,"",_xlfn.MINIFS('Observed lines'!$G$2:$G$36,'Observed lines'!$F$2:$F$36,A69)) -> 9.11 | F69: =IF(D69=0,"",_xlfn.MAXIFS('Observed lines'!$G$2:$G$36,'Observed lines'!$F$2:$F$36,A69)) -> 9.11 | G69: =IF(D69=0,"none seen",IF(E69=F69,TEXT(E69,"$#,##0.00"),TEXT(E69,"$#,##0.00")&" – "&TEXT(F69,"$#,##0.00"))) -> $9.11 | H69: seed + observed | I69: OK
A70: J7613 | C70: =COUNTIF('Observed lines'!$F$2:$F$36,A70) -> 0 | D70: =COUNTIFS('Observed lines'!$F$2:$F$36,A70,'Observed lines'!$G$2:$G$36,"<>") -> 0 | E70: =IF(D70=0,"",_xlfn.MINIFS('Observed lines'!$G$2:$G$36,'Observed lines'!$F$2:$F$36,A70)) | F70: =IF(D70=0,"",_xlfn.MAXIFS('Observed lines'!$G$2:$G$36,'Observed lines'!$F$2:$F$36,A70)) | G70: =IF(D70=0,"none seen",IF(E70=F70,TEXT(E70,"$#,##0.00"),TEXT(E70,"$#,##0.00")&" – "&TEXT(F70,"$#,##0.00"))) -> none seen | H70: seed (business list) | I70: OK
A71: A4616 | C71: =COUNTIF('Observed lines'!$F$2:$F$36,A71) -> 0 | D71: =COUNTIFS('Observed lines'!$F$2:$F$36,A71,'Observed lines'!$G$2:$G$36,"<>") -> 0 | E71: =IF(D71=0,"",_xlfn.MINIFS('Observed lines'!$G$2:$G$36,'Observed lines'!$F$2:$F$36,A71)) | F71: =IF(D71=0,"",_xlfn.MAXIFS('Observed lines'!$G$2:$G$36,'Observed lines'!$F$2:$F$36,A71)) | G71: =IF(D71=0,"none seen",IF(E71=F71,TEXT(E71,"$#,##0.00"),TEXT(E71,"$#,##0.00")&" – "&TEXT(F71,"$#,##0.00"))) -> none seen | H71: seed (business list) | I71: OK
A72: E0441 | C72: =COUNTIF('Observed lines'!$F$2:$F$36,A72) -> 0 | D72: =COUNTIFS('Observed lines'!$F$2:$F$36,A72,'Observed lines'!$G$2:$G$36,"<>") -> 0 | E72: =IF(D72=0,"",_xlfn.MINIFS('Observed lines'!$G$2:$G$36,'Observed lines'!$F$2:$F$36,A72)) | F72: =IF(D72=0,"",_xlfn.MAXIFS('Observed lines'!$G$2:$G$36,'Observed lines'!$F$2:$F$36,A72)) | G72: =IF(D72=0,"none seen",IF(E72=F72,TEXT(E72,"$#,##0.00"),TEXT(E72,"$#,##0.00")&" – "&TEXT(F72,"$#,##0.00"))) -> none seen | H72: seed (business list) | I72: OK
A73: 86769 | C73: =COUNTIF('Observed lines'!$F$2:$F$36,A73) -> 0 | D73: =COUNTIFS('Observed lines'!$F$2:$F$36,A73,'Observed lines'!$G$2:$G$36,"<>") -> 0 | E73: =IF(D73=0,"",_xlfn.MINIFS('Observed lines'!$G$2:$G$36,'Observed lines'!$F$2:$F$36,A73)) | F73: =IF(D73=0,"",_xlfn.MAXIFS('Observed lines'!$G$2:$G$36,'Observed lines'!$F$2:$F$36,A73)) | G73: =IF(D73=0,"none seen",IF(E73=F73,TEXT(E73,"$#,##0.00"),TEXT(E73,"$#,##0.00")&" – "&TEXT(F73,"$#,##0.00"))) -> none seen | H73: seed (business list) | I73: OK
A74: 87428 | C74: =COUNTIF('Observed lines'!$F$2:$F$36,A74) -> 0 | D74: =COUNTIFS('Observed lines'!$F$2:$F$36,A74,'Observed lines'!$G$2:$G$36,"<>") -> 0 | E74: =IF(D74=0,"",_xlfn.MINIFS('Observed lines'!$G$2:$G$36,'Observed lines'!$F$2:$F$36,A74)) | F74: =IF(D74=0,"",_xlfn.MAXIFS('Observed lines'!$G$2:$G$36,'Observed lines'!$F$2:$F$36,A74)) | G74: =IF(D74=0,"none seen",IF(E74=F74,TEXT(E74,"$#,##0.00"),TEXT(E74,"$#,##0.00")&" – "&TEXT(F74,"$#,##0.00"))) -> none seen | H74: seed (business list) | I74: OK
A75: A6453 | C75: =COUNTIF('Observed lines'!$F$2:$F$36,A75) -> 0 | D75: =COUNTIFS('Observed lines'!$F$2:$F$36,A75,'Observed lines'!$G$2:$G$36,"<>") -> 0 | E75: =IF(D75=0,"",_xlfn.MINIFS('Observed lines'!$G$2:$G$36,'Observed lines'!$F$2:$F$36,A75)) | F75: =IF(D75=0,"",_xlfn.MAXIFS('Observed lines'!$G$2:$G$36,'Observed lines'!$F$2:$F$36,A75)) | G75: =IF(D75=0,"none seen",IF(E75=F75,TEXT(E75,"$#,##0.00"),TEXT(E75,"$#,##0.00")&" – "&TEXT(F75,"$#,##0.00"))) -> none seen | H75: seed (business list) | I75: OK
A76: E1399 | B76: Durable medical equipment, miscellaneous | C76: =COUNTIF('Observed lines'!$F$2:$F$36,A76) -> 1 | D76: =COUNTIFS('Observed lines'!$F$2:$F$36,A76,'Observed lines'!$G$2:$G$36,"<>") -> 1 | E76: =IF(D76=0,"",_xlfn.MINIFS('Observed lines'!$G$2:$G$36,'Observed lines'!$F$2:$F$36,A76)) -> 0.79 | F76: =IF(D76=0,"",_xlfn.MAXIFS('Observed lines'!$G$2:$G$36,'Observed lines'!$F$2:$F$36,A76)) -> 0.79 | G76: =IF(D76=0,"none seen",IF(E76=F76,TEXT(E76,"$#,##0.00"),TEXT(E76,"$#,##0.00")&" – "&TEXT(F76,"$#,##0.00"))) -> $0.79 | H76: seed + observed | I76: OK
A77: A4930 | B77: GLOVES STERILE PER PAIR | C77: =COUNTIF('Observed lines'!$F$2:$F$36,A77) -> 1 | D77: =COUNTIFS('Observed lines'!$F$2:$F$36,A77,'Observed lines'!$G$2:$G$36,"<>") -> 1 | E77: =IF(D77=0,"",_xlfn.MINIFS('Observed lines'!$G$2:$G$36,'Observed lines'!$F$2:$F$36,A77)) -> 28.87 | F77: =IF(D77=0,"",_xlfn.MAXIFS('Observed lines'!$G$2:$G$36,'Observed lines'!$F$2:$F$36,A77)) -> 28.87 | G77: =IF(D77=0,"none seen",IF(E77=F77,TEXT(E77,"$#,##0.00"),TEXT(E77,"$#,##0.00")&" – "&TEXT(F77,"$#,##0.00"))) -> $28.87 | H77: seed + observed | I77: OK
A78: 73562 | C78: =COUNTIF('Observed lines'!$F$2:$F$36,A78) -> 0 | D78: =COUNTIFS('Observed lines'!$F$2:$F$36,A78,'Observed lines'!$G$2:$G$36,"<>") -> 0 | E78: =IF(D78=0,"",_xlfn.MINIFS('Observed lines'!$G$2:$G$36,'Observed lines'!$F$2:$F$36,A78)) | F78: =IF(D78=0,"",_xlfn.MAXIFS('Observed lines'!$G$2:$G$36,'Observed lines'!$F$2:$F$36,A78)) | G78: =IF(D78=0,"none seen",IF(E78=F78,TEXT(E78,"$#,##0.00"),TEXT(E78,"$#,##0.00")&" – "&TEXT(F78,"$#,##0.00"))) -> none seen | H78: seed (business list) | I78: OK
A79: 73080 | C79: =COUNTIF('Observed lines'!$F$2:$F$36,A79) -> 0 | D79: =COUNTIFS('Observed lines'!$F$2:$F$36,A79,'Observed lines'!$G$2:$G$36,"<>") -> 0 | E79: =IF(D79=0,"",_xlfn.MINIFS('Observed lines'!$G$2:$G$36,'Observed lines'!$F$2:$F$36,A79)) | F79: =IF(D79=0,"",_xlfn.MAXIFS('Observed lines'!$G$2:$G$36,'Observed lines'!$F$2:$F$36,A79)) | G79: =IF(D79=0,"none seen",IF(E79=F79,TEXT(E79,"$#,##0.00"),TEXT(E79,"$#,##0.00")&" – "&TEXT(F79,"$#,##0.00"))) -> none seen | H79: seed (business list) | I79: OK
A80: A6449 | C80: =COUNTIF('Observed lines'!$F$2:$F$36,A80) -> 0 | D80: =COUNTIFS('Observed lines'!$F$2:$F$36,A80,'Observed lines'!$G$2:$G$36,"<>") -> 0 | E80: =IF(D80=0,"",_xlfn.MINIFS('Observed lines'!$G$2:$G$36,'Observed lines'!$F$2:$F$36,A80)) | F80: =IF(D80=0,"",_xlfn.MAXIFS('Observed lines'!$G$2:$G$36,'Observed lines'!$F$2:$F$36,A80)) | G80: =IF(D80=0,"none seen",IF(E80=F80,TEXT(E80,"$#,##0.00"),TEXT(E80,"$#,##0.00")&" – "&TEXT(F80,"$#,##0.00"))) -> none seen | H80: seed (business list) | I80: OK
A81: A4223 | C81: =COUNTIF('Observed lines'!$F$2:$F$36,A81) -> 0 | D81: =COUNTIFS('Observed lines'!$F$2:$F$36,A81,'Observed lines'!$G$2:$G$36,"<>") -> 0 | E81: =IF(D81=0,"",_xlfn.MINIFS('Observed lines'!$G$2:$G$36,'Observed lines'!$F$2:$F$36,A81)) | F81: =IF(D81=0,"",_xlfn.MAXIFS('Observed lines'!$G$2:$G$36,'Observed lines'!$F$2:$F$36,A81)) | G81: =IF(D81=0,"none seen",IF(E81=F81,TEXT(E81,"$#,##0.00"),TEXT(E81,"$#,##0.00")&" – "&TEXT(F81,"$#,##0.00"))) -> none seen | H81: seed (business list) | I81: OK
A82: 82247 | C82: =COUNTIF('Observed lines'!$F$2:$F$36,A82) -> 0 | D82: =COUNTIFS('Observed lines'!$F$2:$F$36,A82,'Observed lines'!$G$2:$G$36,"<>") -> 0 | E82: =IF(D82=0,"",_xlfn.MINIFS('Observed lines'!$G$2:$G$36,'Observed lines'!$F$2:$F$36,A82)) | F82: =IF(D82=0,"",_xlfn.MAXIFS('Observed lines'!$G$2:$G$36,'Observed lines'!$F$2:$F$36,A82)) | G82: =IF(D82=0,"none seen",IF(E82=F82,TEXT(E82,"$#,##0.00"),TEXT(E82,"$#,##0.00")&" – "&TEXT(F82,"$#,##0.00"))) -> none seen | H82: seed (business list) | I82: OK
A83: 82040 | C83: =COUNTIF('Observed lines'!$F$2:$F$36,A83) -> 0 | D83: =COUNTIFS('Observed lines'!$F$2:$F$36,A83,'Observed lines'!$G$2:$G$36,"<>") -> 0 | E83: =IF(D83=0,"",_xlfn.MINIFS('Observed lines'!$G$2:$G$36,'Observed lines'!$F$2:$F$36,A83)) | F83: =IF(D83=0,"",_xlfn.MAXIFS('Observed lines'!$G$2:$G$36,'Observed lines'!$F$2:$F$36,A83)) | G83: =IF(D83=0,"none seen",IF(E83=F83,TEXT(E83,"$#,##0.00"),TEXT(E83,"$#,##0.00")&" – "&TEXT(F83,"$#,##0.00"))) -> none seen | H83: seed (business list) | I83: OK
A84: 81003 | B84: URINALYSIS, AUTO, W/O SCOPE | C84: =COUNTIF('Observed lines'!$F$2:$F$36,A84) -> 1 | D84: =COUNTIFS('Observed lines'!$F$2:$F$36,A84,'Observed lines'!$G$2:$G$36,"<>") -> 0 | E84: =IF(D84=0,"",_xlfn.MINIFS('Observed lines'!$G$2:$G$36,'Observed lines'!$F$2:$F$36,A84)) | F84: =IF(D84=0,"",_xlfn.MAXIFS('Observed lines'!$G$2:$G$36,'Observed lines'!$F$2:$F$36,A84)) | G84: =IF(D84=0,"none seen",IF(E84=F84,TEXT(E84,"$#,##0.00"),TEXT(E84,"$#,##0.00")&" – "&TEXT(F84,"$#,##0.00"))) -> none seen | H84: seed + observed | I84: OK
A85: 84075 | C85: =COUNTIF('Observed lines'!$F$2:$F$36,A85) -> 0 | D85: =COUNTIFS('Observed lines'!$F$2:$F$36,A85,'Observed lines'!$G$2:$G$36,"<>") -> 0 | E85: =IF(D85=0,"",_xlfn.MINIFS('Observed lines'!$G$2:$G$36,'Observed lines'!$F$2:$F$36,A85)) | F85: =IF(D85=0,"",_xlfn.MAXIFS('Observed lines'!$G$2:$G$36,'Observed lines'!$F$2:$F$36,A85)) | G85: =IF(D85=0,"none seen",IF(E85=F85,TEXT(E85,"$#,##0.00"),TEXT(E85,"$#,##0.00")&" – "&TEXT(F85,"$#,##0.00"))) -> none seen | H85: seed (business list) | I85: OK
A86: 84450 | C86: =COUNTIF('Observed lines'!$F$2:$F$36,A86) -> 0 | D86: =COUNTIFS('Observed lines'!$F$2:$F$36,A86,'Observed lines'!$G$2:$G$36,"<>") -> 0 | E86: =IF(D86=0,"",_xlfn.MINIFS('Observed lines'!$G$2:$G$36,'Observed lines'!$F$2:$F$36,A86)) | F86: =IF(D86=0,"",_xlfn.MAXIFS('Observed lines'!$G$2:$G$36,'Observed lines'!$F$2:$F$36,A86)) | G86: =IF(D86=0,"none seen",IF(E86=F86,TEXT(E86,"$#,##0.00"),TEXT(E86,"$#,##0.00")&" – "&TEXT(F86,"$#,##0.00"))) -> none seen | H86: seed (business list) | I86: OK
A87: 82977 | C87: =COUNTIF('Observed lines'!$F$2:$F$36,A87) -> 0 | D87: =COUNTIFS('Observed lines'!$F$2:$F$36,A87,'Observed lines'!$G$2:$G$36,"<>") -> 0 | E87: =IF(D87=0,"",_xlfn.MINIFS('Observed lines'!$G$2:$G$36,'Observed lines'!$F$2:$F$36,A87)) | F87: =IF(D87=0,"",_xlfn.MAXIFS('Observed lines'!$G$2:$G$36,'Observed lines'!$F$2:$F$36,A87)) | G87: =IF(D87=0,"none seen",IF(E87=F87,TEXT(E87,"$#,##0.00"),TEXT(E87,"$#,##0.00")&" – "&TEXT(F87,"$#,##0.00"))) -> none seen | H87: seed (business list) | I87: OK
A88: 84460 | C88: =COUNTIF('Observed lines'!$F$2:$F$36,A88) -> 0 | D88: =COUNTIFS('Observed lines'!$F$2:$F$36,A88,'Observed lines'!$G$2:$G$36,"<>") -> 0 | E88: =IF(D88=0,"",_xlfn.MINIFS('Observed lines'!$G$2:$G$36,'Observed lines'!$F$2:$F$36,A88)) | F88: =IF(D88=0,"",_xlfn.MAXIFS('Observed lines'!$G$2:$G$36,'Observed lines'!$F$2:$F$36,A88)) | G88: =IF(D88=0,"none seen",IF(E88=F88,TEXT(E88,"$#,##0.00"),TEXT(E88,"$#,##0.00")&" – "&TEXT(F88,"$#,##0.00"))) -> none seen | H88: seed (business list) | I88: OK
A89: 82150 | B89: ASSAY OF AMYLASE | C89: =COUNTIF('Observed lines'!$F$2:$F$36,A89) -> 1 | D89: =COUNTIFS('Observed lines'!$F$2:$F$36,A89,'Observed lines'!$G$2:$G$36,"<>") -> 1 | E89: =IF(D89=0,"",_xlfn.MINIFS('Observed lines'!$G$2:$G$36,'Observed lines'!$F$2:$F$36,A89)) -> 220.31 | F89: =IF(D89=0,"",_xlfn.MAXIFS('Observed lines'!$G$2:$G$36,'Observed lines'!$F$2:$F$36,A89)) -> 220.31 | G89: =IF(D89=0,"none seen",IF(E89=F89,TEXT(E89,"$#,##0.00"),TEXT(E89,"$#,##0.00")&" – "&TEXT(F89,"$#,##0.00"))) -> $220.31 | H89: seed + observed | I89: OK
A90: 84155 | C90: =COUNTIF('Observed lines'!$F$2:$F$36,A90) -> 0 | D90: =COUNTIFS('Observed lines'!$F$2:$F$36,A90,'Observed lines'!$G$2:$G$36,"<>") -> 0 | E90: =IF(D90=0,"",_xlfn.MINIFS('Observed lines'!$G$2:$G$36,'Observed lines'!$F$2:$F$36,A90)) | F90: =IF(D90=0,"",_xlfn.MAXIFS('Observed lines'!$G$2:$G$36,'Observed lines'!$F$2:$F$36,A90)) | G90: =IF(D90=0,"none seen",IF(E90=F90,TEXT(E90,"$#,##0.00"),TEXT(E90,"$#,##0.00")&" – "&TEXT(F90,"$#,##0.00"))) -> none seen | H90: seed (business list) | I90: OK
A91: 36000 | C91: =COUNTIF('Observed lines'!$F$2:$F$36,A91) -> 0 | D91: =COUNTIFS('Observed lines'!$F$2:$F$36,A91,'Observed lines'!$G$2:$G$36,"<>") -> 0 | E91: =IF(D91=0,"",_xlfn.MINIFS('Observed lines'!$G$2:$G$36,'Observed lines'!$F$2:$F$36,A91)) | F91: =IF(D91=0,"",_xlfn.MAXIFS('Observed lines'!$G$2:$G$36,'Observed lines'!$F$2:$F$36,A91)) | G91: =IF(D91=0,"none seen",IF(E91=F91,TEXT(E91,"$#,##0.00"),TEXT(E91,"$#,##0.00")&" – "&TEXT(F91,"$#,##0.00"))) -> none seen | H91: seed (business list) | I91: OK
A92: 29125 | C92: =COUNTIF('Observed lines'!$F$2:$F$36,A92) -> 0 | D92: =COUNTIFS('Observed lines'!$F$2:$F$36,A92,'Observed lines'!$G$2:$G$36,"<>") -> 0 | E92: =IF(D92=0,"",_xlfn.MINIFS('Observed lines'!$G$2:$G$36,'Observed lines'!$F$2:$F$36,A92)) | F92: =IF(D92=0,"",_xlfn.MAXIFS('Observed lines'!$G$2:$G$36,'Observed lines'!$F$2:$F$36,A92)) | G92: =IF(D92=0,"none seen",IF(E92=F92,TEXT(E92,"$#,##0.00"),TEXT(E92,"$#,##0.00")&" – "&TEXT(F92,"$#,##0.00"))) -> none seen | H92: seed (business list) | I92: OK
A93: 87880 | C93: =COUNTIF('Observed lines'!$F$2:$F$36,A93) -> 0 | D93: =COUNTIFS('Observed lines'!$F$2:$F$36,A93,'Observed lines'!$G$2:$G$36,"<>") -> 0 | E93: =IF(D93=0,"",_xlfn.MINIFS('Observed lines'!$G$2:$G$36,'Observed lines'!$F$2:$F$36,A93)) | F93: =IF(D93=0,"",_xlfn.MAXIFS('Observed lines'!$G$2:$G$36,'Observed lines'!$F$2:$F$36,A93)) | G93: =IF(D93=0,"none seen",IF(E93=F93,TEXT(E93,"$#,##0.00"),TEXT(E93,"$#,##0.00")&" – "&TEXT(F93,"$#,##0.00"))) -> none seen | H93: seed (business list) | I93: OK
A94: J8499 | C94: =COUNTIF('Observed lines'!$F$2:$F$36,A94) -> 0 | D94: =COUNTIFS('Observed lines'!$F$2:$F$36,A94,'Observed lines'!$G$2:$G$36,"<>") -> 0 | E94: =IF(D94=0,"",_xlfn.MINIFS('Observed lines'!$G$2:$G$36,'Observed lines'!$F$2:$F$36,A94)) | F94: =IF(D94=0,"",_xlfn.MAXIFS('Observed lines'!$G$2:$G$36,'Observed lines'!$F$2:$F$36,A94)) | G94: =IF(D94=0,"none seen",IF(E94=F94,TEXT(E94,"$#,##0.00"),TEXT(E94,"$#,##0.00")&" – "&TEXT(F94,"$#,##0.00"))) -> none seen | H94: seed (business list) | I94: OK
A95: 12001 | B95: REPAIR- TRUNK/SCALP/NECK/AXIL/LIMBS <2.5 | C95: =COUNTIF('Observed lines'!$F$2:$F$36,A95) -> 1 | D95: =COUNTIFS('Observed lines'!$F$2:$F$36,A95,'Observed lines'!$G$2:$G$36,"<>") -> 1 | E95: =IF(D95=0,"",_xlfn.MINIFS('Observed lines'!$G$2:$G$36,'Observed lines'!$F$2:$F$36,A95)) -> 447.17 | F95: =IF(D95=0,"",_xlfn.MAXIFS('Observed lines'!$G$2:$G$36,'Observed lines'!$F$2:$F$36,A95)) -> 447.17 | G95: =IF(D95=0,"none seen",IF(E95=F95,TEXT(E95,"$#,##0.00"),TEXT(E95,"$#,##0.00")&" – "&TEXT(F95,"$#,##0.00"))) -> $447.17 | H95: seed + observed | I95: OK
A96: 73140 | C96: =COUNTIF('Observed lines'!$F$2:$F$36,A96) -> 0 | D96: =COUNTIFS('Observed lines'!$F$2:$F$36,A96,'Observed lines'!$G$2:$G$36,"<>") -> 0 | E96: =IF(D96=0,"",_xlfn.MINIFS('Observed lines'!$G$2:$G$36,'Observed lines'!$F$2:$F$36,A96)) | F96: =IF(D96=0,"",_xlfn.MAXIFS('Observed lines'!$G$2:$G$36,'Observed lines'!$F$2:$F$36,A96)) | G96: =IF(D96=0,"none seen",IF(E96=F96,TEXT(E96,"$#,##0.00"),TEXT(E96,"$#,##0.00")&" – "&TEXT(F96,"$#,##0.00"))) -> none seen | H96: seed (business list) | I96: OK
A97: 96360 | C97: =COUNTIF('Observed lines'!$F$2:$F$36,A97) -> 0 | D97: =COUNTIFS('Observed lines'!$F$2:$F$36,A97,'Observed lines'!$G$2:$G$36,"<>") -> 0 | E97: =IF(D97=0,"",_xlfn.MINIFS('Observed lines'!$G$2:$G$36,'Observed lines'!$F$2:$F$36,A97)) | F97: =IF(D97=0,"",_xlfn.MAXIFS('Observed lines'!$G$2:$G$36,'Observed lines'!$F$2:$F$36,A97)) | G97: =IF(D97=0,"none seen",IF(E97=F97,TEXT(E97,"$#,##0.00"),TEXT(E97,"$#,##0.00")&" – "&TEXT(F97,"$#,##0.00"))) -> none seen | H97: seed (business list) | I97: OK
A98: 76882 | C98: =COUNTIF('Observed lines'!$F$2:$F$36,A98) -> 0 | D98: =COUNTIFS('Observed lines'!$F$2:$F$36,A98,'Observed lines'!$G$2:$G$36,"<>") -> 0 | E98: =IF(D98=0,"",_xlfn.MINIFS('Observed lines'!$G$2:$G$36,'Observed lines'!$F$2:$F$36,A98)) | F98: =IF(D98=0,"",_xlfn.MAXIFS('Observed lines'!$G$2:$G$36,'Observed lines'!$F$2:$F$36,A98)) | G98: =IF(D98=0,"none seen",IF(E98=F98,TEXT(E98,"$#,##0.00"),TEXT(E98,"$#,##0.00")&" – "&TEXT(F98,"$#,##0.00"))) -> none seen | H98: seed (business list) | I98: OK
A99: L4361 | C99: =COUNTIF('Observed lines'!$F$2:$F$36,A99) -> 0 | D99: =COUNTIFS('Observed lines'!$F$2:$F$36,A99,'Observed lines'!$G$2:$G$36,"<>") -> 0 | E99: =IF(D99=0,"",_xlfn.MINIFS('Observed lines'!$G$2:$G$36,'Observed lines'!$F$2:$F$36,A99)) | F99: =IF(D99=0,"",_xlfn.MAXIFS('Observed lines'!$G$2:$G$36,'Observed lines'!$F$2:$F$36,A99)) | G99: =IF(D99=0,"none seen",IF(E99=F99,TEXT(E99,"$#,##0.00"),TEXT(E99,"$#,##0.00")&" – "&TEXT(F99,"$#,##0.00"))) -> none seen | H99: seed (business list) | I99: OK
A100: 72100 | C100: =COUNTIF('Observed lines'!$F$2:$F$36,A100) -> 0 | D100: =COUNTIFS('Observed lines'!$F$2:$F$36,A100,'Observed lines'!$G$2:$G$36,"<>") -> 0 | E100: =IF(D100=0,"",_xlfn.MINIFS('Observed lines'!$G$2:$G$36,'Observed lines'!$F$2:$F$36,A100)) | F100: =IF(D100=0,"",_xlfn.MAXIFS('Observed lines'!$G$2:$G$36,'Observed lines'!$F$2:$F$36,A100)) | G100: =IF(D100=0,"none seen",IF(E100=F100,TEXT(E100,"$#,##0.00"),TEXT(E100,"$#,##0.00")&" – "&TEXT(F100,"$#,##0.00"))) -> none seen | H100: seed (business list) | I100: OK
A101: A6203 | C101: =COUNTIF('Observed lines'!$F$2:$F$36,A101) -> 0 | D101: =COUNTIFS('Observed lines'!$F$2:$F$36,A101,'Observed lines'!$G$2:$G$36,"<>") -> 0 | E101: =IF(D101=0,"",_xlfn.MINIFS('Observed lines'!$G$2:$G$36,'Observed lines'!$F$2:$F$36,A101)) | F101: =IF(D101=0,"",_xlfn.MAXIFS('Observed lines'!$G$2:$G$36,'Observed lines'!$F$2:$F$36,A101)) | G101: =IF(D101=0,"none seen",IF(E101=F101,TEXT(E101,"$#,##0.00"),TEXT(E101,"$#,##0.00")&" – "&TEXT(F101,"$#,##0.00"))) -> none seen | H101: seed (business list) | I101: OK
A102: 96523 | C102: =COUNTIF('Observed lines'!$F$2:$F$36,A102) -> 0 | D102: =COUNTIFS('Observed lines'!$F$2:$F$36,A102,'Observed lines'!$G$2:$G$36,"<>") -> 0 | E102: =IF(D102=0,"",_xlfn.MINIFS('Observed lines'!$G$2:$G$36,'Observed lines'!$F$2:$F$36,A102)) | F102: =IF(D102=0,"",_xlfn.MAXIFS('Observed lines'!$G$2:$G$36,'Observed lines'!$F$2:$F$36,A102)) | G102: =IF(D102=0,"none seen",IF(E102=F102,TEXT(E102,"$#,##0.00"),TEXT(E102,"$#,##0.00")&" – "&TEXT(F102,"$#,##0.00"))) -> none seen | H102: seed (business list) | I102: OK
A103: 80053 | C103: =COUNTIF('Observed lines'!$F$2:$F$36,A103) -> 0 | D103: =COUNTIFS('Observed lines'!$F$2:$F$36,A103,'Observed lines'!$G$2:$G$36,"<>") -> 0 | E103: =IF(D103=0,"",_xlfn.MINIFS('Observed lines'!$G$2:$G$36,'Observed lines'!$F$2:$F$36,A103)) | F103: =IF(D103=0,"",_xlfn.MAXIFS('Observed lines'!$G$2:$G$36,'Observed lines'!$F$2:$F$36,A103)) | G103: =IF(D103=0,"none seen",IF(E103=F103,TEXT(E103,"$#,##0.00"),TEXT(E103,"$#,##0.00")&" – "&TEXT(F103,"$#,##0.00"))) -> none seen | H103: seed (business list) | I103: OK
A104: 74018 | C104: =COUNTIF('Observed lines'!$F$2:$F$36,A104) -> 0 | D104: =COUNTIFS('Observed lines'!$F$2:$F$36,A104,'Observed lines'!$G$2:$G$36,"<>") -> 0 | E104: =IF(D104=0,"",_xlfn.MINIFS('Observed lines'!$G$2:$G$36,'Observed lines'!$F$2:$F$36,A104)) | F104: =IF(D104=0,"",_xlfn.MAXIFS('Observed lines'!$G$2:$G$36,'Observed lines'!$F$2:$F$36,A104)) | G104: =IF(D104=0,"none seen",IF(E104=F104,TEXT(E104,"$#,##0.00"),TEXT(E104,"$#,##0.00")&" – "&TEXT(F104,"$#,##0.00"))) -> none seen | H104: seed (business list) | I104: OK
A105: 81025 | B105: URINE PREGNANCY TEST | C105: =COUNTIF('Observed lines'!$F$2:$F$36,A105) -> 2 | D105: =COUNTIFS('Observed lines'!$F$2:$F$36,A105,'Observed lines'!$G$2:$G$36,"<>") -> 1 | E105: =IF(D105=0,"",_xlfn.MINIFS('Observed lines'!$G$2:$G$36,'Observed lines'!$F$2:$F$36,A105)) -> 17.04 | F105: =IF(D105=0,"",_xlfn.MAXIFS('Observed lines'!$G$2:$G$36,'Observed lines'!$F$2:$F$36,A105)) -> 17.04 | G105: =IF(D105=0,"none seen",IF(E105=F105,TEXT(E105,"$#,##0.00"),TEXT(E105,"$#,##0.00")&" – "&TEXT(F105,"$#,##0.00"))) -> $17.04 | H105: seed + observed | I105: OK
A106: 80305 | C106: =COUNTIF('Observed lines'!$F$2:$F$36,A106) -> 0 | D106: =COUNTIFS('Observed lines'!$F$2:$F$36,A106,'Observed lines'!$G$2:$G$36,"<>") -> 0 | E106: =IF(D106=0,"",_xlfn.MINIFS('Observed lines'!$G$2:$G$36,'Observed lines'!$F$2:$F$36,A106)) | F106: =IF(D106=0,"",_xlfn.MAXIFS('Observed lines'!$G$2:$G$36,'Observed lines'!$F$2:$F$36,A106)) | G106: =IF(D106=0,"none seen",IF(E106=F106,TEXT(E106,"$#,##0.00"),TEXT(E106,"$#,##0.00")&" – "&TEXT(F106,"$#,##0.00"))) -> none seen | H106: seed (business list) | I106: OK
...

Sheet Trends
A1: Portal field | B1: Observed value | C1: Count | D1: Out of | E1: Share | F1: Unit | G1: Studio action (v3)
A2: Was the service in question provided prior to 1/1/2022? | B2: No | C2: 4 | D2: 4 | E2: =IF(OR(C2="",D2=""),"",C2/D2) -> 1 | F2: notices | G2: Default No; Yes = hard stop.
A3: I am (or I am acting on behalf of) a: | B3: Health care facility | C3: 3 | D3: 4 | E3: =IF(OR(C3="",D3=""),"",C3/D3) -> 0.75 | F3: notices | G3: Locked chip from the billing entity (2 options only).
A4: I am (or I am acting on behalf of) a: | B4: Health care provider | C4: 1 | D4: 4 | E4: =IF(OR(C4="",D4=""),"",C4/D4) -> 0.25 | F4: notices | G4: Locked chip from the billing entity (2 options only).
A5: Tax ID / NPI | B5: Facility 862923814 / 1972273233 | C5: 3 | D5: 4 | E5: =IF(OR(C5="",D5=""),"",C5/D5) -> 0.75 | F5: notices | G5: Filled from the billing entity; at least one required.
A6: Tax ID / NPI | B6: Provider 872524265 / 1609548056 | C6: 1 | D6: 4 | E6: =IF(OR(C6="",D6=""),"",C6/D6) -> 0.25 | F6: notices | G6: Filled from the billing entity; at least one required.
A7: Health Plan Type | B7: Either partially or fully self-insured ERISA group health plan | C7: 4 | D7: 4 | E7: =IF(OR(C7="",D7=""),"",C7/D7) -> 1 | F7: notices | G7: Default of the strict 7-option dropdown.
A8: When did the open negotiation period start? | B8: 09/01/2026 (filed 10/15/2026) | C8: 2 | D8: 4 | E8: =IF(OR(C8="",D8=""),"",C8/D8) -> 0.5 | F8: notices | G8: Filed on business day 31, the first day of the window (start date = day 1).
A9: When did the open negotiation period start? | B9: 09/02/2026 (filed 10/16/2026) | C9: 2 | D9: 4 | E9: =IF(OR(C9="",D9=""),"",C9/D9) -> 0.5 | F9: notices | G9: Filed on business day 31, the first day of the window (start date = day 1).
A10: Proof of open negotiation | B10: "OMB <account>.pdf" | C10: 2 | D10: 4 | E10: =IF(OR(C10="",D10=""),"",C10/D10) -> 0.5 | F10: notices | G10: Keep upload; suggest a name.
A11: Proof of open negotiation | B11: "PROOF <account>.png" | C11: 1 | D11: 4 | E11: =IF(OR(C11="",D11=""),"",C11/D11) -> 0.25 | F11: notices | G11: Keep upload; suggest a name.
A12: Proof of open negotiation | B12: "<date> LLC NSA NEG LETTER C <account>.pdf" | C12: 1 | D12: 4 | E12: =IF(OR(C12="",D12=""),"",C12/D12) -> 0.25 | F12: notices | G12: Keep upload; suggest a name.
A13: Consent to waive surprise billing protections | B13: No | C13: 4 | D13: 4 | E13: =IF(OR(C13="",D13=""),"",C13/D13) -> 1 | F13: notices | G13: Default No; Yes = hard stop.
... A37: Data quality | B37: Line with blank claim number, date, QPA, POS and location | C37: 10 | D37: 35 | E37: =IF(OR(C37="",D37=""),"",C37/D37) -> 0.28571429 | F37: lines | G37: Required on every line. All blanks are DISP-7998956 lines 2–11.
A38: Lines per dispute | B38: 4, 7, 13 and 11 lines | C38: 35 | E38: =IF(OR(C38="",D38=""),"",C38/D38) | F38: lines in 4 notices | G38: Batched: 2–50 lines; single not bundled: 1 line.
A39: Timing bands (computed) | B39: ON start 09/01/2026 (day 1): ON ends 10/14/2026 (day 30); window 10/15/2026 to 10/20/2026 (days 31–34); extension needed from 10/21/2026 (day 35) | G39: businessDeadline_: onEnds 10/14/2026, opens 10/15/2026, initiateBy 10/20/2026. Labor Day and Columbus Day skipped. Matches the real filing on 10/15/2026.
A40: Timing bands (computed) | B40: ON start 09/02/2026 (day 1): ON ends 10/15/2026 (day 30); window 10/16/2026 to 10/21/2026 (days 31–34); extension needed from 10/22/2026 (day 35) | G40: businessDeadline_: onEnds 10/15/2026, opens 10/16/2026, initiateBy 10/21/2026. Labor Day and Columbus Day skipped. Matches the real filing on 10/16/2026.

Sheet Observed lines
A1: Dispute ref | B1: Payer (as on notice) | C1: Billing entity (as on notice) | D1: Line no | E1: Description | F1: Service code | G1: QPA | H1: Cost sharing | I1: Initial payment | J1: Item type | K1: POS | L1: Location | M1: IDR entity | N1: Data-quality flag
A2: DISP-7997846 | B2: Cigna | C2: SILVER ALLIANCE LLC | D2: 1 | E2: EMERGENCY ROOM SERVICE | F2: 99284 | G2: 1052.46 | H2: 0 | I2: 1052.46 | J2: Emergency item(s)/service(s) | K2: 23 | L2: TX | M2: Maximus Federal Services Inc
A3: DISP-7997846 | B3: Cigna | C3: SILVER ALLIANCE LLC | D3: 2 | E3: DRAINAGE OF SKIN ABSCESS | F3: 10061 | G3: 775.52 | H3: 0 | I3: 775.52 | J3: Emergency item(s)/service(s) | K3: 23 | L3: TX | M3: Maximus Federal Services Inc
A4: DISP-7997846 | B4: Cigna | C4: SILVER ALLIANCE LLC | D4: 3 | E4: PHARMACY | F4: J3490 | G4: 96.71 | H4: 0 | I4: 96.71 | J4: Emergency item(s)/service(s) | K4: 23 | L4: TX | M4: Maximus Federal Services Inc
A5: DISP-7997846 | B5: Cigna | C5: SILVER ALLIANCE LLC | D5: 4 | E5: Injection, ceftriaxone sodium, per 250 mg | F5: J0696 | G5: 25.34 | H5: 0 | I5: 25.34 | J5: Emergency item(s)/service(s) | K5: 23 | L5: TX | M5: Maximus Federal Services Inc
A6: DISP-7986216 | B6: UMR | C6: SILVER ALLIANCE,LLC | D6: 1 | E6: EMERGENCY ROOM SERVICE | F6: 99283 | G6: 905.44 | H6: 905.44 | I6: 0 | J6: Emergency item(s)/service(s) | K6: 23 | L6: TX | M6: Capitol Bridge LLC | N6: Entity name written "SILVER ALLIANCE,LLC".
A7: DISP-7986216 | B7: UMR | C7: SILVER ALLIANCE,LLC | D7: 2 | E7: MEASURE BLOOD OXYGEN LEVEL | F7: 94761 | G7: 143.2 | H7: 143.2 | I7: 0 | J7: Emergency item(s)/service(s) | K7: 23 | L7: TX | M7: Capitol Bridge LLC | N7: Entity name written "SILVER ALLIANCE,LLC".
A8: DISP-7986216 | B8: UMR | C8: SILVER ALLIANCE,LLC | D8: 3 | E8: REPAIR- TRUNK/SCALP/NECK/AXIL/LIMBS <2.5 | F8: 12001 | G8: 447.17 | H8: 447.17 | I8: 0 | J8: Emergency item(s)/service(s) | K8: 23 | L8: TX | M8: Capitol Bridge LLC | N8: Entity name written "SILVER ALLIANCE,LLC".
A9: DISP-7986216 | B9: UMR | C9: SILVER ALLIANCE,LLC | D9: 4 | E9: AUTOMATIC BLOOD PRESSURE MONITOR | F9: A4670 | G9: 10.32 | H9: 10.32 | I9: 0 | J9: Emergency item(s)/service(s) | K9: 23 | L9: TX | M9: Capitol Bridge LLC | N9: Entity name written "SILVER ALLIANCE,LLC".
A10: DISP-7986216 | B10: UMR | C10: SILVER ALLIANCE,LLC | D10: 5 | E10: ADHESIVE BANDAGE, FIRST-AID | F10: A6413 | G10: 6.5 | H10: 6.5 | I10: 0 | J10: Emergency item(s)/service(s) | K10: 23 | L10: TX | M10: Capitol Bridge LLC | N10: Entity name written "SILVER ALLIANCE,LLC".
A11: DISP-7986216 | B11: UMR | C11: SILVER ALLIANCE,LLC | D11: 6 | E11: GLOVES STERILE PER PAIR | F11: A4930 | G11: 28.87 | H11: 28.87 | I11: 0 | J11: Emergency item(s)/service(s) | K11: 23 | L11: TX | M11: Capitol Bridge LLC | N11: Entity name written "SILVER ALLIANCE,LLC".
A12: DISP-7986216 | B12: UMR | C12: SILVER ALLIANCE,LLC | D12: 7 | E12: CHLORHEXIDINE ANTISEPT | F12: A4248 | G12: 1.91 | H12: 1.91 | I12: 0 | J12: Emergency item(s)/service(s) | K12: 23 | L12: TX | M12: Capitol Bridge LLC | N12: Entity name written "SILVER ALLIANCE,LLC".
A13: DISP-7984427 | B13: United Healthcare | C13: SILVER ALLIANCE LLC | D13: 1 | E13: EMERGENCY ROOM SERVICE | F13: 99284 | G13: 250.3 | H13: 0 | I13: 250.3 | J13: Emergency item(s)/service(s) | K13: 23 | L13: TX | M13: Maximus Federal Services Inc
A14: DISP-7984427 | B14: United Healthcare | C14: SILVER ALLIANCE LLC | D14: 2 | E14: MEASURE BLOOD OXYGEN LEVEL | F14: 94761 | G14: 29.41 | H14: 0 | I14: 29.41 | J14: Emergency item(s)/service(s) | K14: 23 | L14: TX | M14: Maximus Federal Services Inc
A15: DISP-7984427 | B15: United Healthcare | C15: SILVER ALLIANCE LLC | D15: 3 | E15: THERAPY/PROPHYLAXIS/DIAGNOSIS INJECTION, SC/IM | F15: 96372 | G15: 37.78 | H15: 0 | I15: 37.78 | J15: Emergency item(s)/service(s) | K15: 23 | L15: TX | M15: Maximus Federal Services Inc
A16: DISP-7984427 | B16: United Healthcare | C16: SILVER ALLIANCE LLC | D16: 4 | E16: URINE PREGNANCY TEST | F16: 81025 | G16: 17.04 | H16: 0 | I16: 17.04 | J16: Emergency item(s)/service(s) | K16: 23 | L16: TX | M16: Maximus Federal Services Inc
A17: DISP-7984427 | B17: United Healthcare | C17: SILVER ALLIANCE LLC | D17: 5 | E17: CT NECK SPINE W/O DYE | F17: 72125 | G17: 374.66 | H17: 350 | I17: 24.66 | J17: Emergency item(s)/service(s) | K17: 23 | L17: TX | M17: Maximus Federal Services Inc
A18: DISP-7984427 | B18: United Healthcare | C18: SILVER ALLIANCE LLC | D18: 6 | E18: CT HEAD/BRAIN W/O DYE | F18: 70450 | G18: 348.35 | H18: 0 | I18: 348.35 | J18: Emergency item(s)/service(s) | K18: 23 | L18: TX | M18: Maximus Federal Services Inc
A19: DISP-7984427 | B19: United Healthcare | C19: SILVER ALLIANCE LLC | D19: 7 | E19: Computed tomography, thoracic spine | F19: 72128 | G19: 228.66 | H19: 0 | I19: 228.66 | J19: Emergency item(s)/service(s) | K19: 23 | L19: TX | M19: Maximus Federal Services Inc
A20: DISP-7984427 | B20: United Healthcare | C20: SILVER ALLIANCE LLC | D20: 8 | E20: AUTOMATIC BLOOD PRESSURE MONITOR | F20: A4670 | G20: 2.12 | H20: 0 | I20: 2.12 | J20: Emergency item(s)/service(s) | K20: 23 | L20: TX | M20: Maximus Federal Services Inc
A21: DISP-7984427 | B21: United Healthcare | C21: SILVER ALLIANCE LLC | D21: 9 | E21: Injection, ketorolac tromethamine, per 15 mg | F21: J1885 | G21: 5.26 | H21: 0 | I21: 5.26 | J21: Emergency item(s)/service(s) | K21: 23 | L21: TX | M21: Maximus Federal Services Inc
A22: DISP-7984427 | B22: United Healthcare | C22: SILVER ALLIANCE LLC | D22: 10 | E22: NEEDLES ONLY STERILE ANY SIZE EACH | F22: A4215 | G22: 2.59 | H22: 0 | I22: 2.59 | J22: Emergency item(s)/service(s) | K22: 23 | L22: TX | M22: Maximus Federal Services Inc
A23: DISP-7984427 | B23: United Healthcare | C23: SILVER ALLIANCE LLC | D23: 11 | E23: ADHESIVE BANDAGE, FIRST-AID | F23: A6413 | G23: 1.34 | H23: 0 | I23: 1.34 | J23: Emergency item(s)/service(s) | K23: 23 | L23: TX | M23: Maximus Federal Services Inc
A24: DISP-7984427 | B24: United Healthcare | C24: SILVER ALLIANCE LLC | D24: 12 | E24: SYRINGE WITH OR WITHOUT NEEDLE EACH | F24: A4657 | G24: 9.11 | H24: 0 | I24: 9.11 | J24: Emergency item(s)/service(s) | K24: 23 | L24: TX | M24: Maximus Federal Services Inc
... A26: DISP-7998956 | B26: BLUECROSS BLUESHIELD | C26: CAPITAL HEALTH PLLC | D26: 1 | E26: ASSAY OF AMYLASE | F26: 82150 | G26: 220.31 | H26: 4.72 | I26: 215.59 | J26: Emergency item(s)/service(s) | K26: 23 | L26: TX | M26: Federal Hearings and Appeals Services, LLC
A27: DISP-7998956 | B27: BLUECROSS BLUESHIELD | C27: CAPITAL HEALTH PLLC | D27: 2 | E27: EMERGENCY ROOM SERVICE | F27: 99284 | J27: Emergency item(s)/service(s) | M27: Federal Hearings and Appeals Services, LLC | N27: Blank claim number; blank date of service; QPA "$" only; no QPA documentation; cost sharing "$" only; initial payment "N/A"; blank POS; blank location.
A28: DISP-7998956 | B28: BLUECROSS BLUESHIELD | C28: CAPITAL HEALTH PLLC | D28: 3 | E28: URINALYSIS, AUTO, W/O SCOPE | F28: 81003 | J28: Emergency item(s)/service(s) | M28: Federal Hearings and Appeals Services, LLC | N28: Blank claim number; blank date of service; QPA "$" only; no QPA documentation; cost sharing "$" only; initial payment "N/A"; blank POS; blank location.
A29: DISP-7998956 | B29: BLUECROSS BLUESHIELD | C29: CAPITAL HEALTH PLLC | D29: 4 | E29: URINE PREGNANCY TEST | F29: 81025 | J29: Emergency item(s)/service(s) | M29: Federal Hearings and Appeals Services, LLC | N29: Blank claim number; blank date of service; QPA "$" only; no QPA documentation; cost sharing "$" only; initial payment "N/A"; blank POS; blank location.
A30: DISP-7998956 | B30: BLUECROSS BLUESHIELD | C30: CAPITAL HEALTH PLLC | D30: 5 | E30: COMPLETE CBC W/AUTO DIFF WBC | F30: 85025 | J30: Emergency item(s)/service(s) | M30: Federal Hearings and Appeals Services, LLC | N30: Blank claim number; blank date of service; QPA "$" only; no QPA documentation; cost sharing "$" only; initial payment "N/A"; blank POS; blank location.
A31: DISP-7998956 | B31: BLUECROSS BLUESHIELD | C31: CAPITAL HEALTH PLLC | D31: 6 | E31: ELECTROLYTE PANEL | F31: 80051 | J31: Emergency item(s)/service(s) | M31: Federal Hearings and Appeals Services, LLC | N31: Blank claim number; blank date of service; QPA "$" only; no QPA documentation; cost sharing "$" only; initial payment "N/A"; blank POS; blank location.
A32: DISP-7998956 | B32: BLUECROSS BLUESHIELD | C32: CAPITAL HEALTH PLLC | D32: 7 | E32: ASSAY OF CK (CPK) | F32: 82550 | J32: Emergency item(s)/service(s) | M32: Federal Hearings and Appeals Services, LLC | N32: Blank claim number; blank date of service; QPA "$" only; no QPA documentation; cost sharing "$" only; initial payment "N/A"; blank POS; blank location.
A33: DISP-7998956 | B33: BLUECROSS BLUESHIELD | C33: CAPITAL HEALTH PLLC | D33: 8 | E33: ASSAY OF CREATININE | F33: 82565 | J33: Emergency item(s)/service(s) | M33: Federal Hearings and Appeals Services, LLC | N33: Blank claim number; blank date of service; QPA "$" only; no QPA documentation; cost sharing "$" only; initial payment "N/A"; blank POS; blank location.
A34: DISP-7998956 | B34: BLUECROSS BLUESHIELD | C34: CAPITAL HEALTH PLLC | D34: 9 | E34: ASSAY, GLUCOSE, BLOOD QUANT | F34: 82947 | J34: Emergency item(s)/service(s) | M34: Federal Hearings and Appeals Services, LLC | N34: Blank claim number; blank date of service; QPA "$" only; no QPA documentation; cost sharing "$" only; initial payment "N/A"; blank POS; blank location.
A35: DISP-7998956 | B35: BLUECROSS BLUESHIELD | C35: CAPITAL HEALTH PLLC | D35: 10 | E35: ASSAY OF UREA NITROGEN | F35: 84520 | J35: Emergency item(s)/service(s) | M35: Federal Hearings and Appeals Services, LLC | N35: Blank claim number; blank date of service; QPA "$" only; no QPA documentation; cost sharing "$" only; initial payment "N/A"; blank POS; blank location.
A36: DISP-7998956 | B36: BLUECROSS BLUESHIELD | C36: CAPITAL HEALTH PLLC | D36: 11 | E36: HEPATIC FUNCTION PANEL | F36: 80076 | J36: Emergency item(s)/service(s) | M36: Federal Hearings and Appeals Services, LLC | N36: Blank claim number; blank date of service; QPA "$" only; no QPA documentation; cost sharing "$" only; initial payment "N/A"; blank POS; blank location.

Sheet Learning rules
A1: ID | B1: Requirement | C1: Acceptance criteria | D1: Priority | E1: Version
A2: L01 | B2: The Options tab is the single source for every list except billing entities (BillingEntities tab). Columns: List | Key | Value | Label | Data | Count | LastUsed | Source | Status | Sort | Strict | AddedBy | AddedAt. Code.gs BUILTIN_LISTS are only a fallback seed when a list is missing or has no active value. | C2: Changing a label on the Options tab shows in getBootstrap after the cache clears. | D2: Do first | E2: v4 (changed)
A3: L02 | B3: Combo fields with suggestions ranked by Count then LastUsed: plan_name (Payer), prov_name (BillingEntities), idr_entity, service_code, modifiers, pos_code, ReturnReason. Team and RCM Specialist are searchable boxes with "Add new". Strict lists (Strict = Yes) and State never learn. | C3: Typing 2 letters shows matching Active values, most used first. | D3: Do first | E3: v4 (changed)
A4: L03 | B4: Learn on save: saveDispute, saveLine, saveLines and returnDispute. New value: Source learned, Count 1; known value: Count + 1, LastUsed. Saving the same dispute again does not count twice. | C4: A new payer adds one row; saving again does not double count. | D4: Do first | E4: v3
A5: L04 | B5: Address books: Payer keeps the latest non-empty profile in Data JSON. BillingEntities: a new entity typed by a user is added (Confirmed No; Hidden while LearningMode is Off); empty columns are filled from the saved dispute; a non-empty value is never overwritten, except an unconfirmed ActingAs, which the saved dispute confirms. | C5: Admin-entered TIN is never replaced by a save. | D5: Do first | E5: v4 (changed)
A6: L05 | B6: Caches: Options + BillingEntities rows 10 minutes; Settings and Fields 10 minutes; Users 2 minutes. A save that learns, an admin change or an edit to the tab (onEdit) clears the matching cache. | C6: A value saved by user A appears for user B after a reload. | D6: Do first | E6: v4 (changed)
A7: L06 | B7: Profile auto-fill: payer -> plan contact; billing entity -> q_acting_as, tin, npi, prov_group_name, provider contact; service code -> description; q_plan_type -> plan_role (editable). | C7: Only empty fields (or fields still holding the previous pick) are filled; "Refill from" overwrites. | D7: Do first | E7: v3
A8: L07 | B8: Defaults come from the Fields tab: DefaultMode Fixed = the Default column; Learned = the most used value in the last DefaultWindow saves when its share >= DefaultShare and at least 5 records have the field, else the Default column; None = no default. Tokens: @top (most used of the list), @me (signed-in LB Member email), @myteam (signed-in user's Team). | C8: Changing DefaultMode to Fixed applies on the next page load. | D8: Do first | E8: v4 (changed)
A9: L08 | B9: Defaults show a "default" chip. Locked = Yes with a Fixed default shows a chip and always stores the value (Location of Service TX). | C9: New line shows TX as a locked chip. | D9: Do first | E9: v4 (changed)
A10: L09 | B10: Admin -> Lists: reword a value (keeps its Key), change label or sort, hide or activate, merge a learned value into another. Portal options with a Key are reworded, never merged. Names the portal would reject are flagged with the Fix result. | C10: adminUpdateOption refuses BillingEntity (own view). | D10: Do next | E10: v4 (changed)
A11: L10 | B11: Hidden values never show as suggestions. | C11: Hidden alias "Health Now" is not suggested. | D11: Do next | E11: v2
A12: L11 | B12: Typo protection within 2 edits (case, spaces, punctuation ignored); values whose digits differ are never typos. Alias rows (Hidden, Data.mergedInto) and the BillingEntities Aliases column map to the main value. | C12: "SILVER ALLIANCE,LLC" -> Did you mean Silver Alliance, LLC? | D12: Do first | E12: v4 (changed)
... A20: L19 | B20: Fields merge (applyFields_): the sheet wins for Label, Help, Required (not Rule), Default, DefaultMode, Locked, Visible, Order, Pattern, PatternMessage, CopyOrder. Invalid values keep the built-in value and show as warnings. setup() adds rows for new built-in fields and never changes existing rows. | C20: Hiding a required field is ignored with a warning. | D20: Do first | E20: v4

Sheet Validation rules
A1: Rule ID | B1: Field(s) | C1: Rule | D1: Message | E1: Blocking/Warning | F1: Version | G1: Guide §
A2: V01 | B2: All required fields | C2: Not empty. v3 adds prov_group_name, cost_sharing, plan_role, dispute_type. | D2: <label> is required | E2: Blocking | F2: v3 (changed) | G2: 1.5, 1.6
A3: V02 | B3: *_zip | C3: Accept 12345, 12345-6789 or 123456789. Store 12345 or 12345-6789. | D3: must look like 12345 or 12345-6789 | E3: Blocking | F3: v2
A4: V03 | B4: *_phone, *_fax | C4: Accept (817) 566-1232, 817-566-1232 or 8175661232. Store (817) 566-1232. | D4: must be a 10-digit phone number, like (817) 566-1232 | E4: Blocking | F4: v2
A5: V04 | B5: *_email | C5: ^[^@\s]+@[^@\s]+\.[^@\s]+$ | D5: is not a valid email | E5: Blocking | F5: v2
A6: V05 | B6: qpa, cost_sharing, initial_payment | C6: ^\d+(\.\d{1,2})?$ after removing $ , and spaces. | D6: must be an amount like 154.00 | E6: Blocking | F6: v2
A7: V06 | B7: All date fields | C7: YYYY-MM-DD. | D7: must be a date | E7: Blocking | F7: v2
A8: V07 | B8: service_date | C8: On or after 2022-01-01. | D8: must be on or after 2022-01-01 | E8: Blocking | F8: v2 | G8: 1.3 (2)
A9: V08 | B9: on_start_date | C9: Not in the future. | D9: cannot be in the future | E9: Blocking | F9: v2
A10: V09 | B10: tin | C10: ^\d{9}$ when filled. | D10: Tax ID must be 9 digits | E10: Blocking | F10: v3 (changed) | G10: 1.3 (4a)
A11: V10 | B11: npi | C11: ^\d{10}$ when filled. | D11: NPI must be 10 digits | E11: Blocking | F11: v3 (changed) | G11: 1.3 (4b)
A12: V11 | B12: q_prior_2022 | C12: Yes stops the dispute. | D12: Not eligible for federal IDR (portal alert) | E12: Blocking | F12: v2 | G12: 1.3 (2)
A13: V12 | B13: consent_waiver | C13: Yes stops the dispute. | D13: Not eligible for federal IDR | E13: Blocking | F13: v2 | G13: 1.3 (10)
A14: V13 | B14: on_start_date, extension_reason | C14: b > 34 and no extension_reason. | D14: Deadline passed. Pick an extension reason or return the dispute. | E14: Blocking | F14: v3 (changed) | G14: 1.3 (9b, 9c)
A15: V14 | B15: on_start_date | C15: 31 <= b <= 34: show the window. Red when 1 business day or less is left. Example (start date = day 1): ON start 09/01/2026 -> day 30 = 10/14/2026, window 10/15/2026 to 10/20/2026, extension needed from 10/21/2026. | D15: Initiation window: <first day> to <last day> (<n> business days left) | E15: Warning (info) | F15: v3 (changed) | G15: 1.3 (9)
A16: V15 | B16: dispute_kind, claim_number | C16: v2 "Single dispute with several claim numbers" warning. | D16: (removed) | E16: n/a | F16: Removed (v3)
A17: V16 | B17: cost_sharing, qpa | C17: cost_sharing > qpa. | D17: Cost sharing is more than the QPA | E17: Warning | F17: v2
A18: V17 | B18: cost_sharing, initial_payment, qpa | C18: cost_sharing + initial_payment differs from qpa (both filled). | D18: Cost sharing plus initial payment does not equal the QPA | E18: Warning | F18: v2
A19: V18 | B19: qpa, initial_payment | C19: qpa = 0, or initial_payment > qpa. | D19: Check the QPA and the initial payment | E19: Warning | F19: v2
A20: V19 | B20: description, claim_number, service_date, qpa, cost_sharing, service_code, pos_code | C20: Required on every line (cost_sharing now required). | D20: Line <n>: <label> is required | E20: Blocking | F20: v3 (changed) | G20: 1.6.1.1
A21: V20 | B21: Line items | C21: At least 1 line. Kind-specific counts in V52–V55. | D21: Add at least one line item. | E21: Blocking | F21: v3 (changed) | G21: 1.6.2
A22: V21 | B22: Line items | C22: App-wide cap: at most 50 lines on any dispute. | D22: A dispute can have at most 50 line items. | E22: Blocking | F22: v2 | G22: 1.6.2.3
A23: V22 | B23: claim_number | C23: Claim number also in another dispute that is not Returned (kept as a warning; the blocking line rule is V57). | D23: Claim <claim> is also in <id> (<status>). | E23: Warning | F23: v2
A24: V23 | B24: qpa_docs | C24: At least 1 file per line, or a file marked for all lines with the same claim number. | D24: Line <n>: QPA documentation is missing | E24: Blocking | F24: v3 (changed) | G24: 1.6.1.1 (9)
A25: V24 | B25: on_evidence | C25: At least 1 file. Batched: reminder to upload proof for each distinct ON start date. | D25: Proof of open negotiation is missing / Upload proof for each open negotiation start date in this batch. | E25: Blocking / Warning | F25: v3 (changed) | G25: 1.1, 1.3 (9)
A26: V25 | B26: other_desc | C26: Required when item_types includes "Other: Provide description". | D26: Other: Provide description is required | E26: Blocking | F26: v2 | G26: 1.6.1.1 (7g)
A27: V26 | B27: idr_entity | C27: Not empty. | D27: Certified IDR entity is required | E27: Blocking | F27: v2 | G27: 1.7.1
A28: V27 | B28: third_party_attest | C28: Yes or No. | D28: Answer the third-party question | E28: Blocking | F28: v2 | G28: 1.7.2
A29: V28 | B29: PortalDisputeNumber | C29: ^DISP-\d+$ | D29: Enter the portal dispute number, like DISP-1234567 | E29: Blocking | F29: v3 (changed) | G29: 1.9
A30: V29 | B30: PortalPdfUrl | C30: Notice of IDR Initiation PDF (portal "Save as PDF") attached to mark Filed. | D30: Attach the Notice of IDR Initiation PDF | E30: Blocking | F30: v3 (changed) | G30: 1.9 (1)
A31: V30 | B31: ReturnReason | C31: Not empty; from ReturnReason (combo). | D31: Say what needs fixing. | E31: Blocking | F31: v2
A32: V31 | B32: All combo fields (incl. Team, RCM Specialist) | C32: Typed value within edit distance 2 of an Active value or alias. | D32: Did you mean <value>? | E32: Warning | F32: v2
A33: V32 | B33: *_state, location | C33: Strict select from State. location is fixed TX (read-only). | D33: Pick a state from the list | E33: Blocking | F33: v3 (changed) | G33: 1.6.1.1 (8d)
A34: V33 | B34: modifiers | C34: Optional (see V50 for the format). | D34: (none) | E34: n/a | F34: v3 (changed) | G34: 1.6.1.1 (8b)
A35: V34 | B35: Any edit | C35: Filed disputes cannot be edited. | D35: This dispute is already filed and can no longer be edited. | E35: Blocking | F35: v2
A36: V35 | B36: Any upload | C36: Under MaxFileMb MB per file (Settings; default 45, at most 45: the Apps Script limit). | D36: Files must be under <MaxFileMb> MB each. | E36: Blocking | F36: v4 (changed)
A37: V36 | B37: uploadFile target | C37: A saved dispute id, or the draft token (DRAFT-...) of a new dispute: files can be attached before the first save (staging). | D37: No dispute to attach the file to. | E37: Blocking | F37: v4 (changed)
A38: V37 | B38: service_date (batched) | C38: All service dates within 30 business days of each other (latest minus earliest), unless extension_reason = cooling off period. | D38: All dates of service in a batched dispute must be within 30 business days of each other. | E38: Blocking | F38: v3 (changed) | G38: 1.6.1.3, 1.6.2.3
A39: V38 | B39: tin, npi | C39: At least one of tin / npi. | D39: Enter the Tax ID or the NPI (at least one). | E39: Blocking | F39: v3 | G39: 1.3 (4)
A40: V39 | B40: q_acting_as | C40: One of: Health care provider, Health care facility. | D40: Pick provider or facility | E40: Blocking | F40: v3 | G40: 1.3 (3)
A41: V40 | B41: q_plan_type | C41: One of the 7 portal options, exact text. | D41: Pick a Health Plan Type from the list | E41: Blocking | F41: v3 | G41: 1.3 (5)
A42: V41 | B42: q_plan_type | C42: Always shown under the field. | D42: Coverage only through Medicare, Medicaid, CHIP, TRICARE or a health care sharing ministry is not eligible for the Federal IDR process. | E42: Info | F42: v3 | G42: 1.3 (3)
A43: V42 | B43: fehb_enrollment_code | C43: ^\d{3}$; required only when q_plan_type is the FEHB carrier option. | D43: Enter the three-digit FEHB enrollment code | E43: Blocking | F43: v3 | G43: 1.3 (6)
A44: V43 | B44: on_start_date | C44: b < 31. Ready for US desk is allowed (notice only). Start portal entry and Mark as filed are blocked (assertWindowOpen_). The dispute shows under "Not open yet" on the US desk. Example (start date = day 1): ON start 09/01/2026 -> day 30 = 10/14/2026, window 10/15/2026 to 10/20/2026, extension needed from 10/21/2026. | D44: Notice: Filing window opens <date> (open negotiation business day <b> today). US desk: If the parties can’t agree on an out-of-network rate, the 30-business-day open negotiation period must elapse before starting the Federal IDR process. Filing window opens <date>. | E44: Warning (Ready) / Blocking (US desk) | F44: v3 | G44: 1.3 (9a)
A45: V44 | B45: ext_approval | C45: Reason (i): at least 1 file. | D45: Upload the extension approval from the Federal IDR Questions mailbox | E45: Blocking | F45: v3 | G45: 1.3 (9c i)
A46: V45 | B46: cooling_dispute_ref | C46: Reason (ii): required, ^DISP-\d+$. | D46: Enter the dispute reference number. / The dispute number is not valid. | E46: Blocking | F46: v3 | G46: 1.3 (9c ii)
A47: V46 | B47: cooling_docs | C47: Reason (ii): at least 1 file. | D47: Upload the payment determination(s) that started the cooling off period | E47: Blocking | F47: v3 | G47: 1.3 (9c ii)
A48: V47 | B48: service_date, on_start_date | C48: service_date strictly before on_start_date, every line, every kind. | D48: Line <n>: the date of service must be before the open negotiation start date | E48: Blocking | F48: v3 | G48: 1.6.1.1 (3)
A49: V48 | B49: claim_number | C49: ^[A-Za-z0-9]{1,40}$ | D49: Claim number: letters and digits only, up to 40 | E49: Blocking | F49: v3 | G49: 1.6.1.1 (2)
... A85: V84 | B85: Editor tools | C85: setup, installTriggers, seedDemoData, clearDemoData: Admin only (or the script owner while no member is active); dailyMaintenance also from its time trigger. | D85: Only an Admin can run this. | E85: Blocking | F85: v4 | G85: -

Sheet Workflow
A1: From status | B1: Action | C1: To status | D1: Who | E1: Required conditions | F1: Server function | G1: Log event | H1: Version
A2: (none) | B2: Save page 1 | C2: Draft | D2: LB Member / Admin | E2: None. New DisputeID (IDR-yymmdd-XXXX) and Drive folder. | F2: saveDispute | G2: save | H2: v2
A3: Draft | B3: Save any page or line | C3: Draft | D3: LB Member / Admin | E3: Not Filed. Learn on save (L03). Stepper shows per-page completeness (7 pages). | F3: saveDispute, saveLine, deleteLine | G3: save, line:<n> | H3: v3 (changed)
A4: Draft | B4: Upload or remove a file | C4: Draft | D4: LB Member / Admin | E4: Dispute saved; under 45 MB per file; dispute total <= 500 MB (V60). | F4: uploadFile, removeFile | G4: upload, file-removed | H4: v3 (changed)
A5: Draft | B5: Save & create confirmation PDF | C5: Ready for US desk | D5: LB Member / Admin | E5: No blocking rules, including deadline (V13), line-count rules (V52–V55), duplicates (V56, V57). Allowed before business day 31: notice "Filing window opens <date>" (V43). | F5: finalizeDispute | G5: status | H5: v3 (changed)
A6: Ready for US desk | B6: (before business day 31) | C6: Ready for US desk | D6: US Member / Admin | E6: Listed under "Not open yet", sorted by opening date. Start portal entry and Mark as filed wait until the window opens. | F6: listDisputes (band, opens) | G6: - | H6: v3
A7: Ready for US desk | B7: Start portal entry (copy desk) | C7: Ready for US desk | D7: US Member / Admin | E7: "Start only when you can finish this dispute in one sitting." 60-minute timer, warning at 50 minutes. Portal times out after 60 minutes of inactivity; nothing is saved on exit. Blocked before business day 31 (V43). | F7: (client only) | G7: - | H7: v3
A8: Ready for US desk | B8: Copy to the portal | C8: Ready for US desk | D8: US Member / Admin | E8: Order: pages 1–4, line items in summary-table column order, page 6, Review & Submit. Gateway banner until 2027-01-15. | F8: (client only) | G8: - | H8: v3 (changed)
A9: Ready for US desk | B9: Mark as filed | C9: Filed | D9: US Member / Admin | E9: ^DISP-\d+$ number, Notice of IDR Initiation PDF, nip_notified_date and nip_notified_method (V28, V29, V65). Warning if NIP date is not the filed date (V66). Blocked before business day 31 (V43). idre_status set to Pending. | F9: markFiled(id, portalNumber, portalPdf, notice) | G9: status | H9: v3 (changed)
A10: Ready for US desk | B10: Return | C10: Returned | D10: US Member / Admin | E10: Reason from ReturnReason (V30) and details. | F10: returnDispute | G10: status | H10: v2
A11: Ready for US desk | B11: Edit | C11: Ready for US desk | D11: LB Member / Admin | E11: Allowed today; status does not change (Open questions). | F11: saveDispute, saveLine | G11: save | H11: v2
A12: Returned | B12: Fix and save | C12: Returned | D12: LB Member / Admin | E12: Reason shown at the top. | F12: saveDispute, saveLine | G12: save | H12: v2
... A35: (demo) | B35: Switch demo view | C35: - | D35: Admin | E35: demoUseLebanonView / demoUseUsView / demoUseAdminView set your own role on Users; the admin who switched away can switch back. | F35: DemoData.gs | G35: user | H35: v4

Sheet Roles & permissions
A1: Function / screen | B1: Area | C1: Admin | D1: LB Member | E1: US Member | F1: Not a member | G1: Server check (Code.gs) | H1: Notes
A2: doGet | B2: Open the app | C2: Yes | D2: Yes | E2: Yes | F2: "Access not granted" page | G2: me_()
A3: getBootstrap | B3: Read | C3: Yes | D3: Yes | E3: Yes | F3: No | G3: requireRole_() | H3: US Members start on Ready for US desk.
A4: listDisputes | B4: Read | C4: All | D4: All | E4: Ready + Filed only | F4: No | G4: requireRole_() + visibleTo_
A5: getDispute | B5: Read | C5: All | D5: All | E5: Ready + Filed only | F5: No | G5: requireRole_() + visibleTo_
A6: getInsights | B6: Read | C6: Yes | D6: Yes | E6: Yes | F6: No | G6: requireRole_()
A7: saveDispute | B7: Prepare | C7: Yes (not Filed) | D7: New, Draft, Returned | E7: No | F7: No | G7: requireRole_(Admin, LB) + assertCanEdit_ | H7: First save relinks staged files (own draft token only).
A8: saveLine | B8: Prepare | C8: Yes (not Filed) | D8: Draft, Returned | E8: No | F8: No | G8: requireRole_(Admin, LB) + assertCanEdit_
A9: saveLines | B9: Prepare | C9: Yes (not Filed) | D9: Draft, Returned | E9: No | F9: No | G9: requireRole_(Admin, LB) + assertCanEdit_
A10: deleteLine | B10: Prepare | C10: Yes (not Filed) | D10: Draft, Returned | E10: No | F10: No | G10: requireRole_(Admin, LB) + assertCanEdit_
A11: uploadFile | B11: Prepare | C11: Yes (not Filed; staged: own) | D11: Draft, Returned; staged: own | E11: No | F11: No | G11: requireRole_(Admin, LB) + assertCanEdit_ / assertOwnDraft_
A12: removeFile | B12: Prepare | C12: Yes (not Filed; staged: own) | D12: Draft, Returned; staged: own | E12: No | F12: No | G12: requireRole_(Admin, LB) + assertCanEdit_ / assertOwnDraft_
A13: finalizeDispute | B13: Send to US desk | C13: Yes (not Filed) | D13: Draft, Returned | E13: No | F13: No | G13: requireRole_(Admin, LB) + assertCanEdit_
A14: markFiled | B14: US desk | C14: Yes (Ready, window open) | D14: No | E14: Yes (Ready, window open) | F14: No | G14: requireRole_(Admin, US) + readyDispute_ + assertWindowOpen_
A15: returnDispute | B15: US desk | C15: Yes (Ready) | D15: No | E15: Yes (Ready) | F15: No | G15: requireRole_(Admin, US) + readyDispute_
A16: updateIdreSelection | B16: US desk | C16: Yes (Filed) | D16: No | E16: Yes (Filed) | F16: No | G16: requireRole_(Admin, US)
A17: adminListOptions / adminUpdateOption | B17: Admin -> Lists | C17: Yes | D17: No | E17: No | F17: No | G17: requireRole_(Admin)
A18: adminListUsers / adminSaveUser | B18: Admin -> Users | C18: Yes | D18: No | E18: No | F18: No | G18: requireRole_(Admin) | H18: Last active Admin protected.
A19: adminListEntities / adminSaveEntity | B19: Admin -> Billing entities | C19: Yes | D19: No | E19: No | F19: No | G19: requireRole_(Admin)
A20: adminGetConfig / adminSaveSetting / adminSaveField | B20: Admin -> Settings & fields | C20: Yes | D20: No | E20: No | F20: No | G20: requireRole_(Admin)
A21: setup / installTriggers | B21: Editor tools | C21: Yes | D21: No | E21: No | F21: Script owner only while no member is active | G21: requireEditorOrAdmin_()
A22: dailyMaintenance | B22: Editor tools | C22: Yes | D22: No | E22: No | F22: Time trigger | G22: requireEditorOrAdmin_(true)
A23: seedDemoData / clearDemoData | B23: Demo (DemoData.gs) | C23: Yes | D23: No | E23: No | F23: No | G23: requireEditorOrAdmin_()
A24: demoUseLebanonView / demoUseUsView / demoUseAdminView | B24: Demo (DemoData.gs) | C24: Yes | D24: Only the admin who switched away | E24: Only the admin who switched away | F24: No | G24: demoSetRole_ (DEMO_SWITCH_EMAIL)
A25: onEdit | B25: Sheet trigger | C25: Sheet editors | D25: - | E25: - | F25: - | G25: simple trigger | H25: Only clears caches.
A26: UI: copy desk, Start portal entry | B26: US desk screen | C26: Yes (Ready opens in the copy desk, with "Open in editor") | D26: No | E26: Yes | F26: No | G26: markFiled checks on the server
A27: UI: Admin screens | B27: Admin | C27: Yes | D27: No | E27: No | F27: No | G27: admin* functions

Sheet Data model
A1: Table | B1: Column | C1: Type | D1: Version | E1: Notes
A2: Disputes | B2: DisputeID | C2: text | D2: v2 | E2: Key. IDR-yymmdd-XXXX.
A3: Disputes | B3: Status | C3: text | D3: v2 | E3: Draft, Ready for US desk, Filed, Returned.
A4: Disputes | B4: Team | C4: text | D4: v4 (changed) | E4: Searchable with Add new; default @myteam.
A5: Disputes | B5: RcmSpecialist | C5: email | D5: v4 (changed) | E5: Was Owner: setup() renames the header; the app reads Owner until then.
A6: Disputes | B6: CreatedBy | C6: email | D6: v2
A7: Disputes | B7: CreatedAt | C7: timestamp | D7: v2
A8: Disputes | B8: UpdatedBy | C8: email | D8: v2
A9: Disputes | B9: UpdatedAt | C9: timestamp | D9: v2
A10: Disputes | B10: FolderUrl | C10: url | D10: v2 | E10: Drive folder.
A11: Disputes | B11: ConfirmationPdfUrl | C11: url | D11: v2
A12: Disputes | B12: ReadyAt | C12: timestamp | D12: v2
A13: Disputes | B13: FiledBy | C13: email | D13: v2
A14: Disputes | B14: FiledAt | C14: timestamp | D14: v2
A15: Disputes | B15: PortalDisputeNumber | C15: text | D15: v3 (changed) | E15: ^DISP-\d+$
A16: Disputes | B16: PortalPdfUrl | C16: url | D16: v2 | E16: Notice of IDR Initiation PDF.
A17: Disputes | B17: ReturnReason | C17: text | D17: v2 | E17: "reason: details".
A18: Disputes | B18: dispute_kind | C18: text | D18: v3 (changed) | E18: Derived (3 kinds).
A19: Disputes | B19: nip_notified_date | C19: date | D19: v3
A20: Disputes | B20: nip_notified_method | C20: text | D20: v3 | E20: NipMethod list.
A21: Disputes | B21: idre_final | C21: text | D21: v3
A22: Disputes | B22: idre_status | C22: text | D22: v3 | E22: IdreStatus list.
A23: Disputes | B23: q_prior_2022 | C23: radio | D23: v2 | E23: Field. See Fields.
A24: Disputes | B24: q_acting_as | C24: radio | D24: v3 (changed) | E24: Field. See Fields.
A25: Disputes | B25: tin | C25: text | D25: v3 (changed) | E25: Field. See Fields.
A26: Disputes | B26: npi | C26: text | D26: v3 (changed) | E26: Field. See Fields.
A27: Disputes | B27: q_plan_type | C27: select | D27: v3 (changed) | E27: Field. See Fields.
A28: Disputes | B28: fehb_enrollment_code | C28: text | D28: v3 | E28: Field. See Fields.
A29: Disputes | B29: on_start_date | C29: date | D29: v3 (changed) | E29: Field. See Fields.
A30: Disputes | B30: extension_reason | C30: radio | D30: v3 | E30: Field. See Fields.
A31: Disputes | B31: cooling_dispute_ref | C31: text | D31: v3 | E31: Field. See Fields.
A32: Disputes | B32: consent_waiver | C32: radio | D32: v3 (changed) | E32: Field. See Fields.
A33: Disputes | B33: dispute_type | C33: radio | D33: v3 | E33: Field. See Fields.
... A110: Files | B110: LineNo | C110: number | D110: v2 | E110: Saved line; blank while the line is not saved.
A111: Files | B111: Name | C111: text | D111: v2
A112: Files | B112: Url | C112: text | D112: v2
A113: Files | B113: FileId | C113: text | D113: v2
A114: Files | B114: UploadedBy | C114: text | D114: v2
A115: Files | B115: UploadedAt | C115: text | D115: v2
A116: Files | B116: Size | C116: number | D116: v3 | E116: Bytes.
A117: Files | B117: LineKey | C117: text | D117: v4 | E117: Client key of a line not saved yet; mapped to LineNo on save.
A118: Files | B118: SameClaim | C118: Yes/blank | D118: v4 | E118: Apply the QPA file to the claim's other lines when the line is saved.
A119: Options | B119: List | C119: text | D119: v2
A120: Options | B120: Key | C120: text | D120: v4 | E120: Stable id used by the rules (portal options); blank for ordinary values.
A121: Options | B121: Value | C121: text | D121: v2
A122: Options | B122: Label | C122: text | D122: v2
A123: Options | B123: Data | C123: JSON text | D123: v3 (changed) | E123: Payer profile; mergedInto on alias rows.
A124: Options | B124: Count | C124: text | D124: v2
A125: Options | B125: LastUsed | C125: text | D125: v2
A126: Options | B126: Source | C126: text | D126: v2
A127: Options | B127: Status | C127: text | D127: v2
A128: Options | B128: Sort | C128: number | D128: v4 | E128: Display order (strict lists); others ranked by use.
A129: Options | B129: Strict | C129: Yes/blank | D129: v4 | E129: Portal wording; the list never learns.
A130: Options | B130: AddedBy | C130: text | D130: v2
A131: Options | B131: AddedAt | C131: text | D131: v2
A132: Settings | B132: Key | C132: text | D132: v2 | E132: One row per setting (see below).
A133: Settings | B133: Value | C133: text | D133: v2 | E133: One row per setting (see below).
A134: Settings | B134: Note | C134: text | D134: v2 | E134: One row per setting (see below).
A135: Settings (rows) | B135: LearningMode | C135: setting | D135: v2 | E135: Default: On. On: new values typed by users are active at once (training). Off: they are added as Hidden until an admin activates them.
A136: Settings (rows) | B136: DefaultWindow | C136: setting | D136: v2 | E136: Default: 50. How many recent saved records the learned defaults look at.
A137: Settings (rows) | B137: DefaultShare | C137: setting | D137: v2 | E137: Default: 0.8. Share of those records (0 to 1) one value needs to become the default.
A138: Settings (rows) | B138: ComplexStates | C138: setting | D138: v3 | E138: Default: (empty). States on CMS's Complex State list, comma separated (like TX, NM). Lines with a location in the list need the state-specific eligibility attestation. Empty until confirmed.
A139: Settings (rows) | B139: MaxFileMb | C139: setting | D139: v4 | E139: Default: 45. Largest file the app accepts, in MB (Apps Script allows up to 45).
A140: Settings (rows) | B140: DisputeMaxMb | C140: setting | D140: v4 | E140: Default: 500. Total size of the files of one dispute that go to the portal, in MB (the portal allows 500).
A141: Settings (rows) | B141: GatewayFrom | C141: setting | D141: v4 | E141: Default: 2026-11-13. Date the web form moves into the IDR Gateway (sign-in), YYYY-MM-DD.
A142: Settings (rows) | B142: GatewayBannerUntil | C142: setting | D142: v4 | E142: Default: 2027-01-15. Last day the IDR Gateway banner shows on the copy desk (the form without sign-in ends that day), YYYY-MM-DD.
A143: Settings (rows) | B143: PortalSessionMinutes | C143: setting | D143: v4 | E143: Default: 60. The portal session times out after this many minutes of inactivity (copy desk timer).
... A146: Fields | B146: Page | C146: text | D146: v4 | E146: qual, dtype, init, noninit, lines, final, internal.
A147: Fields | B147: Section | C147: text | D147: v4
A148: Fields | B148: Order | C148: text | D148: v4 | E148: Order inside the section.
A149: Fields | B149: Key | C149: text | D149: v4
A150: Fields | B150: Label | C150: text | D150: v4
A151: Fields | B151: Help | C151: text | D151: v4
A152: Fields | B152: Type | C152: text | D152: v4
A153: Fields | B153: List | C153: text | D153: v4
A154: Fields | B154: Required | C154: text | D154: v4 | E154: Yes | No | Rule (portal logic in code; read-only).
A155: Fields | B155: Default | C155: text | D155: v4 | E155: Value or token @top, @me, @myteam.
A156: Fields | B156: DefaultMode | C156: text | D156: v4 | E156: Fixed | Learned | None.
A157: Fields | B157: Locked | C157: text | D157: v4 | E157: Yes/No.
A158: Fields | B158: Visible | C158: text | D158: v4 | E158: Yes/No (required fields stay visible).
A159: Fields | B159: Pattern | C159: text | D159: v4
A160: Fields | B160: PatternMessage | C160: text | D160: v4
A161: Fields | B161: CopyOrder | C161: text | D161: v4 | E161: Copy-desk order (line fields).
A162: Fields | B162: Notes | C162: text | D162: v4
A163: Users | B163: Email | C163: text | D163: v4 | E163: Key (lower case).
A164: Users | B164: Name | C164: text | D164: v4
A165: Users | B165: Role | C165: text | D165: v4 | E165: Admin | LB Member | US Member.
A166: Users | B166: Team | C166: text | D166: v4 | E166: Default team (@myteam).
A167: Users | B167: Active | C167: text | D167: v4 | E167: Yes/No (never delete).
A168: Users | B168: AddedBy | C168: text | D168: v4
A169: Users | B169: AddedAt | C169: text | D169: v4
A170: Users | B170: Notes | C170: text | D170: v4
A171: BillingEntities | B171: Name | C171: text | D171: v4 | E171: Key (legal name).
A172: BillingEntities | B172: ActingAs | C172: text | D172: v4 | E172: From the ActingAs list.
A173: BillingEntities | B173: TIN | C173: text | D173: v4
A174: BillingEntities | B174: NPI | C174: text | D174: v4
A175: BillingEntities | B175: GroupName | C175: text | D175: v4
A176: BillingEntities | B176: Addr1 | C176: text | D176: v4
A177: BillingEntities | B177: Addr2 | C177: text | D177: v4
A178: BillingEntities | B178: City | C178: text | D178: v4
...

Sheet API
A1: Function | B1: Visibility | C1: Roles | D1: Version | E1: Inputs | F1: Outputs | G1: Purpose
A2: doGet | B2: Public | C2: Any active member | D2: v4 (changed) | E2: (none) | F2: HtmlOutput | G2: App, or the "Access not granted" page.
A3: getBootstrap | B3: Public | C3: Any | D3: v4 (changed) | E3: withList (boolean) | F3: {user, role, me {email, name, team}, isAdmin, isUsDesk, isLb, people, schema, lists, aliases, defaults, learningMode, complexStates, today, status, kinds, gateway, rules, listFilter?, list?} | G3: First screen data. rules: maxLines, batchCapFrom, fileLimit, disputeFileLimit, maxFileMb, disputeMaxMb, portalFileCategories, sessionMinutes, warnMinutes, draftPrefix, msg. schema = built-in merged with Fields.
A4: listDisputes | B4: Public | C4: Any (US: Ready/Filed) | D4: v4 (changed) | E4: filter (status or "All") | F4: [{id, status, team, rcm, plan, kind, lines, updatedAt, updatedBy, returnReason, pdf, portalNumber, idreStatus, initiateBy, daysLeft, band, opens, extension}] | G4: Newest first. rcm replaces owner.
A5: getDispute | B5: Public | C5: Any (US: Ready/Filed) | D5: v3 | E5: id | F5: {dispute, lines, files, warnings, deadline}
A6: saveDispute | B6: Public | C6: Admin, LB | D6: v4 (changed) | E6: payload {id?, values, page, draftToken?} | F6: {id, bundle} | G6: First save relinks the files staged under draftToken (relinkDraft_).
A7: saveLine | B7: Public | C7: Admin, LB | D7: v4 (changed) | E7: id, lineNo?, values, lineKey? | F7: {lineNo, bundle} | G7: lineKey: files uploaded before the line was saved get its LineNo.
A8: saveLines | B8: Public | C8: Admin, LB | D8: v4 (changed) | E8: id, rows [{field: value, lineKey?}] | F8: {lineNos, bundle} | G8: Bulk paste; all rows checked first.
A9: deleteLine | B9: Public | C9: Admin, LB | D9: v2 | E9: id, lineNo | F9: bundle
A10: uploadFile | B10: Public | C10: Admin, LB | D10: v4 (changed) | E10: target (dispute id or draft token), category, lineNo, name, mimeType, data (base64), sameClaim, lineKey? | F10: {name, url, id, files} | G10: Staged in Drive Staging/<token> before the first save. MaxFileMb, DisputeMaxMb.
A11: removeFile | B11: Public | C11: Admin, LB | D11: v4 (changed) | E11: target, fileId, lineNo?, lineKey? | F11: files | G11: Works on staged files; a shared QPA file is only unlinked from the line.
A12: finalizeDispute | B12: Public | C12: Admin, LB | D12: v3 | E12: id | F12: {ok, problems?, warnings?, pdfUrl?, bundle?}
A13: markFiled | B13: Public | C13: Admin, US | D13: v3 | E13: id, portalNumber, portalPdf {name, mimeType, data}, notice {date, method} | F13: bundle | G13: Ready only; window open; method from NipMethod.
A14: updateIdreSelection | B14: Public | C14: Admin, US | D14: v3 | E14: id, idreFinal, idreStatus | F14: bundle | G14: Filed only.
A15: returnDispute | B15: Public | C15: Admin, US | D15: v4 (changed) | E15: id, reason, details | F15: true | G15: Ready only.
A16: getInsights | B16: Public | C16: Any | D16: v3 | E16: (none) | F16: {settings, addedThisWeek, lists, defaults, notices}
A17: adminListOptions | B17: Public | C17: Admin | D17: v4 (changed) | E17: list? | F17: list names with counts, or every value of a list | G17: BillingEntity and the private lists excluded.
A18: adminUpdateOption | B18: Public | C18: Admin | D18: v4 (changed) | E18: list, value, change {label?, status?, mergeInto?, value?, sort?} | F18: the list again | G18: value rewords in place keeping the Key.
A19: adminListUsers | B19: Public | C19: Admin | D19: v4 | E19: (none) | F19: {roles, users} | G19: Every member, active or not.
A20: adminSaveUser | B20: Public | C20: Admin | D20: v4 | E20: user {email, name?, role, team?, active?, notes?} | F20: {roles, users} | G20: Add or update; last active Admin protected.
A21: adminListEntities | B21: Public | C21: Admin | D21: v4 | E21: (none) | F21: {columns, actingAs, states, rows}
A22: adminSaveEntity | B22: Public | C22: Admin | D22: v4 | E22: entity {column: value}, originalName? | F22: the list again | G22: Add (no originalName) or update; renaming keeps the old name in Aliases.
A23: adminGetConfig | B23: Public | C23: Admin | D23: v4 | E23: (none) | F23: {settings [{key, value, effective, fallback, note}], fields, lists, warnings, defaultModes}
A24: adminSaveSetting | B24: Public | C24: Admin | D24: v4 | E24: key, value | F24: config | G24: Validated (settingProblem_).
A25: adminSaveField | B25: Public | C25: Admin | D25: v4 | E25: key, change {label?, help?, required?, default?, defaultMode?, locked?, visible?, order?} | F25: config | G25: Validated.
A26: dailyMaintenance | B26: Public (trigger) | C26: Admin or time trigger | D26: v4 | E26: (none) | F26: rows removed | G26: Runs cleanupStaging_.
A27: installTriggers | B27: Public (editor) | C27: Admin | D27: v4 | E27: (none) | F27: (none) | G27: One daily trigger at about 3 AM.
A28: onEdit | B28: Public (trigger) | C28: Sheet editors | D28: v4 (changed) | E28: e | F28: (none) | G28: Clears the cache of the edited tab: Options/BillingEntities, Settings, Fields, Users.
A29: setup | B29: Public (editor) | C29: Admin | D29: v4 (changed) | E29: (none) | F29: (none) | G29: Idempotent; tabs, columns, migrations, seeds, cleanupStaging_.
A30: seedDemoData / clearDemoData | B30: Public (DemoData.gs) | C30: Admin | D30: v4 (changed) | E30: (none) | F30: (none) | G30: 12 synthetic disputes IDR-DEMO-001 to 012 (012 prepared ahead).
A31: demoUseLebanonView / demoUseUsView / demoUseAdminView | B31: Public (DemoData.gs) | C31: Admin (or the admin who switched away) | D31: v4 (changed) | E31: (none) | F31: (none) | G31: Sets your own role on Users.
A32: requireRole_ / requireEditorOrAdmin_ / assertCanEdit_ / visibleTo_ | B32: Private | C32: - | D32: v4 | E32: roles / id, u | F32: member / throws | G32: Role checks (Roles & permissions).
A33: usersAll_ / activeUsers_ / userOf_ / me_ / clearUsersCache_ | B33: Private | C33: - | D33: v4 | E33: email | F33: member | G33: Users tab, cached 2 minutes.
A34: schema_ / baseSchema_ / applyFields_ / fieldRow_ / seedFields_ | B34: Private | C34: - | D34: v4 | E34: s, rows, warnings | F34: schema | G34: Fields merge and seed.
A35: listEntries_ / optValue_ / optKeyOf_ / isStrictList_ | B35: Private | C35: - | D35: v4 | E35: list, key | F35: value / key | G35: Options by Key.
... A41: validate_ / warnings_ / checkField_ / lineRules_ / duplicateLines_ | B41: Private | C41: - | D41: v3 | E41: - | F41: - | G41: Portal rules (Validation rules).

Sheet Backlog
A1: ID | B1: Source | C1: User story | D1: Priority | E1: Effort (S/M/L) | F1: Acceptance criteria | G1: Version
A2: B01 | B2: FR-1 | C2: As a preparer, I pick the payer from a list so the contact fields fill in. | D2: Do first | E2: M | F2: 124 payers seeded; 4 with profiles. Only empty fields filled. New payers learned. | G2: v3 (changed)
A3: B02 | B3: FR-2 | C3: As a preparer, I pick our billing entity so acting-as, TIN, NPI, group name and contact fill in. | D3: Do first | E3: S | F3: 24 entities on the BillingEntities tab; ActingAs guess with Confirmed No until saved. | G3: v3 (changed)
A4: B03 | B4: FR-3 | C4: As a preparer, I see smart defaults I can change. | D4: Do first | E4: S | F4: No, No, batched, Emergency, POS 23, TX (locked), third party No pre-selected. | G4: v3 (changed)
A5: B04 | B5: FR-4 | C5: As a preparer, I see the open negotiation timing band. | D5: Do first | E5: M | F5: Start date = day 1. b < 31: Ready allowed with "Filing window opens <date>", US desk blocked, "Not open yet" group; 31–34 shows the window; > 34 needs an extension reason. | G5: v3 (changed)
A6: B05 | B6: FR-5 | C6: As a preparer, I am stopped when a dispute is not eligible. | D6: Do first | E6: S | F6: Yes on prior-2022 or consent blocks Ready. | G6: v2
A7: B06 | B7: FR-6 | C7: As a preparer, I pick the Health Plan Type from the 7 portal options. | D7: Do first | E7: S | F7: Strict dropdown, exact text; FEHB shows the enrollment code; plan_role derived. | G7: v3 (changed)
A8: B07 | B8: FR-7 | C8: As a preparer, I cannot repeat a line already filed. | D8: Do first | E8: M | F8: V56 within the dispute; V57 across Ready/Filed disputes, override only with an extension reason. | G8: v3 (changed)
A9: B08 | B9: FR-8 | C9: As a preparer, I cannot batch lines more than 30 business days apart. | D9: Do first | E9: M | F9: V37 blocks unless the cooling off reason is set. | G9: v3 (changed)
A10: B09 | B10: FR-9 | C10: As a preparer, I duplicate a line and change only what differs. | D10: Do next | E10: S | F10: Duplicate line copies all fields; then V56 asks for a change. | G10: v2
A11: B10 | B11: FR-10 | C11: As a preparer, I pick service codes, modifiers and POS codes from lists. | D11: Do first | E11: S | F11: 373 codes; formats V49–V51. | G11: v3 (changed)
A12: B11 | B12: FR-11 | C12: As the US desk, I pick a return reason from a list. | D12: Do next | E12: S | F12: ReturnReason combo. | G12: v2
... A62: B61 | B62: Spec v4 | C62: As an admin, I have a configuration guide. | D62: Do first | E62: S | F62: Sheet "Configuration guide". | G62: v4

Sheet Open questions
A1: ID | B1: Topic | C1: Question | D1: Owner | E1: Status | F1: Answer / note
A2: Q01 | B2: US desk users | C2: Who are the LB Members and US Members, and their teams? Add them on the Users tab (Admin -> Users). Each US Member needs an IDR Gateway account joined to our organization before 2027-01-15. | D2: Business | E2: Open
A3: Q02 | B3: Admins | C3: Who are the Admins (Users tab, Role Admin)? At least one active Admin is always kept. | D3: Business | E3: Open
A4: Q03 | B4: Health Plan Type | C4: Which options does the portal show? | D4: US desk | E4: Answered (v3) | F4: Guide v15 lists 7 options; seeded as a strict list.
A5: Q04 | B5: Bundled disputes | C5: When do we use a bundled dispute? | D5: Business | E5: Answered (v3) | F5: Single dispute + bundled Yes; line 1 Bundled, lines 2+ Component (guide 1.6.1.2).
A6: Q05 | B6: Batching rules | C6: Which batching rules should the Studio check? | D6: Business | E6: Answered (v3) | F6: 2–50 lines, dates within 30 business days, DOS before ON start (guide 1.6.1.3).
A7: Q06 | B7: Teams and RCM Specialists | C7: Should Team and RCM Specialist have seed values, or only be learned ("Add new")? Should the RCM Specialist default (@me) also apply to Admins? | D7: Business | E7: Open
A8: Q07 | B8: Modifiers | C8: Is Service Code Modifier(s) optional? | D8: US desk | E8: Answered (v3) | F8: Yes: no asterisk in guide v15; 0–4 two-character codes.
A9: Q08 | B9: Editing Ready disputes | C9: Should an edit to a Ready dispute move it back to Draft? | D9: Business | E9: Open
A10: Q09 | B10: Data quality | C10: DISP-7998956 lines 2–11 have no claim number, date, QPA, POS or location. It is also a "Single dispute" with 11 lines, which v3 rules would block. Was it filed that way? | D10: US desk | E10: Open
A11: Q10 | B11: Deadline time zone | C11: Which time zone sets "today" for the timing bands (Central)? | D11: Business | E11: Open
A12: Q11 | B12: Holidays | C12: Confirm the federal holiday list for 2026 and 2027. Who adds 2028? | D12: IT | E12: Open
A13: Q12 | B13: Learning mode | C13: When does training end and LearningMode switch to Off? | D13: Business | E13: Open
A14: Q13 | B14: Default share | C14: Is 0.8 over the last 50 records right? | D14: Business | E14: Open
A15: Q14 | B15: Plan role | C15: Which plan role is the default? | D15: US desk | E15: Answered (v3) | F15: Derived from Health Plan Type (FEHB, Individual, else Group health plan). Confirm the mapping for "No Plan/Issuer Response", Church plan and governmental plans.
A16: Q15 | B16: Billing entities | C16: Are there more billing entities? | D16: Business | E16: Answered (v3) | F16: 24 entities on the BillingEntities tab.
A17: Q16 | B17: Payer fax | C17: Should we collect payer fax numbers? | D17: Business | E17: Open | F17: Optional on the portal.
A18: Q17 | B18: Options Note column | C18: Keep the Note column, or move its text into Label? | D18: IT | E18: Open
A19: Q18 | B19: Complex State list | C19: Is Texas on the CMS Complex State list? Which states go into Settings.ComplexStates? Today the setting is empty, so state_attest never shows. | D19: Business / Compliance | E19: Open
A20: Q19 | B20: Entity typos | C20: Confirm the legal spelling (not changed in the seed): "Deerfield plains, LLC" – Lower-case "plains" (Deerfield Plains?).; "Silver choice, PLLC" – Lower-case "choice" (Silver Choice?).; "Cedar Physcians, PLLC" – "Physcians" (Physicians?).; "WRFER University, LLC" – "WRFER" vs "WFRER" in WFRER Denton and WFRER Cooper.; "RSER Benbrook, LLC" – "RSER" (compare TotalCare ER Benbrook, PLLC). | D20: Business | E20: Open
A21: Q20 | B21: Timing count | C21: Does the portal count the open negotiation start date as business day 1? | D21: US desk / IT | E21: Answered (v3) | F21: Yes. b counts both days. 09/01/2026 -> ON ends 10/14, window 10/15–10/20; 09/02/2026 -> ON ends 10/15, window 10/16–10/21. Matches the 2 real filings (10/15 and 10/16).
A22: Q21 | B22: Entity profiles | C22: We need TIN, NPI, hospital/facility/group name, address, email and phone for the 22 entities with no profile, and a group name for Silver Alliance, LLC (now required). Confirm acting_as for all 24 (guessed from PLLC/LLC). | D22: Business | E22: Open
A23: Q22 | B23: Payer contact details | C23: We need IDR mailing address, email and phone (fax optional) for 120 of the 124 payers (only UMR, UHC, BCBS and Cigna have them). | D23: Business | E23: Open
A24: Q23 | B24: GEHA name | C24: "GEHA (Government Employees Health Association, Inc.)" has parentheses, which the portal rejects in name fields. Store it as "GEHA Government Employees Health Association, Inc."? | D24: Business | E24: Open
A25: Q24 | B25: Payer duplicates | C25: BENEFITS HEALTHSMART vs Healthsmart; UHSS vs UHC Shared Services; Allegiance vs "Allegiance Benefi Plan Management, Inc"; Medica vs Medica Insurance Company; healthnet. Same or different? Also possible typos: "Professional Benefit Administators", "Concord Hospital Entreprises". | D25: Business | E25: Open
A26: Q25 | B26: Third evidence type | C26: Guide 1.1 also lists "documents to confirm the certified IDR entity request to re-submit the dispute" for late filings, but the portal shows only 2 extension reasons. Do we need it? | D26: US desk | E26: Open
A27: Q26 | B27: Address line 2 | C27: Guide v15 shows one Mailing Address line. The Studio keeps "Mailing Address Line 2" from v2. Does the portal still show a second line? | D27: US desk | E27: Open
A28: Q27 | B28: Billing entity first | C28: q_acting_as, TIN and NPI (page 1) come from the billing entity picked on page 3. Should the entity picker also show on page 1? | D28: Business / UX | E28: Open
A29: Q28 | B29: v3 preparers as LB Members | C29: setup() adds everyone who created or updated a non-demo dispute in v3 as an active LB Member (in v3 the whole Workspace could prepare). Is that wanted, or should an admin approve each one first? | D29: Business | E29: Open | F29: Check Admin -> Users after the upgrade.
A30: Q29 | B30: Fields labels seeded vs blank | C30: setup() seeds each Fields row with the built-in label, so a reworded label in a later code version does not replace it. Should Label (and Help) be seeded blank, so the code text applies until an admin overrides it? | D30: IT / Business | E30: Open | F30: Today: delete the row and run setup again.
A31: Q30 | B31: Admin and Ready disputes | C31: Admins open Ready disputes in the copy desk (with "Open in editor") and may still edit them. Should an Admin edit move a Ready dispute back to Draft, or be logged as a change after review (see Q08)? | D31: Business | E31: Open
A32: Q31 | B32: Final saveLine/uploadFile check | C32: A last small fix to the lineNo checks of saveLine and uploadFile may land after this workbook (no signature change). V74 describes the rule as built on 2026-10-26. | D32: IT | E32: Answered | F32: Done: saveLine/saveLines refuse a lineNo that is not a saved line of the dispute; uploadFile refuses a lineNo that is not a saved line (drafts included). The staged lineKey path is unchanged.

Sheet Guide changes
A1: Guide section | B1: Topic | C1: What the guide says (v15) | D1: What changed in the Studio (v3/v4) | E1: Rule / item IDs | F1: Change type
A2: Introduction | B2: Transition to the IDR Gateway | C2: From 2026-11-13 the web form moves into the Gateway; the form without sign-in ends 2027-01-15; parties need a Gateway account. | D2: README, copy-desk banner until 2027-01-15, Workflow calendar rows; US desk users need Gateway accounts (Q01). | E2: B46 | F2: New
A3: Important Information | B3: Timing | C3: Initiate within 4 business days after the 30-business-day open negotiation period. | D3: Timing bands b < 31 / 31–34 / > 34. | E3: V13, V14, V43 | F3: Changed
A4: Important Information | B4: Duplicate line items | C4: No repeat of Claim Number + Date of Service + Service Code + Modifier(s), except cooling-off ineligible closures or an approved extension. | D4: Blocking duplicate check in and across disputes; override with an extension reason. | E4: V56, V57 | F4: New
A5: Important Information | B5: Resubmission form | C5: Improperly batched/bundled items use "Notice of IDR Initiation – Resubmission". | D5: Out of scope; README note. | E5: - | F5: Info
A6: Important Information | B6: Dates of service | C6: DOS before the ON start date; batched DOS within 30 business days unless cooling off applies. | D6: Blocking checks. | E6: V47, V37 | F6: New
A7: 1.1 | B7: Before starting | C7: Evidence per ON start date; > 34 business days needs extension evidence; one session, 60-minute timeout, nothing saved on exit. | D7: Batched evidence reminder; extension uploads; 60-minute timer on the copy desk. | E7: V24, V44–V46, Workflow | F7: Changed
A8: 1.1 | B8: IDR State list | C8: Check which states have their own processes. | D8: Complex State attestation via Settings.ComplexStates. | E8: V61, Q18 | F8: New
A9: 1.2 | B9: Access | C9: Sign in, Disputes > Start a Dispute. Initiating party information shows first. | D9: Studio page 3 = initiating party, page 4 = non-initiating party. | E9: Fields | F9: Changed
A10: 1.3 (2) | B10: Prior to 1/1/2022 | C10: Yes shows an alert. | D10: Hard stop (unchanged). | E10: V11 | F10: Existing
A11: 1.3 (3) | B11: I am (or I am acting on behalf of) a | C11: 6 options; no auto-fill from the Gateway organization. | D11: Only provider or facility; locked chip from the billing entity. | E11: V39 | F11: Changed
A12: 1.3 (3) | B12: Not eligible coverage | C12: Medicare, Medicaid, CHIP, TRICARE, health care sharing ministry. | D12: Info text under Health Plan Type. | E12: V41 | F12: New
... A45: 1.9 | B45: Who files | C45: The initiating party submits and notifies the non-initiating party. | D45: v4: only US Members and Admins can mark filed, return or record the IDRE selection (server role check). | E45: V69, V72 | F45: Config (v4)
